Workbook

Sheet Executive Summary (GDT Project)
A1: EXECUTIVE SUMMARY - MRS PATHFINDER GDT RAILCAR PROPOSAL
A2: Exchange Rate: | B2: USD 1.00 = BRL 5.16
A3: Profit Margin (%): | B3: 0.45 | C3: <- editable input. Change this to update the sale price table below.
A5: 1) COST / PURE BREAKEVEN (initial Pathfinder price, no margin)
A6: Project Module | B6: Cost BRL (Excl. Taxes) | C6: Cost USD (Excl. Taxes) | D6: Cost BRL (Incl. Taxes) | E6: Cost USD (Incl. Taxes) | F6: % of Total
A7: 1. Equipment & Components (BOM Pathfinder + SKID) | B7: =SUM('Final Cost List'!L2:L163) -> 2137279.5 | C7: 350000 | D7: =SUM('Final Cost List'!M2:M163) -> 2676282.9 | E7: =SUM('Final Cost List'!K2:K163) -> 518659.48 | F7: =B7/$B$9 -> 0.75122209
A8: 2. Adaptation, Container & Labor (Rollup GDT) | B8: =SUM('GDT Integration and Assembly'!C2:C18) -> 707790.6 | C8: =SUM('GDT Integration and Assembly'!D2:D18) -> 137168.72 | D8: =SUM('GDT Integration and Assembly'!E2:E18) -> 886289.26 | E8: =SUM('GDT Integration and Assembly'!F2:F18) -> 171761.48 | F8: =B8/$B$9 -> 0.24877791
A9: TOTAL CONSOLIDATED GDT RAILCAR PROJECT (COST) | B9: =SUM(B7:B8) -> 2845070.1 | C9: =SUM(C7:C8) -> 487168.72 | D9: =SUM(D7:D8) -> 3562572.2 | E9: =SUM(E7:E8) -> 690420.96 | F9: 1
A11: 2) SALE PRICE WITH PROFIT MARGIN (driven by cell B3)
A12: Project Module | B12: Sale Price BRL (Excl. Taxes) | C12: Sale Price USD (Excl. Taxes) | D12: Sale Price BRL (Incl. Taxes) | E12: Sale Price USD (Incl. Taxes) | F12: % of Total
A13: 1. Equipment & Components (BOM Pathfinder + SKID) | B13: =B7*(1+$B$3) -> 3099055.3 | C13: =C7*(1+$B$3) -> 507500 | D13: =D7*(1+$B$3) -> 3880610.2 | E13: =E7*(1+$B$3) -> 752056.24 | F13: =B13/$B$15 -> 0.75122209
A14: 2. Adaptation, Container & Labor (Rollup GDT) | B14: =B8*(1+$B$3) -> 1026296.4 | C14: =C8*(1+$B$3) -> 198894.65 | D14: =D8*(1+$B$3) -> 1285119.4 | E14: =E8*(1+$B$3) -> 249054.15 | F14: =B14/$B$15 -> 0.24877791
A15: TOTAL CONSOLIDATED GDT RAILCAR PROJECT (SALE PRICE) | B15: =SUM(B13:B14) -> 4125351.7 | C15: =SUM(C13:C14) -> 706394.65 | D15: =SUM(D13:D14) -> 5165729.6 | E15: =SUM(E13:E14) -> 1001110.4 | F15: 1

Sheet Final Cost List
A1: Part Number | B1: Description | C1: System | D1: SubSystem | E1: Weight (lbs) | F1: Quantity | G1: BOM Price (USD Unit) | H1: Final Unit Price USD (Excluding Taxes) | I1: Final Total Price USD (Excluding Taxes) | J1: Final Unit Price USD (Including Taxes) | K1: Final Total Price USD (Including Taxes) | L1: Total Price BRL (Excluding Taxes) | M1: Total Price BRL (Including Taxes) | N1: PAC Price (BRL Unit) | O1: BOM Price (USD Unit) | P1: Cost Source | Q1: Status / Notes | S1: Simple Item Category | T1: Nationalization Status | U1: Import Scenario (BOM+TP+Freight+Duty, BRL Incl. Tax) | V1: Nationalized/PAC Price (BRL Incl. Tax) | W1: Cheaper Option
A2: 41A296352CMP437 | B2: Dual Processor Module (DPM)+ LXA (Distributed Power Radio) | C2: Controls (MCA, train control, er etc) | D2: LXA | E2: 10 | F2: 1 | G2: 63100.819 | H2: 96312.869 | I2: 96312.869 | J2: 120602.14 | K2: 120602.14 | L2: 496974.41 | M2: 622307.04 | P2: Imported BOM (USA) | Q2: TP included; international freight updated to 9%
A3: 37495P | B3: KIT ETMS VIRGIN TRAINS FEC EVO44 | C3: PTC | D3: PTC KIT MASTER | F3: 1 | G3: 28529 | H3: 43544.757 | I3: 43544.757 | J3: 54526.368 | K3: 54526.368 | L3: 224690.95 | M3: 281356.06 | P3: Imported BOM (USA) | Q3: Direct supplier purchase; TP excluded; international freight 9%
A4: 84A222059P5 | B4: BATTERIES | C4: Power | D4: POWER | E4: 2476 | F4: 2 | G4: 15685.42 | H4: 20427.624 | I4: 40855.249 | J4: 25579.294 | K4: 51158.589 | L4: 210813.08 | M4: 263978.32 | P4: Imported BOM (USA) | Q4: TP included; international freight updated to 9%
A5: 41A296352LUG24 | B5: CSX Antenna Enclosure Arrangement | C5: Connectivity | D5: ANTENNA KIT Master | F5: 1 | G5: 30000 | H5: 39069.96 | I5: 39069.96 | J5: 48923.065 | K5: 48923.065 | L5: 201600.99 | M5: 252443.02 | P5: Imported BOM (USA) | Q5: TP included; international freight updated to 9%
A6: 84A215295P62 | B6: Pneumatic Brake Control System (Including lament and control portions) Includes EM EAB Control Functionality | C6: Air | D6: Fastbrake | E6: 296 | F6: 1 | G6: 23409.1 | H6: 35730.084 | I6: 35730.084 | J6: 44740.902 | K6: 44740.902 | L6: 184367.23 | M6: 230863.05 | P6: Imported BOM (USA) | Q6: Direct supplier purchase; TP excluded; international freight 9%
A7: 41A296352DNP37 | B7: RADIO PRAD PTC RADIO | C7: PTC | D7: PTC | E7: 21.2 | F7: 1 | G7: 20000 | H7: 26046.64 | I7: 26046.64 | J7: 32615.377 | K7: 32615.377 | L7: 134400.66 | M7: 168295.34 | P7: Imported BOM (USA) | Q7: Direct supplier purchase; TP excluded; international freight 9%
A8: 17FM878A6 | B8: NIO 2.0 | C8: Controls (MCA, train control, er etc) | D8: MCA | E8: 19 | F8: 3 | G8: 5176.9118 | H8: 6742.0579 | I8: 20226.174 | J8: 8442.3465 | K8: 25327.039 | L8: 104367.06 | M8: 130687.52 | P8: Imported BOM (USA) | Q8: TP included; international freight updated to 9%
A9: L7000083-900 | B9: Wireless Communications Management Module, Gen 3 (WCM3)​ | C9: Controls (MCA, train control, er etc) | D9: TRAIN CONTROL | E9: 5 | F9: 2 | G9: 5000 | H9: 7631.6655 | I9: 15263.331 | J9: 9556.3054 | K9: 19112.611 | L9: 78758.788 | M9: 98621.072 | P9: Imported BOM (USA) | Q9: Made by GET; retained for GET impact analysis | S9: Wire/Cable | T9: Low confidence - no comparable PAC item found | U9: 98621.072 | V9: 7609.408 | W9: PAC/National is cheaper (by R$ 91,011.66)
A10: 84A237085AEP121 | B10: 8 Slot ACC Chassis for MCA w/ i7 HPEAP and SMM2 Cards | C10: Controls (MCA, train control, er etc) | D10: TRAIN CONTROL | E10: 20 | F10: 1 | G10: 8000 | H10: 12210.665 | I10: 12210.665 | J10: 15290.089 | K10: 15290.089 | L10: 63007.031 | M10: 78896.858 | P10: Imported BOM (USA) | Q10: TP included; international freight updated to 9%
A11: 17FL472A2 | B11: TMC PANEL | C11: SKID Assembly | D11: SKID (Skid) | E11: 45 | F11: 1 | I11: 11326.967 | J11: 14183.531 | K11: 14183.531 | L11: 58447.152 | M11: 73187.017 | N11: 58447.152 | P11: PAC (Brazil BRL) | Q11: Direct supplier purchase; TP excluded; international freight 9%
A12: 17KC108E28 | B12: MASTER CONTROLLER | C12: Controls (MCA, train control, er etc) | D12: TRAIN CONTROL | E12: 57 | F12: 1 | G12: 5877.102 | I12: 9464.1997 | J12: 11850.989 | K12: 11850.989 | L12: 48835.27 | M12: 61151.102 | P12: GET | Q12: TP included; international freight updated to 9%
A13: 84A215295P73 | B13: Air Brake Handle Assembly (AAR Console) | C13: Air | D13: Fastbrake | E13: 17.5 | F13: 1 | G13: 5702.83 | H13: 8704.4182 | I13: 8704.4182 | J13: 10899.597 | K13: 10899.597 | L13: 44914.798 | M13: 56241.921 | P13: Imported BOM (USA) | Q13: Direct supplier purchase; TP excluded; international freight 9%
A14: 17FM868B2 | B14: SNIO | C14: Controls (MCA, train control, er etc) | D14: MCA | E14: 11 | F14: 1 | G14: 4150.9559 | H14: 5405.9227 | I14: 5405.9227 | J14: 6769.2496 | K14: 6769.2496 | L14: 27894.561 | M14: 34929.328 | P14: Imported BOM (USA) | Q14: Direct supplier purchase; TP excluded; international freight 9%
A15: 41A296352DNP55 | B15: VOICE RADIO RITRON | C15: Connectivity | D15: VOICE RADIO | E15: 16.7 | F15: 1 | G15: 3933 | H15: 5122.0718 | I15: 5122.0718 | J15: 6413.8139 | K15: 6413.8139 | L15: 26429.89 | M15: 33095.28 | P15: Imported BOM (USA) | Q15: TP included; international freight updated to 9%
A16: 32613P | B16: KIT ETMS AXLE INTERFACE FOR WPart Number 29266P | C16: PTC | D16: PTC | E16: 10 | F16: 1 | G16: 2981.71 | H16: 4551.0827 | I16: 4551.0827 | J16: 5698.8263 | K16: 5698.8263 | L16: 23483.587 | M16: 29405.944 | P16: Imported BOM (USA) | Q16: Direct supplier purchase; TP excluded; international freight 9%
A17: 17FH40X1 | B17: LPS 17FH40 (COMMON LOGIC POWER SUPPLY) (5v, 15v, 19v, 24v) | C17: POWER | D17: POWER SUPPLY | E17: 40 | F17: 1 | I17: 2915.0271 | J17: 3650.1717 | K17: 3650.1717 | L17: 15041.54 | M17: 18834.886 | N17: 15041.54 | P17: PAC (Brazil BRL) | Q17: Brazilian factory PAC price (local Brazilian cost)
A18: 41D758679BJG16 84D704379AFG1 | B18: EC Part NumberL ASM | C18: Power | D18: Circuit Breaker | F18: 1 | G18: 1572.36 | I18: 2532.0522 | J18: 3170.6138 | K18: 3170.6138 | L18: 13065.389 | M18: 16360.367 | P18: GET | Q18: Made by GET; retained for GET impact analysis
A19: 41B546155P2 | B19: Horn | C19: Controls (MCA, train control, er etc) | D19: TRAIN CONTROL | E19: 10 | F19: 1 | G19: 1891.99 | H19: 2463.9991 | I19: 2463.9991 | J19: 3085.3983 | K19: 3085.3983 | L19: 12714.235 | M19: 15920.655 | P19: Imported BOM (USA) | Q19: Brazilian factory PAC price (local Brazilian cost)
B20: Ditchlight Control Box (SMART BOX-V3-DLC ) | C20: Controls (MCA, train control, er etc) | D20: TRAIN CONTROL | E20: 5 | F20: 2 | G20: 800 | H20: 1221.0665 | I20: 2442.133 | J20: 1529.0089 | K20: 3058.0177 | L20: 12601.406 | M20: 15779.372 | P20: Imported BOM (USA) | Q20: Brazilian factory PAC price (local Brazilian cost)
B21: LED Ditch Light | C21: Controls (MCA, train control, er etc) | D21: TRAIN CONTROL | E21: 2 | F21: 4 | G21: 375 | H21: 572.37491 | I21: 2289.4997 | J21: 716.72291 | K21: 2866.8916 | L21: 11813.818 | M21: 14793.161 | P21: Imported BOM (USA) | Q21: TP included; international freight updated to 9%
A22: 17FM839B1 | B22: PANEL ASM CFD - Thin Client Display | C22: Controls (MCA, train control, er etc) | D22: MCA | F22: 1 | I22: 2248.7824 | J22: 2815.9058 | K22: 2815.9058 | L22: 11603.717 | M22: 14530.074 | N22: 11603.717 | P22: PAC (Brazil BRL) | Q22: Made by GET; retained for GET impact analysis
A23: 17FM839A3 | B23: TCD (Thin Client Display) | C23: SKID Assembly | D23: SKID (Skid) | F23: 1 | I23: 2248.7824 | J23: 2815.9058 | K23: 2815.9058 | L23: 11603.717 | M23: 14530.074 | N23: 11603.717 | P23: PAC (Brazil BRL) | Q23: Direct supplier purchase; TP excluded; international freight 9%
A24: 84A201003DAP1 | B24: ELECTRIC Bell | C24: Controls (MCA, train control, er etc) | D24: TRAIN CONTROL | F24: 1 | I24: 1839.4297 | J24: 2303.3179 | K24: 2303.3179 | L24: 9491.4571 | M24: 11885.12 | N24: 9491.4571 | P24: PAC (Brazil BRL) | Q24: TP included; international freight updated to 9%
A25: 17FB193E2F | B25: GET Card | C25: GET | D25: GET Card | F25: 1 | I25: 1792.8535 | J25: 2244.9956 | K25: 2244.9956 | L25: 9251.1239 | M25: 11584.177 | N25: 9251.1239 | P25: PAC (Brazil BRL) | Q25: Made by GET; retained for GET impact analysis
A26: 84A215295P3 | B26: POU-to-Handle cable 18' length | C26: Air | D26: Fastbrake | F26: 1 | G26: 1036.89 | H26: 1582.6395 | I26: 1582.6395 | J26: 1981.7675 | K26: 1981.7675 | L26: 8166.42 | M26: 10225.92 | P26: Imported BOM (USA) | Q26: TP included; international freight updated to 9% | S26: Wire/Cable | T26: Low confidence - PAC family match, different length | U26: 10225.92 | V26: 8409.4743 | W26: PAC/National is cheaper (by R$ 1,816.45)
A27: 41B566322ACG1 | B27: TRAINLINE RESISTOR PANEL | C27: SKID Assembly | D27: Controls (MCA, train control, er etc) | F27: 1 | I27: 1306.7417 | J27: 1636.2907 | K27: 1636.2907 | L27: 6742.7873 | M27: 8443.2599 | N27: 6742.7873 | P27: GET | Q27: TP included; international freight updated to 9%
A28: 41A296304DDP4 | B28: G-RECTIFIER POWER BLOCK | C28: SKID Assembly | D28: Controls (MCA, train control, er etc) | F28: 20 | I28: 1264.4303 | J28: 79.16543 | K28: 1583.3086 | L28: 6524.4601 | M28: 8169.8724 | N28: 326.22301 | P28: PAC (Brazil BRL) | Q28: Brazilian factory PAC price (local Brazilian cost)
A29: RCCR-RMTCBL-RA-CUSTOM | B29: VOICE RADIO RITRON CABLE,REMOTE,RR-225/XXX, RCCR,RIGHT ANGLE,19-PIN,FLAME RETARDANT | C29: Connectivity | D29: VOICE RADIO | F29: 1 | G29: 761 | H29: 991.07465 | I29: 991.07465 | J29: 1241.0151 | K29: 1241.0151 | L29: 5113.9452 | M29: 6403.6379 | P29: Imported BOM (USA) | Q29: Brazilian factory PAC price (local Brazilian cost) | S29: Wire/Cable | T29: Low confidence - no comparable PAC item found | U29: 6403.6379 | V29: 3569.0421 | W29: PAC/National is cheaper (by R$ 2,834.60)
A30: 41C663693G1 | B30: PANEL CPF | C30: Power | D30: POWER | F30: 1 | I30: 924.61033 | J30: 1157.789 | K30: 1157.789 | L30: 4770.9893 | M30: 5974.1915 | N30: 4770.9893 | P30: GET | Q30: Brazilian factory PAC price (local Brazilian cost)
A31: 41A296352PTP306/41A296352PTP122 | B31: Assembled Air Manifold (Contains 3 pressure sensors mounted in appropriate locations on Air Manifold.) | C31: PTC | D31: PTC | F31: 1 | G31: 595.7889 | H31: 909.37232 | I31: 909.37232 | J31: 1138.7081 | K31: 1138.7081 | L31: 4692.3612 | M31: 5875.734 | P31: Imported BOM (USA) | Q31: Brazilian factory PAC price (local Brazilian cost)
A32: 84A232147P1 | B32: KNOB HLD DWN with washer and screw | C32: Controls (MCA, train control, er etc) | D32: TRAIN CONTROL | F32: 30 | I32: 741.13821 | J32: 30.934895 | K32: 928.04685 | L32: 3824.2732 | M32: 4788.7217 | N32: 127.47577 | P32: PAC (Brazil BRL) | Q32: Brazilian factory PAC price (local Brazilian cost)
A33: 32447P | B33: ASY CABLE WHEEL TACH AC EVO/SD70 ACE | C33: PTC | D33: PTC | F33: 1 | G33: 411.22 | H33: 627.6587 | I33: 627.6587 | J33: 785.94878 | K33: 785.94878 | L33: 3238.7189 | M33: 4055.4957 | P33: Imported BOM (USA) | Q33: Calculated with TP (17.2%) + International Freight (15%) + Import Duty (16%) + Domestic Freight (3%) | Qtd=1.0 | S33: Wire/Cable | T33: High confidence PAC match (exact desc, PN 29707P) - not yet applied | U33: 4055.4957 | V33: 373.6982 | W33: PAC/National is cheaper (by R$ 3,681.80)
A34: 41A296352PTP10/319/34 | B34: VALVE Part NumberEUMATIC NC/CO (Penalty Magnet Valve) Graham-White 812-142 | C34: PTC | D34: PTC | F34: 1 | G34: 404.6239 | H34: 617.59085 | I34: 617.59085 | J34: 773.34191 | K34: 773.34191 | L34: 3186.7688 | M34: 3990.4443 | P34: Imported BOM (USA) | Q34: Brazilian factory PAC price (local Brazilian cost)
A35: 84A201176P1 | B35: Pathfinder Control Unit Connector (MU Plug) | C35: Controls (MCA, train control, er etc) | D35: TRAIN CONTROL | F35: 2 | I35: 573.97817 | J35: 359.36524 | K35: 718.73049 | L35: 2961.7273 | M35: 3708.6493 | N35: 1480.8637 | P35: PAC (Brazil BRL) | Q35: Calculated with TP (17.2%) + International Freight (15%) + Import Duty (16%) + Domestic Freight (3%) | Qtd=1.0 | S35: Connector/Plug | T35: Already nationalized (PAC) | U35: 4406.427 | V35: 3708.6493 | W35: PAC/National is cheaper (by R$ 697.78)
A36: 84A201150ACP2 | B36: CROSSING BELL PUSH BUTTON SWITCH | C36: Controls (MCA, train control, er etc) | D36: TRAIN CONTROL | F36: 1 | I36: 551.04203 | J36: 690.01005 | K36: 690.01005 | L36: 2843.3769 | M36: 3560.4519 | N36: 2843.3769 | P36: PAC (Brazil BRL) | Q36: Calculated with TP (17.2%) + International Freight (15%) + Import Duty (16%) + Domestic Freight (3%) | Qtd=1.0
A37: 17FH37A6 | B37: RPS Power Panel - Radio Power Supply - 15V | C37: Controls (MCA, train control, er etc) | D37: MCA | F37: 1 | I37: 491.25711 | J37: 615.14789 | K37: 615.14789 | L37: 2534.8867 | M37: 3174.1631 | N37: 2534.8867 | P37: PAC (Brazil BRL) | Q37: Brazilian factory PAC price (local Brazilian cost)
A38: 41A240644P2 | B38: HORN MAGNET VALVE | C38: Controls (MCA, train control, er etc) | D38: TRAIN CONTROL | F38: 1 | I38: 461.70053 | J38: 578.13741 | K38: 578.13741 | L38: 2382.3747 | M38: 2983.189 | N38: 2382.3747 | P38: PAC (Brazil BRL) | Q38: Brazilian factory PAC price (local Brazilian cost)
A39: 41A296352CMP387 | B39: ETHERNET CABLE | C39: Controls (MCA, train control, er etc) | D39: MCA | F39: 1 | I39: 413.22564 | J39: 517.43757 | K39: 517.43757 | L39: 2132.2443 | M39: 2669.9779 | N39: 2132.2443 | P39: PAC (Brazil BRL) | Q39: Brazilian factory PAC price (local Brazilian cost) | S39: Wire/Cable | T39: Already nationalized (PAC) | U39: 2660.402 | V39: 2669.9779 | W39: Import is cheaper (by R$ 9.58)
A40: 41B511393P2 | B40: Battery Knife Switch | C40: Power | D40: POWER | F40: 1 | I40: 347.82993 | J40: 435.54962 | K40: 435.54962 | L40: 1794.8024 | M40: 2247.436 | N40: 1794.8024 | P40: PAC (Brazil BRL) | Q40: Brazilian factory PAC price (local Brazilian cost)
A41: 84A231123CSP30 | B41: Axle Tac - WRE Part Number: 29266P | C41: PTC | D41: PTC | F41: 1 | G41: 205 | I41: 330.12205 | J41: 413.37596 | K41: 413.37596 | L41: 1703.4298 | M41: 2133.02 | P41: Imported BOM (USA) | Q41: Brazilian factory PAC price (local Brazilian cost)
A42: 84A207079ABP1 | B42: 41A313392DCP18 alternative 300" / | C42: Controls (MCA, train control, er etc) | D42: Wiring | F42: 25 | G42: 8.118 | I42: 326.82082 | J42: 16.369688 | K42: 409.2422 | L42: 1686.3955 | M42: 2111.6898 | P42: Imported BOM (USA) | Q42: Brazilian factory PAC price (local Brazilian cost)
A43: 84A201850P4 | B43: ENGINE CONTROL SWITCH | C43: Controls (MCA, train control, er etc) | D43: TRAIN CONTROL | F43: 1 | G43: 171.544 | I43: 276.24613 | J43: 345.91301 | K43: 345.91301 | L43: 1425.43 | M43: 1784.9111 | P43: Imported BOM (USA) | Q43: Brazilian factory PAC price (local Brazilian cost)
A44: RCCR-PWRCBL | B44: CABLE, PWR, 72V,RA,6.5FT (78").,RR-070,RCCR | C44: Connectivity | D44: VOICE RADIO | F44: 1 | G44: 159 | I44: 256.04588 | J44: 320.61843 | K44: 320.61843 | L44: 1321.1967 | M44: 1654.3911 | P44: Imported BOM (USA) | Q44: Brazilian factory PAC price (local Brazilian cost) | S44: Wire/Cable | T44: Low confidence - PAC match, different length | U44: 1654.3911 | V44: 806.59378 | W44: PAC/National is cheaper (by R$ 847.80)
A45: 41A216641P158 | B45: SNIO CONNECTOR 3 | C45: Controls (MCA, train control, er etc) | D45: Wiring | F45: 2 | I45: 251.78188 | J45: 157.63955 | K45: 315.27909 | L45: 1299.1945 | M45: 1626.8401 | N45: 649.59726 | P45: PAC (Brazil BRL) | Q45: Brazilian factory PAC price (local Brazilian cost) | S45: Connector/Plug | T45: Already nationalized (PAC) | U45: 1529.528 | V45: 1626.8401 | W45: Import is cheaper (by R$ 97.31)
A46: 41B546301P4 | B46: DOOR INTERLOCK SWITCH | C46: Controls (MCA, train control, er etc) | D46: TRAIN CONTROL | F46: 1 | I46: 248.53773 | J46: 311.2168 | K46: 311.2168 | L46: 1282.4547 | M46: 1605.8787 | N46: 1282.4547 | P46: PAC (Brazil BRL) | Q46: Brazilian factory PAC price (local Brazilian cost)
A47: 84A201169AKP1 | B47: ENGINEERS HORN BUTTON | C47: Controls (MCA, train control, er etc) | D47: TRAIN CONTROL | F47: 1 | I47: 220.85663 | J47: 276.55476 | K47: 276.55476 | L47: 1139.6202 | M47: 1427.0226 | N47: 1139.6202 | P47: PAC (Brazil BRL) | Q47: Calculated with TP (17.2%) + International Freight (15%) + Import Duty (16%) + Domestic Freight (3%) | Qtd=1.0
A48: 41B549523ABP101 | B48: BATTERY SAVER RESET PUSH BUTTON | C48: Controls (MCA, train control, er etc) | D48: TRAIN CONTROL | F48: 1 | I48: 216.586 | J48: 271.20711 | K48: 271.20711 | L48: 1117.5838 | M48: 1399.4287 | N48: 1117.5838 | P48: PAC (Brazil BRL) | Q48: Brazilian factory PAC price (local Brazilian cost)
A49: 41B564808G1 | B49: A-DIODE ASM | C49: SKID Assembly | D49: SKID (Skid) | F49: 16 | I49: 197.86975 | J49: 15.485674 | K49: 247.77079 | L49: 1021.0079 | M49: 1278.4973 | N49: 63.812995 | P49: PAC (Brazil BRL) | Q49: Brazilian factory PAC price (local Brazilian cost)
A50: 497A365P13 | B50: ALARM AND SIGNAL BELL | C50: Controls (MCA, train control, er etc) | D50: TRAIN CONTROL | F50: 1 | I50: 189.07809 | J50: 236.76194 | K50: 236.76194 | L50: 975.64293 | M50: 1221.6916 | N50: 975.64293 | P50: PAC (Brazil BRL) | Q50: Calculated with TP (17.2%) + International Freight (15%) + Import Duty (16%) + Domestic Freight (3%) | Qtd=1.0
A51: 84A201850P5 | B51: AC-ROTARY SWITCH | C51: SKID Assembly | D51: SKID (Skid) | F51: 1 | I51: 183.44022 | J51: 229.70225 | K51: 229.70225 | L51: 946.55154 | M51: 1185.2636 | N51: 946.55154 | P51: PAC (Brazil BRL) | Q51: Calculated with TP (17.2%) + International Freight (15%) + Import Duty (16%) + Domestic Freight (3%) | Qtd=1.0
A52: 41A216641P235 | B52: GOLINC / ACC POWER CONNECTOR | C52: Controls (MCA, train control, er etc) | D52: Wiring | F52: 3 | I52: 176.58838 | J52: 73.70748 | K52: 221.12244 | L52: 911.19605 | M52: 1140.9918 | N52: 303.73202 | P52: PAC (Brazil BRL) | Q52: Calculated with TP (17.2%) + International Freight (15%) + Import Duty (16%) + Domestic Freight (3%) | Qtd=1.0 | S52: Connector/Plug | T52: Already nationalized (PAC) | U52: 1028.8052 | V52: 1140.9918 | W52: Import is cheaper (by R$ 112.19)
A53: 84A206730P1 | B53: 565" / CABLE 5 PAIR | C53: Controls (MCA, train control, er etc) | D53: Wiring | F53: 50 | I53: 174.07837 | J53: 4.3595886 | K53: 217.97943 | L53: 898.2444 | M53: 1124.7739 | N53: 17.964888 | P53: PAC (Brazil BRL) | Q53: Brazilian factory PAC price (local Brazilian cost) | S53: Wire/Cable | T53: Already nationalized (PAC) | U53: 975.01723 | V53: 1124.7739 | W53: Import is cheaper (by R$ 149.76)
A54: 41B549523ADP108 | B54: VIGILANCE RESET SWITCH | C54: Controls (MCA, train control, er etc) | D54: TRAIN CONTROL | F54: 1 | I54: 155.80761 | J54: 195.10094 | K54: 195.10094 | L54: 803.96726 | M54: 1006.7208 | N54: 803.96726 | P54: PAC (Brazil BRL) | Q54: Brazilian factory PAC price (local Brazilian cost)
A55: 41A317303ACP49 | B55: AIR RESERVOIR PRESSURE SENSOR | C55: Controls (MCA, train control, er etc) | D55: MCA | F55: 1 | I55: 145.18613 | J55: 181.80081 | K55: 181.80081 | L55: 749.16041 | M55: 938.09217 | N55: 749.16041 | P55: PAC (Brazil BRL) | Q55: Brazilian factory PAC price (local Brazilian cost)
A56: 41A216641AMP126 | B56: NIO1D CONNECTOR BACKSHELL | C56: Controls (MCA, train control, er etc) | D56: Wiring | F56: 3 | G56: 29.9096 | I56: 144.4949 | J56: 60.311755 | K56: 180.93526 | L56: 745.5937 | M56: 933.62597 | P56: Imported BOM (USA) | Q56: Calculated with TP (17.2%) + International Freight (15%) + Import Duty (16%) + Domestic Freight (3%) | Qtd=1.0 | S56: Connector/Plug | T56: Medium confidence PAC match (same PN family - AMP115 backshell) | U56: 933.62597 | V56: 1034.7713 | W56: Import is cheaper (by R$ 101.15)
A57: 84A215329P1 | B57: ENGINE STOP SWITCH | C57: Controls (MCA, train control, er etc) | D57: TRAIN CONTROL | F57: 1 | I57: 136.23751 | J57: 170.59542 | K57: 170.59542 | L57: 702.98553 | M57: 880.27239 | N57: 702.98553 | P57: PAC (Brazil BRL) | Q57: Brazilian factory PAC price (local Brazilian cost)
A58: 41A296328ASP3 | B58: BATTERY TEMPERATURE SENSOR | C58: Controls (MCA, train control, er etc) | D58: Power | F58: 1 | I58: 134.70558 | J58: 168.67716 | K58: 168.67716 | L58: 695.08079 | M58: 870.37414 | N58: 695.08079 | P58: PAC (Brazil BRL) | Q58: Brazilian factory PAC price (local Brazilian cost)
A59: 41A216641ABP45 | B59: DUAL PROCESSOR MODULE CONNECTOR | C59: Controls (MCA, train control, er etc) | D59: Wiring | F59: 2 | I59: 134.48545 | J59: 84.200758 | K59: 168.40152 | L59: 693.94492 | M59: 868.95182 | N59: 346.97246 | P59: PAC (Brazil BRL) | Q59: Brazilian factory PAC price (local Brazilian cost) | S59: Connector/Plug | T59: Already nationalized (PAC) | U59: 814.08342 | V59: 868.95182 | W59: Import is cheaper (by R$ 54.87)
A60: 84A232147P2 | B60: PIN REAR HOLD-DOWN | C60: Controls (MCA, train control, er etc) | D60: TRAIN CONTROL | F60: 30 | I60: 132.57061 | J60: 5.5334588 | K60: 166.00377 | L60: 684.06433 | M60: 856.57943 | N60: 22.802144 | P60: PAC (Brazil BRL) | Q60: Brazilian factory PAC price (local Brazilian cost) | S60: Connector/Plug | T60: Already nationalized (PAC) | U60: 1332.5383 | V60: 856.57943 | W60: PAC/National is cheaper (by R$ 475.96)
A61: 41A321053G1 | B61: Power Resistor | C61: Power | D61: Resistor | F61: 1 | I61: 132.25867 | J61: 165.61316 | K61: 165.61316 | L61: 682.45475 | M61: 854.56392 | N61: 682.45475 | P61: PAC (Brazil BRL) | Q61: Brazilian factory PAC price (local Brazilian cost)
A62: 17 pin MS3106-20-29F | B62: Head of Train Device - Padom - J2 Connector | C62: Controls (MCA, train control, er etc) | D62: Wiring | F62: 1 | G62: 79.83 | I62: 128.55436 | J62: 160.97465 | K62: 160.97465 | L62: 663.34047 | M62: 830.62919 | P62: Imported BOM (USA) | Q62: Brazilian factory PAC price (local Brazilian cost) | S62: Connector/Plug | T62: Low confidence - no comparable PAC item found | U62: 830.62919 | V62: 836.61643 | W62: Import is cheaper (by R$ 5.99)
A63: 41A216641P157 | B63: SNIO CONNECTOR 2 | C63: Controls (MCA, train control, er etc) | D63: Wiring | F63: 1 | I63: 121.26151 | J63: 151.84262 | K63: 151.84262 | L63: 625.70941 | M63: 783.50791 | N63: 625.70941 | P63: PAC (Brazil BRL) | Q63: Brazilian factory PAC price (local Brazilian cost) | S63: Connector/Plug | T63: Already nationalized (PAC) | U63: 702.01339 | V63: 783.50791 | W63: Import is cheaper (by R$ 81.49)
A64: 41A216641AMP125 | B64: NIO1A CONNECTOR BACKSHELL | C64: Controls (MCA, train control, er etc) | D64: Wiring | F64: 3 | G64: 24.1998 | I64: 116.91055 | J64: 48.798125 | K64: 146.39438 | L64: 603.25843 | M64: 755.39498 | P64: Imported BOM (USA) | Q64: Brazilian factory PAC price (local Brazilian cost) | S64: Connector/Plug | T64: Medium confidence PAC match (same PN family - AMP115 backshell) | U64: 755.39498 | V64: 1034.7713 | W64: Import is cheaper (by R$ 279.38)
A65: 5088-7000-P4611-0000000-ND‎ | B65: POE Power Connector on SMM2 (M12 FEMALE 0 L-CODED FIELD-WIREA) | C65: Controls (MCA, train control, er etc) | D65: TRAIN CONTROL | F65: 1 | G65: 72.41 | I65: 116.60555 | J65: 146.01246 | K65: 146.01246 | L65: 601.68463 | M65: 753.42428 | P65: Imported BOM (USA) | Q65: Calculated with TP (17.2%) + International Freight (15%) + Import Duty (16%) + Domestic Freight (3%) | Qtd=1.0 | S65: Connector/Plug | T65: Low confidence - no current price, weak PAC reference only | U65: 753.42428 | V65: 166.36614 | W65: PAC/National is cheaper (by R$ 587.06)
A66: 41A296352PTP67 | B66: CABLE CSX 12V P WR CBL | C66: Controls (MCA, train control, er etc) | D66: MCA | F66: 1 | G66: 71.94 | I66: 115.84868 | J66: 145.06472 | K66: 145.06472 | L66: 597.7792 | M66: 748.53394 | P66: Imported BOM (USA) | Q66: Brazilian factory PAC price (local Brazilian cost) | S66: Wire/Cable | T66: Low confidence - PAC candidate is more expensive | U66: 748.53394 | V66: 1134.2711 | W66: Import is cheaper (by R$ 385.74)
A67: 41A296352PTP69 | B67: CABLE CSX 74V P WR CBL | C67: Controls (MCA, train control, er etc) | D67: MCA | F67: 1 | G67: 71.94 | I67: 115.84868 | J67: 145.06472 | K67: 145.06472 | L67: 597.7792 | M67: 748.53394 | P67: Imported BOM (USA) | Q67: Brazilian factory PAC price (local Brazilian cost) | S67: Wire/Cable | T67: Low confidence - PAC candidate is more expensive | U67: 748.53394 | V67: 1134.2711 | W67: Import is cheaper (by R$ 385.74)
A68: 41A216641AMP93 | B68: NIO1E CONNECTOR | C68: Controls (MCA, train control, er etc) | D68: Wiring | F68: 3 | G68: 23.9499 | I68: 115.70327 | J68: 48.29421 | K68: 144.88263 | L68: 597.02886 | M68: 747.59437 | P68: Imported BOM (USA) | Q68: Brazilian factory PAC price (local Brazilian cost) | S68: Connector/Plug | T68: Medium confidence PAC match (same PN family - AMP84 plug) | U68: 747.59437 | V68: 427.83384 | W68: PAC/National is cheaper (by R$ 319.76)
A69: 41B549523ADP1 | B69: Black push Button | C69: SKID Assembly | D69: Use in place of al levers and other push buttons | F69: 1 | I69: 109.60596 | J69: 137.24763 | K69: 137.24763 | L69: 565.56673 | M69: 708.19776 | N69: 565.56673 | P69: PAC (Brazil BRL) | Q69: Brazilian factory PAC price (local Brazilian cost)
A70: 41B549523ADP2 | B70: SWITCH PUSH BUTTON | C70: SKID Assembly | D70: SKID (Skid) | F70: 1 | I70: 105.17654 | J70: 131.70115 | K70: 131.70115 | L70: 542.71095 | M70: 679.57795 | N70: 542.71095 | P70: PAC (Brazil BRL) | Q70: Brazilian factory PAC price (local Brazilian cost)
A71: 41A296328APP5 | B71: BATTERY CURRENT SENSOR | C71: Controls (MCA, train control, er etc) | D71: MCA | F71: 1 | I71: 102.85197 | J71: 128.79035 | K71: 128.79035 | L71: 530.71617 | M71: 664.55819 | N71: 530.71617 | P71: PAC (Brazil BRL) | Q71: Brazilian factory PAC price (local Brazilian cost)
A72: 41A216641AMP103 | B72: NIO1D CONNECTOR | C72: Controls (MCA, train control, er etc) | D72: Wiring | F72: 3 | G72: 21.2198 | I72: 102.51401 | J72: 42.78905 | K72: 128.36715 | L72: 528.97227 | M72: 662.3745 | P72: Imported BOM (USA) | Q72: Brazilian factory PAC price (local Brazilian cost) | S72: Connector/Plug | T72: Low confidence - family match, wrong sub-type | U72: 662.3745 | V72: 1034.7713 | W72: Import is cheaper (by R$ 372.40)
A73: 16246P | B73: Flexi-Axle - WRE Part Number: 16246P | C73: PTC | D73: PTC | F73: 1 | G73: 59.75 | I73: 96.218499 | J73: 120.48397 | K73: 120.48397 | L73: 496.48745 | M73: 621.69729 | P73: Imported BOM (USA) | Q73: Brazilian factory PAC price (local Brazilian cost)
A74: 41A216641AMP99 | B74: NIO1B CONNECTOR | C74: Controls (MCA, train control, er etc) | D74: Wiring | F74: 3 | G74: 19.67 | I74: 95.026838 | J74: 39.663928 | K74: 118.99178 | L74: 490.33849 | M74: 613.9976 | P74: Imported BOM (USA) | Q74: Calculated with TP (17.2%) + International Freight (15%) + Import Duty (16%) + Domestic Freight (3%) | Qtd=3.0 | S74: Connector/Plug | T74: Medium confidence PAC match (same PN family - AMP84 plug) | U74: 613.9976 | V74: 427.83384 | W74: PAC/National is cheaper (by R$ 186.16)
A75: 41A216641AMP123 | B75: NIO1F CONNECTOR BACKSHELL | C75: Controls (MCA, train control, er etc) | D75: Wiring | F75: 3 | G75: 19.5574 | I75: 94.482862 | J75: 39.436874 | K75: 118.31062 | L75: 487.53157 | M75: 610.4828 | P75: Imported BOM (USA) | Q75: Calculated with TP (17.2%) + International Freight (15%) + Import Duty (16%) + Domestic Freight (3%) | Qtd=3.0 | S75: Connector/Plug | T75: Medium confidence PAC match (same PN family - AMP115 backshell) | U75: 610.4828 | V75: 1034.7713 | W75: Import is cheaper (by R$ 424.29)
A76: 41A216641P140 | B76: Part NumberEUMATIC OPERATING UNIT CONNECTOR - 5 | C76: Air | D76: Fastbrake | F76: 1 | I76: 93.10614 | J76: 116.5867 | K76: 116.5867 | L76: 480.42768 | M76: 601.58738 | N76: 480.42768 | P76: PAC (Brazil BRL) | Q76: Calculated with TP (17.2%) + International Freight (15%) + Import Duty (16%) + Domestic Freight (3%) | Qtd=3.0 | S76: Connector/Plug | T76: Already nationalized (PAC) | U76: 927.42171 | V76: 601.58738 | W76: PAC/National is cheaper (by R$ 325.83)
A77: 41A216641AMP100 | B77: NIO1C CONNECTOR | C77: Controls (MCA, train control, er etc) | D77: Wiring | F77: 3 | G77: 19.173 | I77: 92.625804 | J77: 38.661743 | K77: 115.98523 | L77: 477.94915 | M77: 598.48379 | P77: Imported BOM (USA) | Q77: Brazilian factory PAC price (local Brazilian cost) | S77: Connector/Plug | T77: Low confidence - family match, wrong sub-type | U77: 598.48379 | V77: 1034.7713 | W77: Import is cheaper (by R$ 436.29)
A78: 41A216641P53 | B78: SNIO CONNECTOR 1 | C78: Controls (MCA, train control, er etc) | D78: Wiring | F78: 1 | I78: 91.649811 | J78: 114.7631 | K78: 114.7631 | L78: 472.91303 | M78: 592.17759 | N78: 472.91303 | P78: PAC (Brazil BRL) | Q78: Calculated with TP (17.2%) + International Freight (15%) + Import Duty (16%) + Domestic Freight (3%) | Qtd=1.0 | S78: Connector/Plug | T78: Already nationalized (PAC) | U78: 613.88757 | V78: 592.17759 | W78: PAC/National is cheaper (by R$ 21.71)
A79: 41A216641AMP86 | B79: NIO1F CONNECTOR | C79: Controls (MCA, train control, er etc) | D79: Wiring | F79: 3 | G79: 18.9357 | I79: 91.479395 | J79: 38.183235 | K79: 114.54971 | L79: 472.03368 | M79: 591.07648 | P79: Imported BOM (USA) | Q79: Calculated with TP (17.2%) + International Freight (15%) + Import Duty (16%) + Domestic Freight (3%) | Qtd=3.0 | S79: Connector/Plug | T79: Medium confidence PAC match (same PN family - AMP84 plug) | U79: 591.07648 | V79: 427.83384 | W79: PAC/National is cheaper (by R$ 163.24)
A80: 41A216641P141 | B80: Part NumberEUMATIC OPERATING UNIT CONNECTOR - 7 | C80: Air | D80: Fastbrake | F80: 1 | I80: 88.371988 | J80: 110.65864 | K80: 110.65864 | L80: 455.99946 | M80: 570.99857 | N80: 455.99946 | P80: PAC (Brazil BRL) | Q80: Calculated with TP (17.2%) + International Freight (15%) + Import Duty (16%) + Domestic Freight (3%) | Qtd=3.0 | S80: Connector/Plug | T80: Already nationalized (PAC) | U80: 598.30249 | V80: 570.99857 | W80: PAC/National is cheaper (by R$ 27.30)
A81: 41A212414P35 | B81: CIRCUIT BREAKER 1P | C81: SKID Assembly | D81: SKID (Skid) | F81: 6 | I81: 87.928279 | J81: 18.350505 | K81: 110.10303 | L81: 453.70992 | M81: 568.13163 | N81: 75.61832 | P81: PAC (Brazil BRL) | Q81: Calculated with TP (17.2%) + International Freight (15%) + Import Duty (16%) + Domestic Freight (3%) | Qtd=3.0 | S81: Breaker | T81: Already nationalized (PAC) | U81: 603.56096 | V81: 568.13163 | W81: PAC/National is cheaper (by R$ 35.43)
A82: 41A212414P73 | B82: BATT CHARGER & COMP CIRCUIT BREAKER (2P, 20A / 50A) | C82: Controls (MCA, train control, er etc) | D82: Circuit Breaker | F82: 1 | I82: 85.986164 | J82: 107.67113 | K82: 107.67113 | L82: 443.6886 | M82: 555.58303 | N82: 443.6886 | P82: PAC (Brazil BRL) | Q82: Calculated with TP (17.2%) + International Freight (15%) + Import Duty (16%) + Domestic Freight (3%) | Qtd=3.0 | S82: Breaker | T82: Already nationalized (PAC) | U82: 552.47525 | V82: 555.58303 | W82: Import is cheaper (by R$ 3.11)
A83: 41A212414P76 | B83: FUEL PUMP CIRCUIT BREAKER (4P, 25A / 45A) | C83: Controls (MCA, train control, er etc) | D83: Circuit Breaker | F83: 1 | I83: 82.77345 | J83: 103.6482 | K83: 103.6482 | L83: 427.111 | M83: 534.8247 | N83: 427.111 | P83: PAC (Brazil BRL) | Q83: Calculated with TP (17.2%) + International Freight (15%) + Import Duty (16%) + Domestic Freight (3%) | Qtd=3.0 | S83: Breaker | T83: Already nationalized (PAC) | U83: 643.03503 | V83: 534.8247 | W83: PAC/National is cheaper (by R$ 108.21)
A84: 41A296326DDP52 | B84: EMU CONNECTOR | C84: Controls (MCA, train control, er etc) | D84: Wiring | F84: 1 | I84: 79.8362 | J84: 99.970198 | K84: 99.970198 | L84: 411.95479 | M84: 515.84622 | N84: 411.95479 | P84: PAC (Brazil BRL) | Q84: Brazilian factory PAC price (local Brazilian cost) | S84: Connector/Plug | T84: Already nationalized (PAC) | U84: 582.40181 | V84: 515.84622 | W84: PAC/National is cheaper (by R$ 66.56)
A85: 84B523158P1 | B85: RESERVOIR DRAIN VALVE HEATER # 1 | C85: Controls (MCA, train control, er etc) | D85: TRAIN CONTROL | F85: 1 | I85: 77.094338 | J85: 96.536861 | K85: 96.536861 | L85: 397.80678 | M85: 498.13021 | N85: 397.80678 | P85: PAC (Brazil BRL) | Q85: Brazilian factory PAC price (local Brazilian cost)
A86: 41A216641P142 | B86: Part NumberEUMATIC OPERATING UNIT CONNECTOR - 8 | C86: Air | D86: Fastbrake | F86: 1 | I86: 74.912105 | J86: 93.804289 | K86: 93.804289 | L86: 386.54646 | M86: 484.03013 | N86: 386.54646 | P86: PAC (Brazil BRL) | Q86: Brazilian factory PAC price (local Brazilian cost) | S86: Connector/Plug | T86: Already nationalized (PAC) | U86: 534.28755 | V86: 484.03013 | W86: PAC/National is cheaper (by R$ 50.26)
A87: 41A216641AMP98 | B87: NIO1A CONNECTOR | C87: Controls (MCA, train control, er etc) | D87: Wiring | F87: 3 | G87: 15.455 | I87: 74.663945 | J87: 31.164515 | K87: 93.493544 | L87: 385.26595 | M87: 482.42669 | P87: Imported BOM (USA) | Q87: Brazilian factory PAC price (local Brazilian cost) | S87: Connector/Plug | T87: Medium confidence PAC match (same PN family - AMP84 plug) | U87: 482.42669 | V87: 427.83384 | W87: PAC/National is cheaper (by R$ 54.59)
A88: 41A216641ABP153 | B88: HELPER'S RADIO SPEAKER CONNECTOR | C88: Controls (MCA, train control, er etc) | D88: Wiring | F88: 1 | G88: 45.7356 | I88: 73.650389 | J88: 92.224379 | K88: 92.224379 | L88: 380.03601 | M88: 475.8778 | P88: Imported BOM (USA) | Q88: Brazilian factory PAC price (local Brazilian cost) | S88: Connector/Plug | T88: Low confidence - generic family match only | U88: 475.8778 | V88: 333.06385 | W88: PAC/National is cheaper (by R$ 142.81)
A89: 17LV66BD52 | B89: CONSIST MANAGER SYSTEM RELAY | C89: Controls (MCA, train control, er etc) | D89: TRAIN CONTROL | F89: 1 | I89: 73.009239 | J89: 91.421537 | K89: 91.421537 | L89: 376.72768 | M89: 471.73513 | N89: 376.72768 | P89: PAC (Brazil BRL) | Q89: Brazilian factory PAC price (local Brazilian cost)
A90: 17LV66J10 | B90: RELAYS | C90: Controls (MCA, train control, er etc) | D90: TRAIN CONTROL | F90: 1 | I90: 69.554429 | J90: 87.095454 | K90: 87.095454 | L90: 358.90086 | M90: 449.41254 | N90: 358.90086 | P90: PAC (Brazil BRL) | Q90: Brazilian factory PAC price (local Brazilian cost)
A91: 41A296326DDP78 | B91: GEW LAYER 3 ETH ERNET SWITCH POWER PLUG | C91: Controls (MCA, train control, er etc) | D91: MCA | F91: 1 | I91: 64.940826 | J91: 81.318339 | K91: 81.318339 | L91: 335.09466 | M91: 419.60263 | N91: 335.09466 | P91: PAC (Brazil BRL) | Q91: Brazilian factory PAC price (local Brazilian cost) | S91: Connector/Plug | T91: Already nationalized (PAC) | U91: 621.26344 | V91: 419.60263 | W91: PAC/National is cheaper (by R$ 201.66)
A92: 41A265714P22 | B92: SOCKET CONTACT, .75" | C92: Controls (MCA, train control, er etc) | D92: Wiring | F92: 109 | I92: 59.410357 | J92: 0.68250582 | K92: 74.393135 | L92: 306.55744 | M92: 383.86857 | N92: 2.8124536 | P92: PAC (Brazil BRL) | Q92: Calculated with TP (17.2%) + International Freight (15%) + Import Duty (16%) + Domestic Freight (3%) | Qtd=3.0 | S92: Connector/Plug | T92: Already nationalized (PAC) | U92: 362.69477 | V92: 383.86857 | W92: Import is cheaper (by R$ 21.17)
A93: 41A216641ABP139 | B93: DISTRIBUTED POWER RADIO MODULE BASE CONNECTOR | C93: Controls (MCA, train control, er etc) | D93: Wiring | F93: 1 | I93: 54.7298 | J93: 68.532181 | K93: 68.532181 | L93: 282.40577 | M93: 353.62605 | N93: 282.40577 | P93: PAC (Brazil BRL) | Q93: Brazilian factory PAC price (local Brazilian cost) | S93: Connector/Plug | T93: Already nationalized (PAC) | U93: 360.48467 | V93: 353.62605 | W93: PAC/National is cheaper (by R$ 6.86)
A94: 84B104674ASP14 | B94: AMBIENT AIR TEMPERATURE SENSOR PLUG | C94: Controls (MCA, train control, er etc) | D94: MCA | F94: 1 | I94: 50.927567 | J94: 63.771058 | K94: 63.771058 | L94: 262.78624 | M94: 329.05866 | N94: 262.78624 | P94: PAC (Brazil BRL) | Q94: Brazilian factory PAC price (local Brazilian cost) | S94: Connector/Plug | T94: Already nationalized (PAC) | U94: 337.85212 | V94: 329.05866 | W94: PAC/National is cheaper (by R$ 8.79)
A95: 41A316591P1 | B95: Card Holder 3 Slot | C95: Controls (MCA, train control, er etc) | D95: TRAIN CONTROL | F95: 1 | I95: 38.450979 | J95: 48.147982 | K95: 48.147982 | L95: 198.40705 | M95: 248.44359 | N95: 198.40705 | P95: PAC (Brazil BRL) | Q95: Brazilian factory PAC price (local Brazilian cost)
A96: 41A212414P31, 41A212414P3 2-Pole Option | B96: AUTOCOUPLER CIRCUIT BREAKER, CCB(2A) | C96: Controls (MCA, train control, er etc) | D96: Circuit Breaker | F96: 1 | G96: 22.0206 | I96: 35.460905 | J96: 44.403838 | K96: 44.403838 | L96: 182.97827 | M96: 229.1238 | P96: Imported BOM (USA) | Q96: Brazilian factory PAC price (local Brazilian cost) | S96: Breaker | T96: High confidence PAC match (exact PN) - not yet applied | U96: 229.1238 | V96: 94.303963 | W96: PAC/National is cheaper (by R$ 134.82)
A97: 41A265713P22 | B97: PIN | C97: Controls (MCA, train control, er etc) | D97: Wiring | F97: 82 | I97: 33.234893 | J97: 0.50751763 | K97: 41.616446 | L97: 171.49205 | M97: 214.74086 | N97: 2.0913665 | P97: PAC (Brazil BRL) | Q97: Calculated with TP (17.2%) + International Freight (15%) + Import Duty (16%) + Domestic Freight (3%) | Qtd=1.0
A98: 41A212414P3 | B98: DYNAMIC BRAKE CIRCUIT BREAKER (1P, 2A) | C98: Controls (MCA, train control, er etc) | D98: Circuit Breaker | F98: 1 | I98: 29.821879 | J98: 37.342698 | K98: 37.342698 | L98: 153.88089 | M98: 192.68832 | N98: 153.88089 | P98: PAC (Brazil BRL) | Q98: Brazilian factory PAC price (local Brazilian cost) | S98: Breaker | T98: Already nationalized (PAC) | U98: 189.09308 | V98: 192.68832 | W98: Import is cheaper (by R$ 3.60)
A99: 41A212414P14 | B99: PTC RADIO CIRCUIT BREAKER (2P, 15A) | C99: Controls (MCA, train control, er etc) | D99: Circuit Breaker | F99: 1 | I99: 29.793742 | J99: 37.307466 | K99: 37.307466 | L99: 153.73571 | M99: 192.50652 | N99: 153.73571 | P99: PAC (Brazil BRL) | Q99: Brazilian factory PAC price (local Brazilian cost) | S99: Breaker | T99: Already nationalized (PAC) | U99: 188.95797 | V99: 192.50652 | W99: Import is cheaper (by R$ 3.55)
A100: 41A212414P15 | B100: SMART DISPLAY #1 CIRCUIT BREAKER (2P, 6A) | C100: Controls (MCA, train control, er etc) | D100: Circuit Breaker | F100: 1 | I100: 29.532314 | J100: 36.980108 | K100: 36.980108 | L100: 152.38674 | M100: 190.81736 | N100: 152.38674 | P100: PAC (Brazil BRL) | Q100: Brazilian factory PAC price (local Brazilian cost) | S100: Breaker | T100: Already nationalized (PAC) | U100: 192.06454 | V100: 190.81736 | W100: PAC/National is cheaper (by R$ 1.25)
...

Sheet GDT Integration and Assembly
A1: GDT Category | B1: Item / Service or Material Description | C1: Direct Cost BRL | D1: Direct Cost USD (@ 5.16) | E1: Gross Price BRL (Including PIS/COFINS and ICMS) | F1: Gross Price USD (Including PIS/COFINS and ICMS) | G1: Notes / Calculation Details
A2: Integration / Container Materials | B2: Container + enviromental Report | C2: 70000 | D2: 13565.891 | E2: 87653.393 | F2: 16987.092 | G2: Não incluso transporte do container
A3: Integration / Container Materials | B3: Pneumatics (tubulações, 14un mangueiras, 30un torneiras, conexões) | C3: 25000 | D3: 4844.9612 | E3: 31304.783 | F3: 6066.8185 | G3: Conexões pneumáticas gerais
A4: Integration / Container Materials | B4: Rack Electrical Connection | C4: 25000 | D4: 4844.9612 | E4: 31304.783 | F4: 6066.8185 | G4: Chicotes e passagem de cabos
A5: Integration / Container Materials | B5: Internal Electrical System (cabeamento, iluminação interna, 4un strobe, 6un steplights) | C5: 5000 | D5: 968.99225 | E5: 6260.9567 | F5: 1213.3637 | G5: Horn and headlight not needed
A6: Integration / Container Materials | B6: MU Connectors (4un), MU Jumpers (2un) | C6: 60000 | D6: 11627.907 | E6: 75131.48 | F6: 14560.364 | G6: Considerando eletrodutos e alongamento de cabeamento do container ao vagão
A7: Integration / Container Materials | B7: Air Conditioning, Inverter and Power | C7: 100000 | D7: 19379.845 | E7: 125219.13 | F7: 24267.274 | G7: Ar condicionado, inversor e potência para troca de calor
A8: Integration / Container Materials | B8: Container Thermal Insulation | C8: 100000 | D8: 19379.845 | E8: 125219.13 | F8: 24267.274 | G8: Isolamento térmico interno
A9: Integration / Container Materials | B9: Steel (railcar repair, ladder and access door) | C9: 12500 | D9: 2422.4806 | E9: 15652.392 | F9: 3033.4092 | G9: 25 reais por quilo
A10: Integration / Container Materials | B10: Painting and Lettering (Lettering) | C10: 5000 | D10: 968.99225 | E10: 6260.9567 | F10: 1213.3637 | G10: Não considerando pintar o vagão inteiro
A11: Integration / Container Materials | B11: Miscellaneous | C11: 10000 | D11: 1937.9845 | E11: 12521.913 | F11: 2426.7274 | G11: Insumos e materiais diversos
A12: Labor and Field Services | B12: Assembly and Integration Labor (Labor Cost) | C12: 122752 | D12: 23789.147 | E12: 153708.99 | F12: 29788.564 | G12: 1.096 horas (mecânica, elétrica, solda, pintura e campo) @ R$ 112/h
A13: Labor and Field Services | B13: Engineering / Project Design (NRE) | C13: 39424 | D13: 7640.3101 | E13: 49366.391 | F13: 9567.1301 | G13: 1 engenheiro + 1 projetista durante 1 mês
... A19: TOTAL GDT ROLLUP | B19: Total Integration, Adaptation and Services | C19: 707790.6 | D19: 137168.72 | E19: 886289.26 | F19: 171761.48 | G19: Sum of all additional materials and services from the rollup

Sheet Missing Items
A1: Part Number | B1: Description | C1: System | D1: Subsystem | E1: Status / Notes
A2: 41A296326CYP77 | B2: M12-A_ MALE_ 8-PIN_ STRAIGHT BSH | C2: SKID Assembly | D2: SKID (Skid) | E2: Quotation pending (no USD or BRL price)
A3: 41A296352PTP272 | B3: BC-PRECISION NAVIGATION MODULE | C3: SKID Assembly | D3: SKID (Skid) | E3: Quotation pending (no USD or BRL price)
A4: 41A296352PTP58 | B4: AY-DISPLAY CSX PTC DISPLAY | C4: SKID Assembly | D4: SKID (Skid) | E4: Quotation pending (no USD or BRL price)
A5: 41A296352PTP292 | B5: AX-POWER SUPPLY 13.6 V | C5: SKID Assembly | D5: SKID (Skid) | E5: Quotation pending (no USD or BRL price)
A6: MODEM ATT | B6: MODEM ATT | C6: SKID Assembly | D6: SKID (Skid) | E6: Quotation pending (no USD or BRL price)
A7: 84A237085AJP1 | B7: C-GoLIN EP_3 SMA_M2 CELL MODEM | C7: SKID Assembly | D7: Controls (MCA, train control, er etc) | E7: Quotation pending (no USD or BRL price)
A8: 17FL400B | B8: ST-DEVELOPER v19.4 | C8: SKID Assembly | D8: SKID (Skid) | E8: Quotation pending (no USD or BRL price)
A9: 41A296352CMP448 | B9: FB-DIGITAL RADIO MODULE | C9: SKID Assembly | D9: SKID (Skid) | E9: Quotation pending (no USD or BRL price)
A10: 41A296352PTP326 | B10: BH-WABTEC TRAIN MANAGEMENT COMPUTER _WTMC_ | C10: SKID Assembly | D10: SKID (Skid) | E10: Quotation pending (no USD or BRL price)
A11: 17FM711C3 | B11: H-PANEL DBM | C11: SKID Assembly | D11: SKID (Skid) | E11: Quotation pending (no USD or BRL price)
A12: 41A296352BCP9 | B12: N-HEAD OF TRAIN DEVICE | C12: SKID Assembly | D12: SKID (Skid) | E12: Quotation pending (no USD or BRL price)
... A22: PTC-FILT-NB-220-MIL-MF | B22: 220 Mhz PTC FILTER | C22: SKID Assembly | D22: later | E22: Quotation pending (no USD or BRL price)
B23: PTC Junction Box | C23: SKID Assembly | D23: SKID (Skid) | E23: Quotation pending (no USD or BRL price)
A24: 41A296352LUP15 | B24: 455 MHz Antenna (DPA, DPB, EOT ) | C24: SKID Assembly | D24: SKID (Skid) | E24: Quotation pending (no USD or BRL price)
A25: 84D749224G1 | B25: Power resistor | C25: SKID Assembly | D25: Battery Skid? | E25: Quotation pending (no USD or BRL price)
