Workbook

Sheet Item List
A1: ITEM LIST - MRS Pathfinder GDT Cost Proposal
A3: Part Number | B3: Description | C3: System | D3: SubSystem | E3: Quantity | F3: Cost Source | G3: Unit Cost USD (Imported items, no markup) | H3: Unit Cost BRL (PAC items, local nationalized cost) | I3: Weight (kg) | J3: Weight Confidence | K3: NCM | L3: Dimensions (L x H x W, in) | M3: Notes
A4: 41A296352CMP437 | B4: Dual Processor Module (DPM)+ LXA (Distributed Power Radio) | C4: Controls (MCA, train control, er etc) | D4: LXA | E4: 1 | F4: Imported (USA) | G4: 63100.819 | I4: 4.536 | J4: High | K4: 90328990
A5: 37495P | B5: KIT ETMS VIRGIN TRAINS FEC EVO44 | C5: PTC | D5: PTC KIT MASTER | E5: 1 | F5: Imported (USA) | G5: 28529 | I5: 45.359 | J5: High
A6: 84A222059P5 | B6: BATTERIES | C6: Power | D6: POWER | E6: 2 | F6: Imported (USA) | G6: 15685.42 | I6: 1123.095 | J6: High
A7: 41A296352LUG24 | B7: CSX Antenna Enclosure Arrangement | C7: Connectivity | D7: ANTENNA KIT Master | E7: 1 | F7: Imported (USA) | G7: 30000 | I7: 136.078 | J7: High
A8: 84A215295P62 | B8: Pneumatic Brake Control System (Including lament and control portions) Includes EM EAB Control Functionality | C8: Air | D8: Fastbrake | E8: 1 | F8: Imported (USA) | G8: 23409.1 | I8: 134.263 | J8: High
A9: 41A296352DNP37 | B9: RADIO PRAD PTC RADIO | C9: PTC | D9: PTC | E9: 1 | F9: Imported (USA) | G9: 20000 | I9: 9.616 | J9: High
A10: 17FM878A6 | B10: NIO 2.0 | C10: Controls (MCA, train control, er etc) | D10: MCA | E10: 3 | F10: Imported (USA) | G10: 5176.9118 | I10: 8.618 | J10: High
A11: L7000083-900 | B11: Wireless Communications Management Module, Gen 3 (WCM3)​ | C11: Controls (MCA, train control, er etc) | D11: TRAIN CONTROL | E11: 2 | F11: Imported (USA) | G11: 5000 | I11: 2.268 | J11: High
A12: 84A237085AEP121 | B12: 8 Slot ACC Chassis for MCA w/ i7 HPEAP and SMM2 Cards | C12: Controls (MCA, train control, er etc) | D12: TRAIN CONTROL | E12: 1 | F12: Imported (USA) | G12: 8000 | I12: 9.072 | J12: High
A13: 17FL472A2 | B13: TMC PANEL | C13: SKID Assembly | D13: SKID (Skid) | E13: 1 | F13: PAC (Brazil, nationalized) | H13: 58447.152 | I13: 20.412 | J13: High | K13: 85371090
A14: 17KC108E28 | B14: MASTER CONTROLLER | C14: Controls (MCA, train control, er etc) | D14: TRAIN CONTROL | E14: 1 | F14: GET (made in-house) | G14: 5877.102 | I14: 25.855 | J14: High
A15: 84A215295P73 | B15: Air Brake Handle Assembly (AAR Console) | C15: Air | D15: Fastbrake | E15: 1 | F15: Imported (USA) | G15: 5702.83 | I15: 7.938 | J15: High
A16: 17FM868B2 | B16: SNIO | C16: Controls (MCA, train control, er etc) | D16: MCA | E16: 1 | F16: Imported (USA) | G16: 4150.9559 | I16: 4.99 | J16: High
A17: 41A296352DNP55 | B17: VOICE RADIO RITRON | C17: Connectivity | D17: VOICE RADIO | E17: 1 | F17: Imported (USA) | G17: 3933 | I17: 7.575 | J17: High
A18: 32613P | B18: KIT ETMS AXLE INTERFACE FOR WPart Number 29266P | C18: PTC | D18: PTC | E18: 1 | F18: Imported (USA) | G18: 2981.71 | I18: 4.536 | J18: High
A19: 17FH40X1 | B19: LPS 17FH40 (COMMON LOGIC POWER SUPPLY) (5v, 15v, 19v, 24v) | C19: POWER | D19: POWER SUPPLY | E19: 1 | F19: PAC (Brazil, nationalized) | H19: 15041.54 | I19: 18.144 | J19: High | K19: 85044029 | L19: 24x10x20
A20: 41D758679BJG16 84D704379AFG1 | B20: EC Part NumberL ASM | C20: Power | D20: Circuit Breaker | E20: 1 | F20: GET (made in-house) | G20: 1572.36 | I20: 4.99 | J20: High | K20: 86079100 | L20: 20x3.5x25.5
A21: 41B546155P2 | B21: Horn | C21: Controls (MCA, train control, er etc) | D21: TRAIN CONTROL | E21: 1 | F21: Imported (USA) | G21: 1891.99 | I21: 4.536 | J21: High
B22: Ditchlight Control Box (SMART BOX-V3-DLC ) | C22: Controls (MCA, train control, er etc) | D22: TRAIN CONTROL | E22: 2 | F22: Imported (USA) | G22: 800 | I22: 2.268 | J22: High
B23: LED Ditch Light | C23: Controls (MCA, train control, er etc) | D23: TRAIN CONTROL | E23: 4 | F23: Imported (USA) | G23: 375 | I23: 0.907 | J23: High
A24: 17FM839B1 | B24: PANEL ASM CFD - Thin Client Display | C24: Controls (MCA, train control, er etc) | D24: MCA | E24: 1 | F24: PAC (Brazil, nationalized) | H24: 11603.717 | I24: 9.299 | J24: High | K24: 85312000 | L24: 18.5x8.5x15
A25: 17FM839A3 | B25: TCD (Thin Client Display) | C25: SKID Assembly | D25: SKID (Skid) | E25: 1 | F25: PAC (Brazil, nationalized) | H25: 11603.717 | I25: 9.299 | J25: High | K25: 85312000 | L25: 18.5x8.5x15
A26: 84A201003DAP1 | B26: ELECTRIC Bell | C26: Controls (MCA, train control, er etc) | D26: TRAIN CONTROL | E26: 1 | F26: PAC (Brazil, nationalized) | H26: 9491.4571 | I26: 8.119 | J26: High | K26: 85318000 | L26: 14.25x14.25x10
A27: 17FB193E2F | B27: GET Card | C27: GET | D27: GET Card | E27: 1 | F27: PAC (Brazil, nationalized) | H27: 9251.1239 | I27: 1.114 | J27: High | K27: 85049040 | L27: 17.2x1.95x11.2
A28: 84A215295P3 | B28: POU-to-Handle cable 18' length | C28: Air | D28: Fastbrake | E28: 1 | F28: Imported (USA) | G28: 1036.89 | I28: 1.247 | J28: Medium
A29: 41B566322ACG1 | B29: TRAINLINE RESISTOR PANEL | C29: SKID Assembly | D29: Controls (MCA, train control, er etc) | E29: 1 | F29: GET (made in-house) | I29: 2.859 | J29: High | K29: 85333990 | L29: 14x6x8.5
A30: 41A296304DDP4 | B30: G-RECTIFIER POWER BLOCK | C30: SKID Assembly | D30: Controls (MCA, train control, er etc) | E30: 20 | F30: PAC (Brazil, nationalized) | H30: 326.22301 | I30: 0.054 | J30: Low | K30: 85411099 | L30: 10.85x1.1x8.5 | M30: Weight looks wrong, verify
A31: RCCR-RMTCBL-RA-CUSTOM | B31: VOICE RADIO RITRON CABLE,REMOTE,RR-225/XXX, RCCR,RIGHT ANGLE,19-PIN,FLAME RETARDANT | C31: Connectivity | D31: VOICE RADIO | E31: 1 | F31: Imported (USA) | G31: 761
A32: 41C663693G1 | B32: PANEL CPF | C32: Power | D32: POWER | E32: 1 | F32: GET (made in-house) | I32: 5.761 | J32: High | K32: 85371090 | L32: 20.5x10.5x11.5
A33: 41A296352PTP306/41A296352PTP122 | B33: Assembled Air Manifold (Contains 3 pressure sensors mounted in appropriate locations on Air Manifold.) | C33: PTC | D33: PTC | E33: 1 | F33: Imported (USA) | G33: 595.7889 | I33: 5.897 | J33: Medium | K33: 85381000
A34: 84A232147P1 | B34: KNOB HLD DWN with washer and screw | C34: Controls (MCA, train control, er etc) | D34: TRAIN CONTROL | E34: 30 | F34: PAC (Brazil, nationalized) | H34: 127.47577 | I34: 0.045 | J34: High | K34: 83024900 | L34: 3.5x0.75x0.75
A35: 32447P | B35: ASY CABLE WHEEL TACH AC EVO/SD70 ACE | C35: PTC | D35: PTC | E35: 1 | F35: Imported (USA) | G35: 411.22
A36: 41A296352PTP10/319/34 | B36: VALVE Part NumberEUMATIC NC/CO (Penalty Magnet Valve) Graham-White 812-142 | C36: PTC | D36: PTC | E36: 1 | F36: Imported (USA) | G36: 404.6239
A37: 84A201176P1 | B37: Pathfinder Control Unit Connector (MU Plug) | C37: Controls (MCA, train control, er etc) | D37: TRAIN CONTROL | E37: 2 | F37: PAC (Brazil, nationalized) | H37: 1480.8637 | I37: 2.404 | J37: High | K37: 85366990 | L37: 7x4x7
A38: 84A201150ACP2 | B38: CROSSING BELL PUSH BUTTON SWITCH | C38: Controls (MCA, train control, er etc) | D38: TRAIN CONTROL | E38: 1 | F38: PAC (Brazil, nationalized) | H38: 2843.3769 | I38: 0.411 | J38: High | K38: 85365090 | L38: 11.8x6.4x8.05
A39: 17FH37A6 | B39: RPS Power Panel - Radio Power Supply - 15V | C39: Controls (MCA, train control, er etc) | D39: MCA | E39: 1 | F39: PAC (Brazil, nationalized) | H39: 2534.8867 | I39: 4.247 | J39: High | K39: 85044030 | L39: 12.8x3.8x9.5
A40: 41A240644P2 | B40: HORN MAGNET VALVE | C40: Controls (MCA, train control, er etc) | D40: TRAIN CONTROL | E40: 1 | F40: PAC (Brazil, nationalized) | H40: 2382.3747 | I40: 3.629 | J40: High | K40: 84812090 | L40: 8.4x3.35x7.5
A41: 41A296352CMP387 | B41: ETHERNET CABLE | C41: Controls (MCA, train control, er etc) | D41: MCA | E41: 1 | F41: PAC (Brazil, nationalized) | H41: 2132.2443 | I41: 0.227 | J41: High | K41: 85444200 | L41: 0x0x0
A42: 41B511393P2 | B42: Battery Knife Switch | C42: Power | D42: POWER | E42: 1 | F42: PAC (Brazil, nationalized) | H42: 1794.8024 | I42: 4.445 | J42: High | K42: 85365090 | L42: 13.5x5.25x7
A43: 84A231123CSP30 | B43: Axle Tac - WRE Part Number: 29266P | C43: PTC | D43: PTC | E43: 1 | F43: Imported (USA) | G43: 205
A44: 84A207079ABP1 | B44: 41A313392DCP18 alternative 300" / | C44: Controls (MCA, train control, er etc) | D44: Wiring | E44: 25 | F44: Imported (USA) | G44: 8.118 | I44: 0.227 | J44: High | K44: 85446000 | L44: 24x20x24
A45: 84A201850P4 | B45: ENGINE CONTROL SWITCH | C45: Controls (MCA, train control, er etc) | D45: TRAIN CONTROL | E45: 1 | F45: Imported (USA) | G45: 171.544
A46: RCCR-PWRCBL | B46: CABLE, PWR, 72V,RA,6.5FT (78").,RR-070,RCCR | C46: Connectivity | D46: VOICE RADIO | E46: 1 | F46: Imported (USA) | G46: 159
A47: 41A216641P158 | B47: SNIO CONNECTOR 3 | C47: Controls (MCA, train control, er etc) | D47: Wiring | E47: 2 | F47: PAC (Brazil, nationalized) | H47: 649.59726 | I47: 0.091 | J47: High | K47: 85366990 | L47: 3x2x3
A48: 41B546301P4 | B48: DOOR INTERLOCK SWITCH | C48: Controls (MCA, train control, er etc) | D48: TRAIN CONTROL | E48: 1 | F48: PAC (Brazil, nationalized) | H48: 1282.4547 | I48: 0.966 | J48: High | K48: 85365090 | L48: 6x2.25x3
A49: 84A201169AKP1 | B49: ENGINEERS HORN BUTTON | C49: Controls (MCA, train control, er etc) | D49: TRAIN CONTROL | E49: 1 | F49: PAC (Brazil, nationalized) | H49: 1139.6202 | I49: 0.463 | J49: High | K49: 85365090 | L49: 9.35x5.3x5.2
A50: 41B549523ABP101 | B50: BATTERY SAVER RESET PUSH BUTTON | C50: Controls (MCA, train control, er etc) | D50: TRAIN CONTROL | E50: 1 | F50: PAC (Brazil, nationalized) | H50: 1117.5838 | I50: 0.215 | J50: High | K50: 85365090 | L50: 3.875x1.625x2.125
A51: 41B564808G1 | B51: A-DIODE ASM | C51: SKID Assembly | D51: SKID (Skid) | E51: 16 | F51: PAC (Brazil, nationalized) | H51: 63.812995 | I51: 0.045 | J51: High | K51: 85411092 | L51: 3x0.75x1.5
A52: 497A365P13 | B52: ALARM AND SIGNAL BELL | C52: Controls (MCA, train control, er etc) | D52: TRAIN CONTROL | E52: 1 | F52: PAC (Brazil, nationalized) | H52: 975.64293 | I52: 0.962 | J52: High | K52: 85318000 | L52: 7x3.25x4.75
A53: 84A201850P5 | B53: AC-ROTARY SWITCH | C53: SKID Assembly | D53: SKID (Skid) | E53: 1 | F53: PAC (Brazil, nationalized) | H53: 946.55154 | I53: 0.177 | J53: High | K53: 85365090 | L53: 5.2x2.9x3.35
A54: 41A216641P235 | B54: GOLINC / ACC POWER CONNECTOR | C54: Controls (MCA, train control, er etc) | D54: Wiring | E54: 3 | F54: PAC (Brazil, nationalized) | H54: 303.73202 | I54: 0.043 | J54: High | K54: 85359090 | L54: 4.52x1.35x6.95
A55: 84A206730P1 | B55: 565" / CABLE 5 PAIR | C55: Controls (MCA, train control, er etc) | D55: Wiring | E55: 50 | F55: PAC (Brazil, nationalized) | H55: 17.964888 | I55: 0.041 | J55: High | K55: 85444900 | L55: 12x0.5x0.5
A56: 41B549523ADP108 | B56: VIGILANCE RESET SWITCH | C56: Controls (MCA, train control, er etc) | D56: TRAIN CONTROL | E56: 1 | F56: PAC (Brazil, nationalized) | H56: 803.96726 | I56: 0.204 | J56: High | K56: 85365090 | L56: 4x2.5x2.5
A57: 41A317303ACP49 | B57: AIR RESERVOIR PRESSURE SENSOR | C57: Controls (MCA, train control, er etc) | D57: MCA | E57: 1 | F57: PAC (Brazil, nationalized) | H57: 749.16041 | I57: 0.045 | J57: High | K57: 90262090 | L57: 2.9x0.5x0.5
A58: 41A216641AMP126 | B58: NIO1D CONNECTOR BACKSHELL | C58: Controls (MCA, train control, er etc) | D58: Wiring | E58: 3 | F58: Imported (USA) | G58: 29.9096 | I58: 0 | J58: High | L58: 0x0x0
A59: 84A215329P1 | B59: ENGINE STOP SWITCH | C59: Controls (MCA, train control, er etc) | D59: TRAIN CONTROL | E59: 1 | F59: PAC (Brazil, nationalized) | H59: 702.98553 | I59: 0.175 | J59: High | K59: 85365090 | L59: 1.75x3.25x2.75
A60: 41A296328ASP3 | B60: BATTERY TEMPERATURE SENSOR | C60: Controls (MCA, train control, er etc) | D60: Power | E60: 1 | F60: PAC (Brazil, nationalized) | H60: 695.08079 | I60: 0.422 | J60: High | K60: 90251990 | L60: 9.5x1.5x9.5
A61: 41A216641ABP45 | B61: DUAL PROCESSOR MODULE CONNECTOR | C61: Controls (MCA, train control, er etc) | D61: Wiring | E61: 2 | F61: PAC (Brazil, nationalized) | H61: 346.97246 | I61: 0.058 | J61: High | K61: 85369090 | L61: 2x1x1
A62: 84A232147P2 | B62: PIN REAR HOLD-DOWN | C62: Controls (MCA, train control, er etc) | D62: TRAIN CONTROL | E62: 30 | F62: PAC (Brazil, nationalized) | H62: 22.802144 | I62: 0.005 | J62: High | K62: 73182900 | L62: 1x0.125x0.125
A63: 41A321053G1 | B63: Power Resistor | C63: Power | D63: Resistor | E63: 1 | F63: PAC (Brazil, nationalized) | H63: 682.45475 | I63: 3.629 | J63: High | K63: 85332900 | L63: 12x3x7.5
A64: 17 pin MS3106-20-29F | B64: Head of Train Device - Padom - J2 Connector | C64: Controls (MCA, train control, er etc) | D64: Wiring | E64: 1 | F64: Imported (USA) | G64: 79.83
A65: 41A216641P157 | B65: SNIO CONNECTOR 2 | C65: Controls (MCA, train control, er etc) | D65: Wiring | E65: 1 | F65: PAC (Brazil, nationalized) | H65: 625.70941 | I65: 0.096 | J65: High | K65: 85366990 | L65: 2.5x1.5x1.5
A66: 41A216641AMP125 | B66: NIO1A CONNECTOR BACKSHELL | C66: Controls (MCA, train control, er etc) | D66: Wiring | E66: 3 | F66: Imported (USA) | G66: 24.1998 | I66: 0.005 | J66: High | L66: 0x0x0
A67: 5088-7000-P4611-0000000-ND‎ | B67: POE Power Connector on SMM2 (M12 FEMALE 0 L-CODED FIELD-WIREA) | C67: Controls (MCA, train control, er etc) | D67: TRAIN CONTROL | E67: 1 | F67: Imported (USA) | G67: 72.41
A68: 41A296352PTP67 | B68: CABLE CSX 12V P WR CBL | C68: Controls (MCA, train control, er etc) | D68: MCA | E68: 1 | F68: Imported (USA) | G68: 71.94
A69: 41A296352PTP69 | B69: CABLE CSX 74V P WR CBL | C69: Controls (MCA, train control, er etc) | D69: MCA | E69: 1 | F69: Imported (USA) | G69: 71.94
A70: 41A216641AMP93 | B70: NIO1E CONNECTOR | C70: Controls (MCA, train control, er etc) | D70: Wiring | E70: 3 | F70: Imported (USA) | G70: 23.9499 | I70: 0.054 | J70: High | L70: 0x0x0
A71: 41B549523ADP1 | B71: Black push Button | C71: SKID Assembly | D71: Use in place of al levers and other push buttons | E71: 1 | F71: PAC (Brazil, nationalized) | H71: 565.56673 | I71: 0.142 | J71: High | K71: 85365090 | L71: 4x2.125x2.125
A72: 41B549523ADP2 | B72: SWITCH PUSH BUTTON | C72: SKID Assembly | D72: SKID (Skid) | E72: 1 | F72: PAC (Brazil, nationalized) | H72: 542.71095 | I72: 0.141 | J72: High | K72: 85365090 | L72: 1.95x2.7x1.8
A73: 41A296328APP5 | B73: BATTERY CURRENT SENSOR | C73: Controls (MCA, train control, er etc) | D73: MCA | E73: 1 | F73: PAC (Brazil, nationalized) | H73: 530.71617 | I73: 0.575 | J73: High | K73: 90303390 | L73: 4.75x1.25x4
A74: 41A216641AMP103 | B74: NIO1D CONNECTOR | C74: Controls (MCA, train control, er etc) | D74: Wiring | E74: 3 | F74: Imported (USA) | G74: 21.2198 | I74: 0.045 | J74: High | L74: 1.5x1x1.5
A75: 16246P | B75: Flexi-Axle - WRE Part Number: 16246P | C75: PTC | D75: PTC | E75: 1 | F75: Imported (USA) | G75: 59.75
A76: 41A216641AMP99 | B76: NIO1B CONNECTOR | C76: Controls (MCA, train control, er etc) | D76: Wiring | E76: 3 | F76: Imported (USA) | G76: 19.67 | I76: 0 | J76: High | L76: 0x0x0
A77: 41A216641AMP123 | B77: NIO1F CONNECTOR BACKSHELL | C77: Controls (MCA, train control, er etc) | D77: Wiring | E77: 3 | F77: Imported (USA) | G77: 19.5574 | I77: 0.02 | J77: High | L77: 0x0x0
A78: 41A216641P140 | B78: Part NumberEUMATIC OPERATING UNIT CONNECTOR - 5 | C78: Air | D78: Fastbrake | E78: 1 | F78: PAC (Brazil, nationalized) | H78: 480.42768 | I78: 0.091 | J78: High | K78: 85369090 | L78: 4x2x4
A79: 41A216641AMP100 | B79: NIO1C CONNECTOR | C79: Controls (MCA, train control, er etc) | D79: Wiring | E79: 3 | F79: Imported (USA) | G79: 19.173 | I79: 0 | J79: High | L79: 0x0x0
A80: 41A216641P53 | B80: SNIO CONNECTOR 1 | C80: Controls (MCA, train control, er etc) | D80: Wiring | E80: 1 | F80: PAC (Brazil, nationalized) | H80: 472.91303 | I80: 0.093 | J80: High | K80: 85366990 | L80: 5.85x1.95x3.9
A81: 41A216641AMP86 | B81: NIO1F CONNECTOR | C81: Controls (MCA, train control, er etc) | D81: Wiring | E81: 3 | F81: Imported (USA) | G81: 18.9357 | I81: 0.032 | J81: High | L81: 3.95x1.25x6.65
A82: 41A216641P141 | B82: Part NumberEUMATIC OPERATING UNIT CONNECTOR - 7 | C82: Air | D82: Fastbrake | E82: 1 | F82: PAC (Brazil, nationalized) | H82: 455.99946 | I82: 0.068 | J82: High | K82: 85369090 | L82: 4x2x3
A83: 41A212414P35 | B83: CIRCUIT BREAKER 1P | C83: SKID Assembly | D83: SKID (Skid) | E83: 6 | F83: PAC (Brazil, nationalized) | H83: 75.61832 | I83: 0.095 | J83: High | K83: 85362000 | L83: 3.1x0.7x2.45
A84: 41A212414P73 | B84: BATT CHARGER & COMP CIRCUIT BREAKER (2P, 20A / 50A) | C84: Controls (MCA, train control, er etc) | D84: Circuit Breaker | E84: 1 | F84: PAC (Brazil, nationalized) | H84: 443.6886 | I84: 0.39 | J84: High | K84: 85362000 | L84: 3x2x2.55
A85: 41A212414P76 | B85: FUEL PUMP CIRCUIT BREAKER (4P, 25A / 45A) | C85: Controls (MCA, train control, er etc) | D85: Circuit Breaker | E85: 1 | F85: PAC (Brazil, nationalized) | H85: 427.111 | I85: 0.386 | J85: High | K85: 85362000 | L85: 2.9x2.45x3.05
A86: 41A296326DDP52 | B86: EMU CONNECTOR | C86: Controls (MCA, train control, er etc) | D86: Wiring | E86: 1 | F86: PAC (Brazil, nationalized) | H86: 411.95479 | I86: 0.113 | J86: High | K86: 85359090
A87: 84B523158P1 | B87: RESERVOIR DRAIN VALVE HEATER # 1 | C87: Controls (MCA, train control, er etc) | D87: TRAIN CONTROL | E87: 1 | F87: PAC (Brazil, nationalized) | H87: 397.80678 | I87: 0.272 | J87: High | K87: 85168090 | L87: 9x1.5x9
A88: 41A216641P142 | B88: Part NumberEUMATIC OPERATING UNIT CONNECTOR - 8 | C88: Air | D88: Fastbrake | E88: 1 | F88: PAC (Brazil, nationalized) | H88: 386.54646 | I88: 0.054 | J88: High | K88: 85369090 | L88: 4x1x4
A89: 41A216641AMP98 | B89: NIO1A CONNECTOR | C89: Controls (MCA, train control, er etc) | D89: Wiring | E89: 3 | F89: Imported (USA) | G89: 15.455 | I89: 0.053 | J89: High | L89: 0x0x0
A90: 41A216641ABP153 | B90: HELPER'S RADIO SPEAKER CONNECTOR | C90: Controls (MCA, train control, er etc) | D90: Wiring | E90: 1 | F90: Imported (USA) | G90: 45.7356
A91: 17LV66BD52 | B91: CONSIST MANAGER SYSTEM RELAY | C91: Controls (MCA, train control, er etc) | D91: TRAIN CONTROL | E91: 1 | F91: PAC (Brazil, nationalized) | H91: 376.72768 | I91: 2.313 | J91: High | K91: 85364900 | L91: 4.5x5.25x4.5
A92: 17LV66J10 | B92: RELAYS | C92: Controls (MCA, train control, er etc) | D92: TRAIN CONTROL | E92: 1 | F92: PAC (Brazil, nationalized) | H92: 358.90086 | I92: 2.155 | J92: High | K92: 85364900 | L92: 5.8x3.5x4.5
A93: 41A296326DDP78 | B93: GEW LAYER 3 ETH ERNET SWITCH POWER PLUG | C93: Controls (MCA, train control, er etc) | D93: MCA | E93: 1 | F93: PAC (Brazil, nationalized) | H93: 335.09466 | I93: 0.045 | J93: High | K93: 85366990 | L93: 3x1x2
A94: 41A265714P22 | B94: SOCKET CONTACT, .75" | C94: Controls (MCA, train control, er etc) | D94: Wiring | E94: 109 | F94: PAC (Brazil, nationalized) | H94: 2.8124536 | I94: 0 | J94: High | K94: 85369090 | L94: 0.75x0.1x0.1
A95: 41A216641ABP139 | B95: DISTRIBUTED POWER RADIO MODULE BASE CONNECTOR | C95: Controls (MCA, train control, er etc) | D95: Wiring | E95: 1 | F95: PAC (Brazil, nationalized) | H95: 282.40577 | I95: 0.066 | J95: High | K95: 85366990 | L95: 2.5x1.25x1.25
A96: 84B104674ASP14 | B96: AMBIENT AIR TEMPERATURE SENSOR PLUG | C96: Controls (MCA, train control, er etc) | D96: MCA | E96: 1 | F96: PAC (Brazil, nationalized) | H96: 262.78624 | I96: 0.027 | J96: High | K96: 85366990 | L96: 3.5x2x3.25
A97: 41A316591P1 | B97: Card Holder 3 Slot | C97: Controls (MCA, train control, er etc) | D97: TRAIN CONTROL | E97: 1 | F97: PAC (Brazil, nationalized) | H97: 198.40705 | I97: 1.315 | J97: High | K97: 39269090 | L97: 17x1.25x12.625
A98: 41A212414P31, 41A212414P3 2-Pole Option | B98: AUTOCOUPLER CIRCUIT BREAKER, CCB(2A) | C98: Controls (MCA, train control, er etc) | D98: Circuit Breaker | E98: 1 | F98: Imported (USA) | G98: 22.0206 | I98: 0.093 | J98: High | K98: 85362000 | L98: 2.5x0.65x3.05
A99: 41A265713P22 | B99: PIN | C99: Controls (MCA, train control, er etc) | D99: Wiring | E99: 82 | F99: PAC (Brazil, nationalized) | H99: 2.0913665 | I99: 0 | J99: High | K99: 85389090 | L99: 1x0.001x0.001
A100: 41A212414P3 | B100: DYNAMIC BRAKE CIRCUIT BREAKER (1P, 2A) | C100: Controls (MCA, train control, er etc) | D100: Circuit Breaker | E100: 1 | F100: PAC (Brazil, nationalized) | H100: 153.88089 | I100: 0.193 | J100: High | K100: 85362000 | L100: 3.1x1.45x2.5
A101: 41A212414P14 | B101: PTC RADIO CIRCUIT BREAKER (2P, 15A) | C101: Controls (MCA, train control, er etc) | D101: Circuit Breaker | E101: 1 | F101: PAC (Brazil, nationalized) | H101: 153.73571 | I101: 0.195 | J101: High | K101: 85362000 | L101: 2.5x1.5x3.25
...

Sheet Executive Summary (P&L)
A1: P&L PATHFINDER - REAL PRICE (Material Pricing / Approval Summary methodology)
A3: Exchange Rate (USD->BRL): | B3: 5.1
A4: Total Deal Margin (TDM): | B4: 0.45 | D4: <- editable. Automatically updates Net Price and Client Price below.
A5: PIS/COFINS (blended, real NCM where available): | B5: 0.1006
A6: ICMS: | B6: 0.18
A7: IPI (blended, real NCM where available): | B7: 0.0969
B8: BRL | C8: USD
A9: 1) COST (Raw Cost + TP + Freight + Import Duty)
A10: Raw Cost - Imported Items (BOM USD x Qty x FX) | B10: 1346980.9 | C10: =B10/$B$3
A11: Raw Cost - PAC Items (already nationalized, all-in local cost) | B11: 166060.16 | C11: =B11/$B$3
A12: TP - Transfer Price (13%/17.2% per item group; this is WBT USA's own margin) | B12: 198163.69 | C12: =B12/$B$3
A13: International Freight (real, China Gate quote, 1.23%) | B13: 18998.55 | C13: =B13/$B$3
A14: II - Import Duty (blended 17.96%, real NCM where available) | B14: 280915.82 | C14: =B14/$B$3
A15: Domestic Freight (real, China Gate quote, Santos->Betim/Contagem) | B15: 21753.1 | C15: =B15/$B$3
A16: Supermetal - GDT Integration/Assembly (railcar modification, direct cost) | B16: 707790.6 | C16: =B16/$B$3
A17: FINAL COST (with TP): | B17: =SUM(B10:B16) | C17: =B17/$B$3
A19: 2) MARGIN (TDM applied on cost WITHOUT TP; TP is added back afterwards with no markup)
A20: Base for margin (Final Cost - TP) | B20: =B17-B12 | C20: =B20/$B$3
A21: Net Price w/o TP (Base / (1 - TDM)) | B21: =B20/(1-$B$4) | C21: =B21/$B$3
A22: NET PRICE ('OUR PRICE' - cost + margin, before pass-through taxes): | B22: =B21+B12 | C22: =B22/$B$3
A24: 3) PASS-THROUGH TAXES (do not affect our margin - the client pays, client can credit part of it)
A25: + PIS/COFINS (gross-up, tax-inclusive) | B25: =B22/(1-$B$5) | C25: =B25/$B$3
A26: + ICMS (gross-up, tax-inclusive, stacked on top of PIS/COFINS) | B26: =B25/(1-$B$6) | C26: =B26/$B$3
A27: + IPI (added on top, % of the value already including ICMS) | B27: =B26*$B$7 | C27: =B27/$B$3
A28: FINAL CLIENT PRICE (all taxes included): | B28: =B26+B27 | C28: =B28/$B$3
A30: Notes / Assumptions:
A31: - Methodology: 'Material Pricing' + 'Approval Summary' tabs of Material Pricing.xlsm (P&L Old was discarded - its formulas are broken / #REF!).
A32: - TP is treated as WBT USA's own margin (GM WBT USA); it feeds the cost base but is excluded from WBT Brazil's own margin base (TDM = (TP + GM BRZ) / Net Price).
A33: - International and Domestic Freight: real values from the China Gate import cost quote (Planilha de Custos de Importacao - Pathfinder - Set 26.xlsx), not the old 9%/3% assumptions.
A34: - II/IPI/PIS-COFINS: real per-NCM rate (Material Pricing's 'II' tab) for the 6 priced imported items with a confirmed NCM; worst-case flat rate (our old blended assumption) for the other 41 without one.
A35: - ICMS: flat 18% (same value used in Material Pricing's own real example).
A36: - 88 PAC items are summed as a single block (already an all-in local cost, not decomposed into TP/freight/duty).
A37: - Supermetal's GDT Integration/Assembly cost (railcar refurbishment: lid, door, ladder, harnesses, battery skid, Fastbrake piping, AC, ballast) is included as a direct cost, feeding the same margin base as the equipment - see the 'GDT Integration and Assembly' tab in the main working file for the line-item breakdown.
A38: - 27 items still without a cost quote (Missing) are NOT included in this total - see the Item List tab (Cost Source = MISSING).
A39: - QQP (service taxes) and ISS (tax on the GDT integration/labor rollup) were disregarded for now, as requested.

Sheet Price Calc Detail
A1: PRICE CALCULATION DETAIL - source and formula for every number
A2: Use this tab to answer 'why is this number X' - every line cites its source.
A4: 0) REALITY CHECK vs. US domestic price
A5: US Domestic Reference Price (input - type the real one here): | B5: 900000
A6: Our Price (Net - cost + margin, before Brazilian pass-through taxes): | B6: 945272.43 | C6: <- this is the number that is actually comparable to a US domestic sale (no BR import/consumption tax).
A7: Final Client Price (with all Brazilian taxes): | B7: 1405909.3
A8: Gap vs. US reference (Net Price): | B8: =B6-B5 | C8: =B8/B5
A9: Gap vs. US reference (Final Client Price): | B9: =B7-B5 | C9: =B9/B5
A10: KEY POINT: our Net Price is close to the US reference price - the big jump to the Final Client Price comes entirely from Brazilian
A11: import duty (II) and consumption taxes (IPI/PIS/COFINS/ICMS), which do not exist in a US domestic sale and would apply just the
A12: same whether we import components or a finished, ready-built railcar (a finished vehicle may in fact face a higher/different II bracket -
A13: worth confirming with an auto/rail import specialist before assuming 'buy it finished' avoids this tax cascade).
A15: 1) FULL WATERFALL (matches the 'Executive Summary (P&L)' tab, expanded with sources)
A16: Step | B16: Formula / Logic | C16: BRL | D16: USD | E16: Multiplier vs. Final Cost (subtotals only) | F16: Source / Justification
A17: Raw Cost - Imported Items | B17: BOM USD unit x Qty x FX rate, summed over 47 priced imported items | C17: 1346980.9 | D17: 264113.91 | E17: - | F17: Final Cost List tab, column F (BOM Price USD Unit) x column E (Quantity), FX from Material Pricing.xlsm 'RATES' tab
A18: Raw Cost - PAC Items | B18: Sum of PAC unit cost (BRL) x Qty over 88 PAC-sourced items | C18: 166060.16 | D18: 32560.816 | E18: - | F18: 7-PAC Item Costs.xlsx 'aco_cost' field per item, already a fully-loaded local manufacturing cost (materials+labor+overhead)
A19: TP - Transfer Price | B19: 13% on items that already carried some TP historically; 17.2% on items that had none | C19: 198163.69 | D19: 38855.625 | E19: - | F19: Matheus's directive this session; 17.2%/0% split originally sourced from the color-coded review copy (yellow/green)
A20: International Freight | B20: 1.2295642% of (Raw Cost + TP) | C20: 18998.55 | D20: 3725.2059 | E20: - | F20: 'Planilha de Custos de Importacao - Pathfinder - Set 26.xlsx' (China Gate customs broker quote), Frete+Seguro / Product Value
A21: II - Import Duty | B21: Blended 17.96% on (Raw Cost+TP+Freight): real per-NCM rate for the 6 items with a confirmed NCM, worst-case 18% flat for the other 41 | C21: 280915.82 | D21: 55081.533 | E21: - | F21: Material Pricing.xlsm 'II' tab (real NCM lookup) + our prior flat assumption as fallback
A22: Domestic Freight | B22: Real flat quote for the whole shipment (Santos -> Betim/Contagem, MG) | C22: 21753.1 | D22: 4265.3137 | E22: - | F22: China Gate quote 'Despesas de Importacao' tab: Siscomex, despachante, armazenagem, road transport, Marinha Mercante, etc.
A23: Supermetal - GDT Integration/Assembly | B23: Direct cost: railcar refurbishment (lid, door, ladder, harnesses, battery skid, Fastbrake piping, AC, ballast) | C23: 707790.6 | D23: 138782.47 | E23: - | F23: 'GDT Integration and Assembly' tab, sum of Direct Cost BRL column (18 line items)
A24: FINAL COST (with TP): | C24: 2740662.8 | D24: 537384.87 | E24: 1.000x (baseline)
A26: 2) MARGIN
A27: Base for margin | B27: Final Cost - TP (TP is excluded from our own margin base - it's WBT USA's margin, not ours) | F27: Approval Summary tab of Material Pricing.xlsm: TDM = (TP + GM_BRZ) / Net Price. Algebraically this is equivalent to computing margin on (cost - TP) and adding TP back after, which is what this line does.
A28: Target margin (TDM) | B28: Editable - see the Executive Summary (P&L) tab cell B4 | F28: Matheus's target for this exercise: 45%
A29: NET PRICE ('OUR PRICE'): | C29: 4820889.4 | D29: 945272.43 | E29: 1.759x
A31: 3) PASS-THROUGH TAXES (client pays; do not affect our margin)
A32: PIS/COFINS | B32: Net Price / (1 - 10.06%) - gross-up, blended real-NCM rate | F32: Material Pricing.xlsm 'II' tab (real per-NCM PIS+COFINS) for known items, worst-case 9.25% for the rest
A33: ICMS | B33: Previous subtotal / (1 - 18%) - gross-up, stacked on top of PIS/COFINS | F33: Flat 18%, matches Material Pricing's own worked example. NOT yet validated against the client's specific destination-state ICMS rate (Tabela ICMS / Aliquotas Basicas tabs have the real origin-destination matrix if needed).
A34: IPI | B34: Previous subtotal x blended IPI% - added on top, not a gross-up | F34: Material Pricing.xlsm 'II' tab (real per-NCM IPI) for known items, worst-case 9.75% for the rest
A35: FINAL CLIENT PRICE: | C35: 7170137.3 | D35: 1405909.3 | E35: 2.616x
A37: 4) ASSUMPTIONS REGISTER (challenge a specific input here, not the whole number)
A38: Assumption | B38: Value Used | C38: Confidence | D38: Where it could be wrong
A39: Exchange Rate | B39: 5.10 BRL/USD | C39: Medium | D39: Fixed snapshot from Material Pricing.xlsm; will drift with the real FX on invoice date
A40: TP rate split | B40: 13% / 17.2% | C40: Low-Medium | D40: Arbitrary split chosen this session, not from an official WBT transfer pricing policy document
A41: International Freight | B41: 1.23% of value | C41: High | D41: Real broker quote, but only a simulation per the quote's own disclaimer - confirm with actual booking
A42: Domestic Freight | B42: R$21,753.10 flat | C42: High | D42: Real broker quote for Santos->Betim/Contagem specifically; changes if origin/destination changes
A43: II (Import Duty) | B43: 17.96% blended (6 of 47 imported items on real NCM) | C43: Medium | D43: 41 of 47 imported items still use the worst-case 18% default - no NCM confirmed for them yet
A44: PIS/COFINS | B44: 10.06% blended | C44: Medium | D44: Same NCM-coverage gap as II
A45: IPI | B45: 9.69% blended | C45: Medium | D45: Same NCM-coverage gap as II
A46: ICMS | B46: 18% flat | C46: Low-Medium | D46: Not looked up per origin-destination UF pair; real rate could be lower (interstate) or have RBC reduction
A47: Total Deal Margin (TDM) | B47: 45% | C47: N/A - business decision | D47: This is the single biggest lever on the final price - see the sensitivity table below
A48: PAC items | B48: Treated as one all-in lump, no TP/freight/duty decomposition | C48: High | D48: PAC cost is a genuine local Brazilian manufacturing cost buildup, not an import transaction
A49: Missing items | B49: 27 items excluded (no cost yet) | C49: N/A | D49: Final price will increase once these get quotes - see 'Missing Items' tab
A50: Supermetal / GDT rollup | B50: Treated as local cost, no import duty applied (correct, it's Brazilian labor+materials) | C50: Medium | D50: Does not yet include ISS (service tax) on the labor portion - disregarded for now per Matheus's instruction
A52: 5) MARGIN SENSITIVITY (same cost base, different TDM targets)
A53: TDM | B53: Net Price (Our Price) USD | C53: Final Client Price USD
A54: 0.3 | B54: 751040.26 | C54: 1117026.6
A56: 0.35 | B56: 805823.69 | C56: 1198506.3
A58: 0.4 | B58: 869737.7 | C58: 1293566
A60: 0.45 | B60: 945272.43 | C60: 1405909.3
A62: 0.5 | B62: 1035914.1 | C62: 1540721.2
A64: 0.55 | B64: 1146698.4 | C64: 1705491.3
A66: Notes:
A67: - This tab is a companion to 'Executive Summary (P&L)' - same numbers, but every line explains itself.
A68: - QQP (service taxes) and ISS on the Supermetal/labor portion were disregarded for now, as requested - the final price could increase once those are added.

Sheet Simulation
A1: SIMULATION - what really makes the Pathfinder Iron Ore Car expensive
A2: Change the two yellow switches; the comparison table on the right never depends on them.
A4: SWITCHES
A5: Remove import duty (II) from everything? (1 = yes, 0 = no) | B5: 0
A6: Battery sets (2 = current BOM, 1 = a single set) | B6: 2
A8: BASE VALUES (read from the P&L tab)
A9: Exchange rate | B9: ='Executive Summary (P&L)'!B3
A10: Total Deal Margin (TDM) | B10: ='Executive Summary (P&L)'!B4
A11: PIS/COFINS | B11: ='Executive Summary (P&L)'!B5
A12: ICMS | B12: ='Executive Summary (P&L)'!B6
A13: IPI | B13: ='Executive Summary (P&L)'!B7
A14: US domestic reference price (USD, input) | B14: 900000
A17: SCENARIOS
B18: Selected (switches) - BRL | C18: Selected (switches) - USD | D18: Base (current) - BRL | E18: Base (current) - USD | F18: No import duty (II) - BRL | G18: No import duty (II) - USD | H18: 1 battery set - BRL | I18: 1 battery set - USD | J18: No II + 1 battery set - BRL | K18: No II + 1 battery set - USD
A19: Raw cost - imported items | B19: =$B$48+$C$48*($B$6) | C19: =B19/$B$9 | D19: =$B$48+$C$48*(2) | E19: =D19/$B$9 | F19: =$B$48+$C$48*(2) | G19: =F19/$B$9 | H19: =$B$48+$C$48*(1) | I19: =H19/$B$9 | J19: =$B$48+$C$48*(1) | K19: =J19/$B$9
A20: Raw cost - PAC items | B20: =$B$49 | C20: =B20/$B$9 | D20: =$B$49 | E20: =D20/$B$9 | F20: =$B$49 | G20: =F20/$B$9 | H20: =$B$49 | I20: =H20/$B$9 | J20: =$B$49 | K20: =J20/$B$9
A21: TP - Transfer Price | B21: =$B$50+$C$50*($B$6) | C21: =B21/$B$9 | D21: =$B$50+$C$50*(2) | E21: =D21/$B$9 | F21: =$B$50+$C$50*(2) | G21: =F21/$B$9 | H21: =$B$50+$C$50*(1) | I21: =H21/$B$9 | J21: =$B$50+$C$50*(1) | K21: =J21/$B$9
A22: International freight | B22: =$B$51+$C$51*($B$6) | C22: =B22/$B$9 | D22: =$B$51+$C$51*(2) | E22: =D22/$B$9 | F22: =$B$51+$C$51*(2) | G22: =F22/$B$9 | H22: =$B$51+$C$51*(1) | I22: =H22/$B$9 | J22: =$B$51+$C$51*(1) | K22: =J22/$B$9
A23: II - Import duty | B23: =($B$52+$C$52*($B$6))*(1-($B$5)) | C23: =B23/$B$9 | D23: =($B$52+$C$52*(2))*(1-(0)) | E23: =D23/$B$9 | F23: =($B$52+$C$52*(2))*(1-(1)) | G23: =F23/$B$9 | H23: =($B$52+$C$52*(1))*(1-(0)) | I23: =H23/$B$9 | J23: =($B$52+$C$52*(1))*(1-(1)) | K23: =J23/$B$9
A24: Domestic freight | B24: =$B$53 | C24: =B24/$B$9 | D24: =$B$53 | E24: =D24/$B$9 | F24: =$B$53 | G24: =F24/$B$9 | H24: =$B$53 | I24: =H24/$B$9 | J24: =$B$53 | K24: =J24/$B$9
A25: Supermetal - refurbishment / integration | B25: =$B$54 | C25: =B25/$B$9 | D25: =$B$54 | E25: =D25/$B$9 | F25: =$B$54 | G25: =F25/$B$9 | H25: =$B$54 | I25: =H25/$B$9 | J25: =$B$54 | K25: =J25/$B$9
A26: FINAL COST (with TP): | B26: =SUM(B19:B25) | C26: =B26/$B$9 | D26: =SUM(D19:D25) | E26: =D26/$B$9 | F26: =SUM(F19:F25) | G26: =F26/$B$9 | H26: =SUM(H19:H25) | I26: =H26/$B$9 | J26: =SUM(J19:J25) | K26: =J26/$B$9
A27: Base for margin (Final Cost - TP) | B27: =B26-B21 | C27: =B27/$B$9 | D27: =D26-D21 | E27: =D27/$B$9 | F27: =F26-F21 | G27: =F27/$B$9 | H27: =H26-H21 | I27: =H27/$B$9 | J27: =J26-J21 | K27: =J27/$B$9
A28: Net price w/o TP (Base / (1 - TDM)) | B28: =B27/(1-$B$10) | C28: =B28/$B$9 | D28: =D27/(1-$B$10) | E28: =D28/$B$9 | F28: =F27/(1-$B$10) | G28: =F28/$B$9 | H28: =H27/(1-$B$10) | I28: =H28/$B$9 | J28: =J27/(1-$B$10) | K28: =J28/$B$9
A29: NET PRICE ('OUR PRICE'): | B29: =B28+B21 | C29: =B29/$B$9 | D29: =D28+D21 | E29: =D29/$B$9 | F29: =F28+F21 | G29: =F29/$B$9 | H29: =H28+H21 | I29: =H29/$B$9 | J29: =J28+J21 | K29: =J29/$B$9
A30: + PIS/COFINS (gross-up) | B30: =B29/(1-$B$11) | C30: =B30/$B$9 | D30: =D29/(1-$B$11) | E30: =D30/$B$9 | F30: =F29/(1-$B$11) | G30: =F30/$B$9 | H30: =H29/(1-$B$11) | I30: =H30/$B$9 | J30: =J29/(1-$B$11) | K30: =J30/$B$9
A31: + ICMS (gross-up) | B31: =B30/(1-$B$12) | C31: =B31/$B$9 | D31: =D30/(1-$B$12) | E31: =D31/$B$9 | F31: =F30/(1-$B$12) | G31: =F31/$B$9 | H31: =H30/(1-$B$12) | I31: =H31/$B$9 | J31: =J30/(1-$B$12) | K31: =J31/$B$9
A32: + IPI (on top) | B32: =B31*$B$13 | C32: =B32/$B$9 | D32: =D31*$B$13 | E32: =D32/$B$9 | F32: =F31*$B$13 | G32: =F32/$B$9 | H32: =H31*$B$13 | I32: =H32/$B$9 | J32: =J31*$B$13 | K32: =J32/$B$9
A33: FINAL CLIENT PRICE: | B33: =B31+B32 | C33: =B33/$B$9 | D33: =D31+D32 | E33: =D33/$B$9 | F33: =F31+F32 | G33: =F33/$B$9 | H33: =H31+H32 | I33: =H33/$B$9 | J33: =J31+J32 | K33: =J33/$B$9
A36: WHAT DRIVES THE FINAL CLIENT PRICE (base case)
A37: Removing ALL import duty (II) lowers the Final Client Price by | B37: =D33-F33 | C37: =B37/$B$9
A38: Local output taxes (PIS/COFINS + ICMS + IPI) add on top of Net Price | B38: =D33-D29 | C38: =B38/$B$9
A39: Local taxes are how many times bigger than the II effect? | B39: =B38/B37
A40: Final Client Price with NO II and 1 battery set, vs. US reference | B40: =J33/$B$9 | C40: =B40/$B$14-1
A42: - II (import duty) sits inside the cost, so it is multiplied by the margin (1/(1-TDM)) and then by the local tax cascade - removing it is worth about 2.7x its face value in the final price.
A43: - Even so, the local output taxes (PIS/COFINS, ICMS, IPI) stack on the whole price and outweigh the II effect - that is the point of this tab.
A44: - Battery sets: II, TP and freight of the batteries scale with the quantity; the row values come from the Final Cost List (84A222059P5, group without historical TP -> 17.2%, no confirmed NCM -> II 18%).
A46: BASE VALUES (read from the P&L tab)
B47: Imported items, excluding batteries | C47: Batteries - value per set (current BOM has 2)
A48: Raw cost - imported items | B48: ='Executive Summary (P&L)'!B10-2*C48 | C48: 79995.64
A49: Raw cost - PAC items | B49: ='Executive Summary (P&L)'!B11 | C49: 0
A50: TP - Transfer Price | B50: ='Executive Summary (P&L)'!B12-2*C50 | C50: 13759.25
A51: International freight | B51: ='Executive Summary (P&L)'!B13-2*C51 | C51: 1152.78
A52: II - Import duty | B52: ='Executive Summary (P&L)'!B14-2*C52 | C52: 17083.38
A53: Domestic freight | B53: ='Executive Summary (P&L)'!B15 | C53: 0
A54: Supermetal - refurbishment / integration | B54: ='Executive Summary (P&L)'!B16 | C54: 0
A58: 6) REFERENCE: FINISHED US UNIT IMPORTED AS-IS (buy the ready-built US$900k Pathfinder and land it in Brazil)
A59: Exchange rate used for this reference (differs from the scenario FX above) | B59: 5.15
B60: BRL | C60: USD
A61: US price (finished product, unchanged) | B61: =C61*$B$59 | C61: 900000
A62: + International freight + insurance | B62: =C62*$B$59 | C62: 80490
A63: + Customs / import expenses | B63: =C63*$B$59 | C63: 16842.857
A64: + All import taxes (II, IPI, PIS/COFINS, ICMS) | B64: =C64*$B$59 | C64: 715697.91
A65: LANDED IN BRAZIL: | B65: =C65*$B$59 | C65: =SUM(C61:C64)
A67: vs. each scenario's Final Client Price (positive = landed-finished-unit costs more)
A68: Base (current) | B68: =C65-E33
A69: No import duty (II) | B69: =C65-G33
A70: 1 battery set | B70: =C65-I33
A71: No II + 1 battery set | B71: =C65-K33
A73: - Source: read LIVE from 'Planilha de Custos de Importacao - Pathfinder completo- Set 26.xlsx', sheet 'Pathfinder Pronto' (cells H24, I22, I26, I27, I28, I35, I56). Different scope than the 4 scenarios above: this is a finished, already-built unit (no Wabtec Brasil margin, no TP, no Supermetal refurbishment - it's a straight import of a complete product), so it is not an apples-to-apples 5th column of the scenario table.
