Workbook

Sheet Executive Summary (GDT Project)
A1: EXECUTIVE SUMMARY - MRS PATHFINDER GDT RAILCAR PROPOSAL
A2: Exchange Rate: | B2: USD 1.00 = BRL 5.16
A3: Profit Margin (%): | B3: 0.45 | C3: <- editable input. Change this to update the sale price table below.
A5: 1) COST / PURE BREAKEVEN (initial Pathfinder price, no margin)
A6: Project Module | B6: Cost BRL (Excl. Taxes) | C6: Cost USD (Excl. Taxes) | D6: Cost BRL (Incl. Taxes) | E6: Cost USD (Incl. Taxes) | F6: % of Total
A7: 1. Equipment & Components (BOM Pathfinder + SKID) | B7: =SUM('Final Cost List'!K2:K163) | C7: 350000 | D7: =SUM('Final Cost List'!L2:L163) | E7: =SUM('Final Cost List'!J2:J163) | F7: =B7/$B$9
A8: 2. Adaptation, Container & Labor (Rollup GDT) | B8: =SUM('GDT Integration and Assembly'!C2:C18) | C8: =SUM('GDT Integration and Assembly'!D2:D18) | D8: =SUM('GDT Integration and Assembly'!E2:E18) | E8: =SUM('GDT Integration and Assembly'!F2:F18) | F8: =B8/$B$9
A9: TOTAL CONSOLIDATED GDT RAILCAR PROJECT (COST) | B9: =SUM(B7:B8) | C9: =SUM(C7:C8) | D9: =SUM(D7:D8) | E9: =SUM(E7:E8) | F9: 1
A11: 2) SALE PRICE WITH PROFIT MARGIN (driven by cell B3)
A12: Project Module | B12: Sale Price BRL (Excl. Taxes) | C12: net Price USD (Excl. Taxes) | D12: Sale Price BRL (Incl. Taxes) | E12: Sale Price USD (Incl. Taxes) | F12: % of Total
A13: 1. Equipment & Components (BOM Pathfinder + SKID) | B13: =B7*(1+$B$3) | C13: =C7/(1-$B$3) | D13: =D7*(1+$B$3) | E13: =E7*(1+$B$3) | F13: =B13/$B$15
A14: 2. Adaptation, Container & Labor (Rollup GDT) | B14: =B8*(1+$B$3) | C14: =C8/(1-$B$3) | D14: =D8*(1+$B$3) | E14: =E8*(1+$B$3) | F14: =B14/$B$15
A15: TOTAL CONSOLIDATED GDT RAILCAR PROJECT (SALE PRICE) | B15: =SUM(B13:B14) | C15: =SUM(C13:C14) | D15: =SUM(D13:D14) | E15: =SUM(E13:E14) | F15: 1

Sheet Final Cost List
A1: Part Number | B1: Description | C1: System | D1: SubSystem | E1: Quantity | F1: BOM Price (USD Unit) | G1: Final Unit Price USD (Excluding Taxes) | H1: Final Total Price USD (Excluding Taxes) | I1: Final Unit Price USD (Including Taxes) | J1: Final Total Price USD (Including Taxes) | K1: Total Price BRL (Excluding Taxes) | L1: Total Price BRL (Including Taxes) | M1: PAC Price (BRL Unit) | N1: BOM Price (USD Unit) | O1: Cost Source | P1: Status / Notes | R1: Simple Item Category | S1: Nationalization Status | T1: Import Scenario (BOM+TP+Freight+Duty, BRL Incl. Tax) | U1: Nationalized/PAC Price (BRL Incl. Tax) | V1: Cheaper Option | W1: Peso (kg) | X1: NCM | Y1: Dimensions (C x A x L, in) | Z1: Weight Data Source | AA1: Peso - Confidence
A2: 41A296352CMP437 | B2: Dual Processor Module (DPM)+ LXA (Distributed Power Radio) | C2: Controls (MCA, train control, er etc) | D2: LXA | E2: 1 | F2: 63100.819 | G2: 96312.869 | H2: 96312.869 | I2: 120602.14 | J2: 120602.14 | K2: 496974.41 | L2: 622307.04 | O2: Imported BOM (USA) | P2: TP included; international freight updated to 9% | W2: 4.536 | X2: 90328990 | Z2: Engineering weight (Harland Updated Weights.xlsx) | AA2: High
A3: 37495P | B3: KIT ETMS VIRGIN TRAINS FEC EVO44 | C3: PTC | D3: PTC KIT MASTER | E3: 1 | F3: 28529 | G3: 43544.757 | H3: 43544.757 | I3: 54526.368 | J3: 54526.368 | K3: 224690.95 | L3: 281356.06 | O3: Imported BOM (USA) | P3: Direct supplier purchase; TP excluded; international freight 9% | W3: 45.359 | Z3: Engineering weight (Harland Updated Weights.xlsx) | AA3: High
A4: 84A222059P5 | B4: BATTERIES | C4: Power | D4: POWER | E4: 2 | F4: 15685.42 | G4: 20427.624 | H4: 40855.249 | I4: 25579.294 | J4: 51158.589 | K4: 210813.08 | L4: 263978.32 | O4: Imported BOM (USA) | P4: TP included; international freight updated to 9% | W4: 1123.095 | Z4: Engineering weight (Harland Updated Weights.xlsx) | AA4: High
A5: 41A296352LUG24 | B5: CSX Antenna Enclosure Arrangement | C5: Connectivity | D5: ANTENNA KIT Master | E5: 1 | F5: 30000 | G5: 39069.96 | H5: 39069.96 | I5: 48923.065 | J5: 48923.065 | K5: 201600.99 | L5: 252443.02 | O5: Imported BOM (USA) | P5: TP included; international freight updated to 9% | W5: 136.078 | Z5: Engineering weight (Harland Updated Weights.xlsx) | AA5: High
A6: 84A215295P62 | B6: Pneumatic Brake Control System (Including lament and control portions) Includes EM EAB Control Functionality | C6: Air | D6: Fastbrake | E6: 1 | F6: 23409.1 | G6: 35730.084 | H6: 35730.084 | I6: 44740.902 | J6: 44740.902 | K6: 184367.23 | L6: 230863.05 | O6: Imported BOM (USA) | P6: Direct supplier purchase; TP excluded; international freight 9% | W6: 134.263 | Z6: Engineering weight (Harland Updated Weights.xlsx) | AA6: High
A7: 41A296352DNP37 | B7: RADIO PRAD PTC RADIO | C7: PTC | D7: PTC | E7: 1 | F7: 20000 | G7: 26046.64 | H7: 26046.64 | I7: 32615.377 | J7: 32615.377 | K7: 134400.66 | L7: 168295.34 | O7: Imported BOM (USA) | P7: Direct supplier purchase; TP excluded; international freight 9% | W7: 9.616 | Z7: Engineering weight (Harland Updated Weights.xlsx) | AA7: High
A8: 17FM878A6 | B8: NIO 2.0 | C8: Controls (MCA, train control, er etc) | D8: MCA | E8: 3 | F8: 5176.9118 | G8: 6742.0579 | H8: 20226.174 | I8: 8442.3465 | J8: 25327.039 | K8: 104367.06 | L8: 130687.52 | O8: Imported BOM (USA) | P8: TP included; international freight updated to 9% | W8: 8.618 | Z8: Engineering weight (Harland Updated Weights.xlsx) | AA8: High
A9: L7000083-900 | B9: Wireless Communications Management Module, Gen 3 (WCM3)​ | C9: Controls (MCA, train control, er etc) | D9: TRAIN CONTROL | E9: 2 | F9: 5000 | G9: 7631.6655 | H9: 15263.331 | I9: 9556.3054 | J9: 19112.611 | K9: 78758.788 | L9: 98621.072 | O9: Imported BOM (USA) | P9: Made by GET; retained for GET impact analysis | R9: Wire/Cable | S9: Low confidence - no comparable PAC item found | T9: 98621.072 | U9: 7609.408 | V9: PAC/National is cheaper (by R$ 91,011.66) | W9: 2.268 | Z9: Engineering weight (Harland Updated Weights.xlsx) | AA9: High
A10: 84A237085AEP121 | B10: 8 Slot ACC Chassis for MCA w/ i7 HPEAP and SMM2 Cards | C10: Controls (MCA, train control, er etc) | D10: TRAIN CONTROL | E10: 1 | F10: 8000 | G10: 12210.665 | H10: 12210.665 | I10: 15290.089 | J10: 15290.089 | K10: 63007.031 | L10: 78896.858 | O10: Imported BOM (USA) | P10: TP included; international freight updated to 9% | W10: 9.072 | Z10: Engineering weight (Harland Updated Weights.xlsx) | AA10: High
A11: 17FL472A2 | B11: TMC PANEL | C11: SKID Assembly | D11: SKID (Skid) | E11: 1 | H11: 11326.967 | I11: 14183.531 | J11: 14183.531 | K11: 58447.152 | L11: 73187.017 | M11: 58447.152 | O11: PAC (Brazil BRL) | P11: Direct supplier purchase; TP excluded; international freight 9% | W11: 20.412 | X11: 85371090 | Z11: Engineering weight (Harland Updated Weights.xlsx) | AA11: High
A12: 17KC108E28 | B12: MASTER CONTROLLER | C12: Controls (MCA, train control, er etc) | D12: TRAIN CONTROL | E12: 1 | F12: 5877.102 | H12: 9464.1997 | I12: 11850.989 | J12: 11850.989 | K12: 48835.27 | L12: 61151.102 | O12: GET | P12: TP included; international freight updated to 9% | W12: 25.855 | Z12: Engineering weight (Harland Updated Weights.xlsx) | AA12: High
A13: 84A215295P73 | B13: Air Brake Handle Assembly (AAR Console) | C13: Air | D13: Fastbrake | E13: 1 | F13: 5702.83 | G13: 8704.4182 | H13: 8704.4182 | I13: 10899.597 | J13: 10899.597 | K13: 44914.798 | L13: 56241.921 | O13: Imported BOM (USA) | P13: Direct supplier purchase; TP excluded; international freight 9% | W13: 7.938 | Z13: Engineering weight (Harland Updated Weights.xlsx) | AA13: High
A14: 17FM868B2 | B14: SNIO | C14: Controls (MCA, train control, er etc) | D14: MCA | E14: 1 | F14: 4150.9559 | G14: 5405.9227 | H14: 5405.9227 | I14: 6769.2496 | J14: 6769.2496 | K14: 27894.561 | L14: 34929.328 | O14: Imported BOM (USA) | P14: Direct supplier purchase; TP excluded; international freight 9% | W14: 4.99 | Z14: Engineering weight (Harland Updated Weights.xlsx) | AA14: High
A15: 41A296352DNP55 | B15: VOICE RADIO RITRON | C15: Connectivity | D15: VOICE RADIO | E15: 1 | F15: 3933 | G15: 5122.0718 | H15: 5122.0718 | I15: 6413.8139 | J15: 6413.8139 | K15: 26429.89 | L15: 33095.28 | O15: Imported BOM (USA) | P15: TP included; international freight updated to 9% | W15: 7.575 | Z15: Engineering weight (Harland Updated Weights.xlsx) | AA15: High
A16: 32613P | B16: KIT ETMS AXLE INTERFACE FOR WPart Number 29266P | C16: PTC | D16: PTC | E16: 1 | F16: 2981.71 | G16: 4551.0827 | H16: 4551.0827 | I16: 5698.8263 | J16: 5698.8263 | K16: 23483.587 | L16: 29405.944 | O16: Imported BOM (USA) | P16: Direct supplier purchase; TP excluded; international freight 9% | W16: 4.536 | Z16: Engineering weight (Harland Updated Weights.xlsx) | AA16: High
A17: 17FH40X1 | B17: LPS 17FH40 (COMMON LOGIC POWER SUPPLY) (5v, 15v, 19v, 24v) | C17: POWER | D17: POWER SUPPLY | E17: 1 | H17: 2915.0271 | I17: 3650.1717 | J17: 3650.1717 | K17: 15041.54 | L17: 18834.886 | M17: 15041.54 | O17: PAC (Brazil BRL) | P17: Brazilian factory PAC price (local Brazilian cost) | W17: 18.144 | X17: 85044029 | Y17: 24x10x20 | Z17: Engineering weight (Harland Updated Weights.xlsx) | AA17: High
A18: 41D758679BJG16 84D704379AFG1 | B18: EC Part NumberL ASM | C18: Power | D18: Circuit Breaker | E18: 1 | F18: 1572.36 | H18: 2532.0522 | I18: 3170.6138 | J18: 3170.6138 | K18: 13065.389 | L18: 16360.367 | O18: GET | P18: Made by GET; retained for GET impact analysis | W18: 4.99 | X18: 86079100 | Y18: 20x3.5x25.5 | Z18: Exact PN match in item catalog (84D704379AFG1) | AA18: High
A19: 41B546155P2 | B19: Horn | C19: Controls (MCA, train control, er etc) | D19: TRAIN CONTROL | E19: 1 | F19: 1891.99 | G19: 2463.9991 | H19: 2463.9991 | I19: 3085.3983 | J19: 3085.3983 | K19: 12714.235 | L19: 15920.655 | O19: Imported BOM (USA) | P19: Brazilian factory PAC price (local Brazilian cost) | W19: 4.536 | Z19: Engineering weight (Harland Updated Weights.xlsx) | AA19: High
B20: Ditchlight Control Box (SMART BOX-V3-DLC ) | C20: Controls (MCA, train control, er etc) | D20: TRAIN CONTROL | E20: 2 | F20: 800 | G20: 1221.0665 | H20: 2442.133 | I20: 1529.0089 | J20: 3058.0177 | K20: 12601.406 | L20: 15779.372 | O20: Imported BOM (USA) | P20: Brazilian factory PAC price (local Brazilian cost) | W20: 2.268 | Z20: Engineering weight (Harland Updated Weights.xlsx) | AA20: High
B21: LED Ditch Light | C21: Controls (MCA, train control, er etc) | D21: TRAIN CONTROL | E21: 4 | F21: 375 | G21: 572.37491 | H21: 2289.4997 | I21: 716.72291 | J21: 2866.8916 | K21: 11813.818 | L21: 14793.161 | O21: Imported BOM (USA) | P21: TP included; international freight updated to 9% | W21: 0.907 | Z21: Engineering weight (Harland Updated Weights.xlsx) | AA21: High
A22: 17FM839B1 | B22: PANEL ASM CFD - Thin Client Display | C22: Controls (MCA, train control, er etc) | D22: MCA | E22: 1 | H22: 2248.7824 | I22: 2815.9058 | J22: 2815.9058 | K22: 11603.717 | L22: 14530.074 | M22: 11603.717 | O22: PAC (Brazil BRL) | P22: Made by GET; retained for GET impact analysis | W22: 9.299 | X22: 85312000 | Y22: 18.5x8.5x15 | Z22: Exact PN match in item catalog (17FM839B1) | AA22: High
A23: 17FM839A3 | B23: TCD (Thin Client Display) | C23: SKID Assembly | D23: SKID (Skid) | E23: 1 | H23: 2248.7824 | I23: 2815.9058 | J23: 2815.9058 | K23: 11603.717 | L23: 14530.074 | M23: 11603.717 | O23: PAC (Brazil BRL) | P23: Direct supplier purchase; TP excluded; international freight 9% | W23: 9.299 | X23: 85312000 | Y23: 18.5x8.5x15 | Z23: ESTIMATE (medium confidence) - Same physical item as 17FM839B1 (already priced as such) | AA23: High
A24: 84A201003DAP1 | B24: ELECTRIC Bell | C24: Controls (MCA, train control, er etc) | D24: TRAIN CONTROL | E24: 1 | H24: 1839.4297 | I24: 2303.3179 | J24: 2303.3179 | K24: 9491.4571 | L24: 11885.12 | M24: 9491.4571 | O24: PAC (Brazil BRL) | P24: TP included; international freight updated to 9% | W24: 8.119 | X24: 85318000 | Y24: 14.25x14.25x10 | Z24: Exact PN match in item catalog (84A201003DAP1) | AA24: High
A25: 17FB193E2F | B25: GET Card | C25: GET | D25: GET Card | E25: 1 | H25: 1792.8535 | I25: 2244.9956 | J25: 2244.9956 | K25: 9251.1239 | L25: 11584.177 | M25: 9251.1239 | O25: PAC (Brazil BRL) | P25: Made by GET; retained for GET impact analysis | W25: 1.114 | X25: 85049040 | Y25: 17.2x1.95x11.2 | Z25: Exact PN match in item catalog (17FB193E2F) | AA25: High
A26: 84A215295P3 | B26: POU-to-Handle cable 18' length | C26: Air | D26: Fastbrake | E26: 1 | F26: 1036.89 | G26: 1582.6395 | H26: 1582.6395 | I26: 1981.7675 | J26: 1981.7675 | K26: 8166.42 | L26: 10225.92 | O26: Imported BOM (USA) | P26: TP included; international freight updated to 9% | R26: Wire/Cable | S26: Low confidence - PAC family match, different length | T26: 10225.92 | U26: 8409.4743 | V26: PAC/National is cheaper (by R$ 1,816.45) | W26: 1.247 | Z26: ESTIMATE (medium confidence) - Estimate from same-PN-family 84A215295P37 (Handle Junction Box) | AA26: Medium
A27: 41B566322ACG1 | B27: TRAINLINE RESISTOR PANEL | C27: SKID Assembly | D27: Controls (MCA, train control, er etc) | E27: 1 | H27: 1306.7417 | I27: 1636.2907 | J27: 1636.2907 | K27: 6742.7873 | L27: 8443.2599 | M27: 6742.7873 | O27: GET | P27: TP included; international freight updated to 9% | W27: 2.859 | X27: 85333990 | Y27: 14x6x8.5 | Z27: Exact PN match in item catalog (41B566322ACG1) | AA27: High
A28: 41A296304DDP4 | B28: G-RECTIFIER POWER BLOCK | C28: SKID Assembly | D28: Controls (MCA, train control, er etc) | E28: 20 | H28: 1264.4303 | I28: 79.16543 | J28: 1583.3086 | K28: 6524.4601 | L28: 8169.8724 | M28: 326.22301 | O28: PAC (Brazil BRL) | P28: Brazilian factory PAC price (local Brazilian cost) | W28: 0.054 | X28: 85411099 | Y28: 10.85x1.1x8.5 | Z28: Exact PN match in item catalog (41A296304DDP4) - FLAGGED: Exact PN match, but 0.054 kg is implausibly light for a 'Rectifier Power Block' - catalog weight likely covers only a sub-component. Do not use for freight without verification. | AA28: Low
A29: RCCR-RMTCBL-RA-CUSTOM | B29: VOICE RADIO RITRON CABLE,REMOTE,RR-225/XXX, RCCR,RIGHT ANGLE,19-PIN,FLAME RETARDANT | C29: Connectivity | D29: VOICE RADIO | E29: 1 | F29: 761 | G29: 991.07465 | H29: 991.07465 | I29: 1241.0151 | J29: 1241.0151 | K29: 5113.9452 | L29: 6403.6379 | O29: Imported BOM (USA) | P29: Brazilian factory PAC price (local Brazilian cost) | R29: Wire/Cable | S29: Low confidence - no comparable PAC item found | T29: 6403.6379 | U29: 3569.0421 | V29: PAC/National is cheaper (by R$ 2,834.60)
A30: 41C663693G1 | B30: PANEL CPF | C30: Power | D30: POWER | E30: 1 | H30: 924.61033 | I30: 1157.789 | J30: 1157.789 | K30: 4770.9893 | L30: 5974.1915 | M30: 4770.9893 | O30: GET | P30: Brazilian factory PAC price (local Brazilian cost) | W30: 5.761 | X30: 85371090 | Y30: 20.5x10.5x11.5 | Z30: Exact PN match in item catalog (41C663693G1) | AA30: High
A31: 41A296352PTP306/41A296352PTP122 | B31: Assembled Air Manifold (Contains 3 pressure sensors mounted in appropriate locations on Air Manifold.) | C31: PTC | D31: PTC | E31: 1 | F31: 595.7889 | G31: 909.37232 | H31: 909.37232 | I31: 1138.7081 | J31: 1138.7081 | K31: 4692.3612 | L31: 5875.734 | O31: Imported BOM (USA) | P31: Brazilian factory PAC price (local Brazilian cost) | W31: 5.897 | X31: 85381000 | Z31: ESTIMATE (medium confidence) - Estimate from similar item 41C619972P3 (Air Brake Manifold) | AA31: Medium
A32: 84A232147P1 | B32: KNOB HLD DWN with washer and screw | C32: Controls (MCA, train control, er etc) | D32: TRAIN CONTROL | E32: 30 | H32: 741.13821 | I32: 30.934895 | J32: 928.04685 | K32: 3824.2732 | L32: 4788.7217 | M32: 127.47577 | O32: PAC (Brazil BRL) | P32: Brazilian factory PAC price (local Brazilian cost) | W32: 0.045 | X32: 83024900 | Y32: 3.5x0.75x0.75 | Z32: Exact PN match in item catalog (84A232147P1) | AA32: High
A33: 32447P | B33: ASY CABLE WHEEL TACH AC EVO/SD70 ACE | C33: PTC | D33: PTC | E33: 1 | F33: 411.22 | G33: 627.6587 | H33: 627.6587 | I33: 785.94878 | J33: 785.94878 | K33: 3238.7189 | L33: 4055.4957 | O33: Imported BOM (USA) | P33: Calculated with TP (17.2%) + International Freight (15%) + Import Duty (16%) + Domestic Freight (3%) | Qtd=1.0 | R33: Wire/Cable | S33: High confidence PAC match (exact desc, PN 29707P) - not yet applied | T33: 4055.4957 | U33: 373.6982 | V33: PAC/National is cheaper (by R$ 3,681.80)
A34: 41A296352PTP10/319/34 | B34: VALVE Part NumberEUMATIC NC/CO (Penalty Magnet Valve) Graham-White 812-142 | C34: PTC | D34: PTC | E34: 1 | F34: 404.6239 | G34: 617.59085 | H34: 617.59085 | I34: 773.34191 | J34: 773.34191 | K34: 3186.7688 | L34: 3990.4443 | O34: Imported BOM (USA) | P34: Brazilian factory PAC price (local Brazilian cost)
A35: 84A201176P1 | B35: Pathfinder Control Unit Connector (MU Plug) | C35: Controls (MCA, train control, er etc) | D35: TRAIN CONTROL | E35: 2 | H35: 573.97817 | I35: 359.36524 | J35: 718.73049 | K35: 2961.7273 | L35: 3708.6493 | M35: 1480.8637 | O35: PAC (Brazil BRL) | P35: Calculated with TP (17.2%) + International Freight (15%) + Import Duty (16%) + Domestic Freight (3%) | Qtd=1.0 | R35: Connector/Plug | S35: Already nationalized (PAC) | T35: 4406.427 | U35: 3708.6493 | V35: PAC/National is cheaper (by R$ 697.78) | W35: 2.404 | X35: 85366990 | Y35: 7x4x7 | Z35: Exact PN match in item catalog (84A201176P1) | AA35: High
A36: 84A201150ACP2 | B36: CROSSING BELL PUSH BUTTON SWITCH | C36: Controls (MCA, train control, er etc) | D36: TRAIN CONTROL | E36: 1 | H36: 551.04203 | I36: 690.01005 | J36: 690.01005 | K36: 2843.3769 | L36: 3560.4519 | M36: 2843.3769 | O36: PAC (Brazil BRL) | P36: Calculated with TP (17.2%) + International Freight (15%) + Import Duty (16%) + Domestic Freight (3%) | Qtd=1.0 | W36: 0.411 | X36: 85365090 | Y36: 11.8x6.4x8.05 | Z36: Exact PN match in item catalog (84A201150ACP2) | AA36: High
A37: 17FH37A6 | B37: RPS Power Panel - Radio Power Supply - 15V | C37: Controls (MCA, train control, er etc) | D37: MCA | E37: 1 | H37: 491.25711 | I37: 615.14789 | J37: 615.14789 | K37: 2534.8867 | L37: 3174.1631 | M37: 2534.8867 | O37: PAC (Brazil BRL) | P37: Brazilian factory PAC price (local Brazilian cost) | W37: 4.247 | X37: 85044030 | Y37: 12.8x3.8x9.5 | Z37: Exact PN match in item catalog (17FH37A6) | AA37: High
A38: 41A240644P2 | B38: HORN MAGNET VALVE | C38: Controls (MCA, train control, er etc) | D38: TRAIN CONTROL | E38: 1 | H38: 461.70053 | I38: 578.13741 | J38: 578.13741 | K38: 2382.3747 | L38: 2983.189 | M38: 2382.3747 | O38: PAC (Brazil BRL) | P38: Brazilian factory PAC price (local Brazilian cost) | W38: 3.629 | X38: 84812090 | Y38: 8.4x3.35x7.5 | Z38: Exact PN match in item catalog (41A240644P2) | AA38: High
A39: 41A296352CMP387 | B39: ETHERNET CABLE | C39: Controls (MCA, train control, er etc) | D39: MCA | E39: 1 | H39: 413.22564 | I39: 517.43757 | J39: 517.43757 | K39: 2132.2443 | L39: 2669.9779 | M39: 2132.2443 | O39: PAC (Brazil BRL) | P39: Brazilian factory PAC price (local Brazilian cost) | R39: Wire/Cable | S39: Already nationalized (PAC) | T39: 2660.402 | U39: 2669.9779 | V39: Import is cheaper (by R$ 9.58) | W39: 0.227 | X39: 85444200 | Y39: 0x0x0 | Z39: Exact PN match in item catalog (41A296352CMP387) | AA39: High
A40: 41B511393P2 | B40: Battery Knife Switch | C40: Power | D40: POWER | E40: 1 | H40: 347.82993 | I40: 435.54962 | J40: 435.54962 | K40: 1794.8024 | L40: 2247.436 | M40: 1794.8024 | O40: PAC (Brazil BRL) | P40: Brazilian factory PAC price (local Brazilian cost) | W40: 4.445 | X40: 85365090 | Y40: 13.5x5.25x7 | Z40: Exact PN match in item catalog (41B511393P2) | AA40: High
A41: 84A231123CSP30 | B41: Axle Tac - WRE Part Number: 29266P | C41: PTC | D41: PTC | E41: 1 | F41: 205 | H41: 330.12205 | I41: 413.37596 | J41: 413.37596 | K41: 1703.4298 | L41: 2133.02 | O41: Imported BOM (USA) | P41: Brazilian factory PAC price (local Brazilian cost)
A42: 84A207079ABP1 | B42: 41A313392DCP18 alternative 300" / | C42: Controls (MCA, train control, er etc) | D42: Wiring | E42: 25 | F42: 8.118 | H42: 326.82082 | I42: 16.369688 | J42: 409.2422 | K42: 1686.3955 | L42: 2111.6898 | O42: Imported BOM (USA) | P42: Brazilian factory PAC price (local Brazilian cost) | W42: 0.227 | X42: 85446000 | Y42: 24x20x24 | Z42: Exact PN match in item catalog (84A207079ABP1) | AA42: High
A43: 84A201850P4 | B43: ENGINE CONTROL SWITCH | C43: Controls (MCA, train control, er etc) | D43: TRAIN CONTROL | E43: 1 | F43: 171.544 | H43: 276.24613 | I43: 345.91301 | J43: 345.91301 | K43: 1425.43 | L43: 1784.9111 | O43: Imported BOM (USA) | P43: Brazilian factory PAC price (local Brazilian cost)
A44: RCCR-PWRCBL | B44: CABLE, PWR, 72V,RA,6.5FT (78").,RR-070,RCCR | C44: Connectivity | D44: VOICE RADIO | E44: 1 | F44: 159 | H44: 256.04588 | I44: 320.61843 | J44: 320.61843 | K44: 1321.1967 | L44: 1654.3911 | O44: Imported BOM (USA) | P44: Brazilian factory PAC price (local Brazilian cost) | R44: Wire/Cable | S44: Low confidence - PAC match, different length | T44: 1654.3911 | U44: 806.59378 | V44: PAC/National is cheaper (by R$ 847.80)
A45: 41A216641P158 | B45: SNIO CONNECTOR 3 | C45: Controls (MCA, train control, er etc) | D45: Wiring | E45: 2 | H45: 251.78188 | I45: 157.63955 | J45: 315.27909 | K45: 1299.1945 | L45: 1626.8401 | M45: 649.59726 | O45: PAC (Brazil BRL) | P45: Brazilian factory PAC price (local Brazilian cost) | R45: Connector/Plug | S45: Already nationalized (PAC) | T45: 1529.528 | U45: 1626.8401 | V45: Import is cheaper (by R$ 97.31) | W45: 0.091 | X45: 85366990 | Y45: 3x2x3 | Z45: Exact PN match in item catalog (41A216641P158) | AA45: High
A46: 41B546301P4 | B46: DOOR INTERLOCK SWITCH | C46: Controls (MCA, train control, er etc) | D46: TRAIN CONTROL | E46: 1 | H46: 248.53773 | I46: 311.2168 | J46: 311.2168 | K46: 1282.4547 | L46: 1605.8787 | M46: 1282.4547 | O46: PAC (Brazil BRL) | P46: Brazilian factory PAC price (local Brazilian cost) | W46: 0.966 | X46: 85365090 | Y46: 6x2.25x3 | Z46: Exact PN match in item catalog (41B546301P4) | AA46: High
A47: 84A201169AKP1 | B47: ENGINEERS HORN BUTTON | C47: Controls (MCA, train control, er etc) | D47: TRAIN CONTROL | E47: 1 | H47: 220.85663 | I47: 276.55476 | J47: 276.55476 | K47: 1139.6202 | L47: 1427.0226 | M47: 1139.6202 | O47: PAC (Brazil BRL) | P47: Calculated with TP (17.2%) + International Freight (15%) + Import Duty (16%) + Domestic Freight (3%) | Qtd=1.0 | W47: 0.463 | X47: 85365090 | Y47: 9.35x5.3x5.2 | Z47: Exact PN match in item catalog (84A201169AKP1) | AA47: High
A48: 41B549523ABP101 | B48: BATTERY SAVER RESET PUSH BUTTON | C48: Controls (MCA, train control, er etc) | D48: TRAIN CONTROL | E48: 1 | H48: 216.586 | I48: 271.20711 | J48: 271.20711 | K48: 1117.5838 | L48: 1399.4287 | M48: 1117.5838 | O48: PAC (Brazil BRL) | P48: Brazilian factory PAC price (local Brazilian cost) | W48: 0.215 | X48: 85365090 | Y48: 3.875x1.625x2.125 | Z48: Exact PN match in item catalog (41B549523ABP101) | AA48: High
A49: 41B564808G1 | B49: A-DIODE ASM | C49: SKID Assembly | D49: SKID (Skid) | E49: 16 | H49: 197.86975 | I49: 15.485674 | J49: 247.77079 | K49: 1021.0079 | L49: 1278.4973 | M49: 63.812995 | O49: PAC (Brazil BRL) | P49: Brazilian factory PAC price (local Brazilian cost) | W49: 0.045 | X49: 85411092 | Y49: 3x0.75x1.5 | Z49: Exact PN match in item catalog (41B564808G1) | AA49: High
A50: 497A365P13 | B50: ALARM AND SIGNAL BELL | C50: Controls (MCA, train control, er etc) | D50: TRAIN CONTROL | E50: 1 | H50: 189.07809 | I50: 236.76194 | J50: 236.76194 | K50: 975.64293 | L50: 1221.6916 | M50: 975.64293 | O50: PAC (Brazil BRL) | P50: Calculated with TP (17.2%) + International Freight (15%) + Import Duty (16%) + Domestic Freight (3%) | Qtd=1.0 | W50: 0.962 | X50: 85318000 | Y50: 7x3.25x4.75 | Z50: Exact PN match in item catalog (497A365P13) | AA50: High
A51: 84A201850P5 | B51: AC-ROTARY SWITCH | C51: SKID Assembly | D51: SKID (Skid) | E51: 1 | H51: 183.44022 | I51: 229.70225 | J51: 229.70225 | K51: 946.55154 | L51: 1185.2636 | M51: 946.55154 | O51: PAC (Brazil BRL) | P51: Calculated with TP (17.2%) + International Freight (15%) + Import Duty (16%) + Domestic Freight (3%) | Qtd=1.0 | W51: 0.177 | X51: 85365090 | Y51: 5.2x2.9x3.35 | Z51: Exact PN match in item catalog (84A201850P5) | AA51: High
A52: 41A216641P235 | B52: GOLINC / ACC POWER CONNECTOR | C52: Controls (MCA, train control, er etc) | D52: Wiring | E52: 3 | H52: 176.58838 | I52: 73.70748 | J52: 221.12244 | K52: 911.19605 | L52: 1140.9918 | M52: 303.73202 | O52: PAC (Brazil BRL) | P52: Calculated with TP (17.2%) + International Freight (15%) + Import Duty (16%) + Domestic Freight (3%) | Qtd=1.0 | R52: Connector/Plug | S52: Already nationalized (PAC) | T52: 1028.8052 | U52: 1140.9918 | V52: Import is cheaper (by R$ 112.19) | W52: 0.043 | X52: 85359090 | Y52: 4.52x1.35x6.95 | Z52: Exact PN match in item catalog (41A216641P235) | AA52: High
A53: 84A206730P1 | B53: 565" / CABLE 5 PAIR | C53: Controls (MCA, train control, er etc) | D53: Wiring | E53: 50 | H53: 174.07837 | I53: 4.3595886 | J53: 217.97943 | K53: 898.2444 | L53: 1124.7739 | M53: 17.964888 | O53: PAC (Brazil BRL) | P53: Brazilian factory PAC price (local Brazilian cost) | R53: Wire/Cable | S53: Already nationalized (PAC) | T53: 975.01723 | U53: 1124.7739 | V53: Import is cheaper (by R$ 149.76) | W53: 0.041 | X53: 85444900 | Y53: 12x0.5x0.5 | Z53: Exact PN match in item catalog (84A206730P1) | AA53: High
A54: 41B549523ADP108 | B54: VIGILANCE RESET SWITCH | C54: Controls (MCA, train control, er etc) | D54: TRAIN CONTROL | E54: 1 | H54: 155.80761 | I54: 195.10094 | J54: 195.10094 | K54: 803.96726 | L54: 1006.7208 | M54: 803.96726 | O54: PAC (Brazil BRL) | P54: Brazilian factory PAC price (local Brazilian cost) | W54: 0.204 | X54: 85365090 | Y54: 4x2.5x2.5 | Z54: Exact PN match in item catalog (41B549523ADP108) | AA54: High
A55: 41A317303ACP49 | B55: AIR RESERVOIR PRESSURE SENSOR | C55: Controls (MCA, train control, er etc) | D55: MCA | E55: 1 | H55: 145.18613 | I55: 181.80081 | J55: 181.80081 | K55: 749.16041 | L55: 938.09217 | M55: 749.16041 | O55: PAC (Brazil BRL) | P55: Brazilian factory PAC price (local Brazilian cost) | W55: 0.045 | X55: 90262090 | Y55: 2.9x0.5x0.5 | Z55: Exact PN match in item catalog (41A317303ACP49) | AA55: High
A56: 41A216641AMP126 | B56: NIO1D CONNECTOR BACKSHELL | C56: Controls (MCA, train control, er etc) | D56: Wiring | E56: 3 | F56: 29.9096 | H56: 144.4949 | I56: 60.311755 | J56: 180.93526 | K56: 745.5937 | L56: 933.62597 | O56: Imported BOM (USA) | P56: Calculated with TP (17.2%) + International Freight (15%) + Import Duty (16%) + Domestic Freight (3%) | Qtd=1.0 | R56: Connector/Plug | S56: Medium confidence PAC match (same PN family - AMP115 backshell) | T56: 933.62597 | U56: 1034.7713 | V56: Import is cheaper (by R$ 101.15) | W56: 0 | Y56: 0x0x0 | Z56: Exact PN match in item catalog (41A216641AMP126) | AA56: High
A57: 84A215329P1 | B57: ENGINE STOP SWITCH | C57: Controls (MCA, train control, er etc) | D57: TRAIN CONTROL | E57: 1 | H57: 136.23751 | I57: 170.59542 | J57: 170.59542 | K57: 702.98553 | L57: 880.27239 | M57: 702.98553 | O57: PAC (Brazil BRL) | P57: Brazilian factory PAC price (local Brazilian cost) | W57: 0.175 | X57: 85365090 | Y57: 1.75x3.25x2.75 | Z57: Exact PN match in item catalog (84A215329P1) | AA57: High
A58: 41A296328ASP3 | B58: BATTERY TEMPERATURE SENSOR | C58: Controls (MCA, train control, er etc) | D58: Power | E58: 1 | H58: 134.70558 | I58: 168.67716 | J58: 168.67716 | K58: 695.08079 | L58: 870.37414 | M58: 695.08079 | O58: PAC (Brazil BRL) | P58: Brazilian factory PAC price (local Brazilian cost) | W58: 0.422 | X58: 90251990 | Y58: 9.5x1.5x9.5 | Z58: Exact PN match in item catalog (41A296328ASP3) | AA58: High
A59: 41A216641ABP45 | B59: DUAL PROCESSOR MODULE CONNECTOR | C59: Controls (MCA, train control, er etc) | D59: Wiring | E59: 2 | H59: 134.48545 | I59: 84.200758 | J59: 168.40152 | K59: 693.94492 | L59: 868.95182 | M59: 346.97246 | O59: PAC (Brazil BRL) | P59: Brazilian factory PAC price (local Brazilian cost) | R59: Connector/Plug | S59: Already nationalized (PAC) | T59: 814.08342 | U59: 868.95182 | V59: Import is cheaper (by R$ 54.87) | W59: 0.058 | X59: 85369090 | Y59: 2x1x1 | Z59: Exact PN match in item catalog (41A216641ABP45) | AA59: High
A60: 84A232147P2 | B60: PIN REAR HOLD-DOWN | C60: Controls (MCA, train control, er etc) | D60: TRAIN CONTROL | E60: 30 | H60: 132.57061 | I60: 5.5334588 | J60: 166.00377 | K60: 684.06433 | L60: 856.57943 | M60: 22.802144 | O60: PAC (Brazil BRL) | P60: Brazilian factory PAC price (local Brazilian cost) | R60: Connector/Plug | S60: Already nationalized (PAC) | T60: 1332.5383 | U60: 856.57943 | V60: PAC/National is cheaper (by R$ 475.96) | W60: 0.005 | X60: 73182900 | Y60: 1x0.125x0.125 | Z60: Exact PN match in item catalog (84A232147P2) | AA60: High
A61: 41A321053G1 | B61: Power Resistor | C61: Power | D61: Resistor | E61: 1 | H61: 132.25867 | I61: 165.61316 | J61: 165.61316 | K61: 682.45475 | L61: 854.56392 | M61: 682.45475 | O61: PAC (Brazil BRL) | P61: Brazilian factory PAC price (local Brazilian cost) | W61: 3.629 | X61: 85332900 | Y61: 12x3x7.5 | Z61: Exact PN match in item catalog (41A321053G1) | AA61: High
A62: 17 pin MS3106-20-29F | B62: Head of Train Device - Padom - J2 Connector | C62: Controls (MCA, train control, er etc) | D62: Wiring | E62: 1 | F62: 79.83 | H62: 128.55436 | I62: 160.97465 | J62: 160.97465 | K62: 663.34047 | L62: 830.62919 | O62: Imported BOM (USA) | P62: Brazilian factory PAC price (local Brazilian cost) | R62: Connector/Plug | S62: Low confidence - no comparable PAC item found | T62: 830.62919 | U62: 836.61643 | V62: Import is cheaper (by R$ 5.99)
A63: 41A216641P157 | B63: SNIO CONNECTOR 2 | C63: Controls (MCA, train control, er etc) | D63: Wiring | E63: 1 | H63: 121.26151 | I63: 151.84262 | J63: 151.84262 | K63: 625.70941 | L63: 783.50791 | M63: 625.70941 | O63: PAC (Brazil BRL) | P63: Brazilian factory PAC price (local Brazilian cost) | R63: Connector/Plug | S63: Already nationalized (PAC) | T63: 702.01339 | U63: 783.50791 | V63: Import is cheaper (by R$ 81.49) | W63: 0.096 | X63: 85366990 | Y63: 2.5x1.5x1.5 | Z63: Exact PN match in item catalog (41A216641P157) | AA63: High
A64: 41A216641AMP125 | B64: NIO1A CONNECTOR BACKSHELL | C64: Controls (MCA, train control, er etc) | D64: Wiring | E64: 3 | F64: 24.1998 | H64: 116.91055 | I64: 48.798125 | J64: 146.39438 | K64: 603.25843 | L64: 755.39498 | O64: Imported BOM (USA) | P64: Brazilian factory PAC price (local Brazilian cost) | R64: Connector/Plug | S64: Medium confidence PAC match (same PN family - AMP115 backshell) | T64: 755.39498 | U64: 1034.7713 | V64: Import is cheaper (by R$ 279.38) | W64: 0.005 | Y64: 0x0x0 | Z64: Exact PN match in item catalog (41A216641AMP125) | AA64: High
A65: 5088-7000-P4611-0000000-ND‎ | B65: POE Power Connector on SMM2 (M12 FEMALE 0 L-CODED FIELD-WIREA) | C65: Controls (MCA, train control, er etc) | D65: TRAIN CONTROL | E65: 1 | F65: 72.41 | H65: 116.60555 | I65: 146.01246 | J65: 146.01246 | K65: 601.68463 | L65: 753.42428 | O65: Imported BOM (USA) | P65: Calculated with TP (17.2%) + International Freight (15%) + Import Duty (16%) + Domestic Freight (3%) | Qtd=1.0 | R65: Connector/Plug | S65: Low confidence - no current price, weak PAC reference only | T65: 753.42428 | U65: 166.36614 | V65: PAC/National is cheaper (by R$ 587.06)
A66: 41A296352PTP67 | B66: CABLE CSX 12V P WR CBL | C66: Controls (MCA, train control, er etc) | D66: MCA | E66: 1 | F66: 71.94 | H66: 115.84868 | I66: 145.06472 | J66: 145.06472 | K66: 597.7792 | L66: 748.53394 | O66: Imported BOM (USA) | P66: Brazilian factory PAC price (local Brazilian cost) | R66: Wire/Cable | S66: Low confidence - PAC candidate is more expensive | T66: 748.53394 | U66: 1134.2711 | V66: Import is cheaper (by R$ 385.74)
A67: 41A296352PTP69 | B67: CABLE CSX 74V P WR CBL | C67: Controls (MCA, train control, er etc) | D67: MCA | E67: 1 | F67: 71.94 | H67: 115.84868 | I67: 145.06472 | J67: 145.06472 | K67: 597.7792 | L67: 748.53394 | O67: Imported BOM (USA) | P67: Brazilian factory PAC price (local Brazilian cost) | R67: Wire/Cable | S67: Low confidence - PAC candidate is more expensive | T67: 748.53394 | U67: 1134.2711 | V67: Import is cheaper (by R$ 385.74)
A68: 41A216641AMP93 | B68: NIO1E CONNECTOR | C68: Controls (MCA, train control, er etc) | D68: Wiring | E68: 3 | F68: 23.9499 | H68: 115.70327 | I68: 48.29421 | J68: 144.88263 | K68: 597.02886 | L68: 747.59437 | O68: Imported BOM (USA) | P68: Brazilian factory PAC price (local Brazilian cost) | R68: Connector/Plug | S68: Medium confidence PAC match (same PN family - AMP84 plug) | T68: 747.59437 | U68: 427.83384 | V68: PAC/National is cheaper (by R$ 319.76) | W68: 0.054 | Y68: 0x0x0 | Z68: Exact PN match in item catalog (41A216641AMP93) | AA68: High
A69: 41B549523ADP1 | B69: Black push Button | C69: SKID Assembly | D69: Use in place of al levers and other push buttons | E69: 1 | H69: 109.60596 | I69: 137.24763 | J69: 137.24763 | K69: 565.56673 | L69: 708.19776 | M69: 565.56673 | O69: PAC (Brazil BRL) | P69: Brazilian factory PAC price (local Brazilian cost) | W69: 0.142 | X69: 85365090 | Y69: 4x2.125x2.125 | Z69: Exact PN match in item catalog (41B549523ADP1) | AA69: High
A70: 41B549523ADP2 | B70: SWITCH PUSH BUTTON | C70: SKID Assembly | D70: SKID (Skid) | E70: 1 | H70: 105.17654 | I70: 131.70115 | J70: 131.70115 | K70: 542.71095 | L70: 679.57795 | M70: 542.71095 | O70: PAC (Brazil BRL) | P70: Brazilian factory PAC price (local Brazilian cost) | W70: 0.141 | X70: 85365090 | Y70: 1.95x2.7x1.8 | Z70: Exact PN match in item catalog (41B549523ADP2) | AA70: High
A71: 41A296328APP5 | B71: BATTERY CURRENT SENSOR | C71: Controls (MCA, train control, er etc) | D71: MCA | E71: 1 | H71: 102.85197 | I71: 128.79035 | J71: 128.79035 | K71: 530.71617 | L71: 664.55819 | M71: 530.71617 | O71: PAC (Brazil BRL) | P71: Brazilian factory PAC price (local Brazilian cost) | W71: 0.575 | X71: 90303390 | Y71: 4.75x1.25x4 | Z71: Exact PN match in item catalog (41A296328APP5) | AA71: High
A72: 41A216641AMP103 | B72: NIO1D CONNECTOR | C72: Controls (MCA, train control, er etc) | D72: Wiring | E72: 3 | F72: 21.2198 | H72: 102.51401 | I72: 42.78905 | J72: 128.36715 | K72: 528.97227 | L72: 662.3745 | O72: Imported BOM (USA) | P72: Brazilian factory PAC price (local Brazilian cost) | R72: Connector/Plug | S72: Low confidence - family match, wrong sub-type | T72: 662.3745 | U72: 1034.7713 | V72: Import is cheaper (by R$ 372.40) | W72: 0.045 | Y72: 1.5x1x1.5 | Z72: Exact PN match in item catalog (41A216641AMP103) | AA72: High
A73: 16246P | B73: Flexi-Axle - WRE Part Number: 16246P | C73: PTC | D73: PTC | E73: 1 | F73: 59.75 | H73: 96.218499 | I73: 120.48397 | J73: 120.48397 | K73: 496.48745 | L73: 621.69729 | O73: Imported BOM (USA) | P73: Brazilian factory PAC price (local Brazilian cost)
A74: 41A216641AMP99 | B74: NIO1B CONNECTOR | C74: Controls (MCA, train control, er etc) | D74: Wiring | E74: 3 | F74: 19.67 | H74: 95.026838 | I74: 39.663928 | J74: 118.99178 | K74: 490.33849 | L74: 613.9976 | O74: Imported BOM (USA) | P74: Calculated with TP (17.2%) + International Freight (15%) + Import Duty (16%) + Domestic Freight (3%) | Qtd=3.0 | R74: Connector/Plug | S74: Medium confidence PAC match (same PN family - AMP84 plug) | T74: 613.9976 | U74: 427.83384 | V74: PAC/National is cheaper (by R$ 186.16) | W74: 0 | Y74: 0x0x0 | Z74: Exact PN match in item catalog (41A216641AMP99) | AA74: High
A75: 41A216641AMP123 | B75: NIO1F CONNECTOR BACKSHELL | C75: Controls (MCA, train control, er etc) | D75: Wiring | E75: 3 | F75: 19.5574 | H75: 94.482862 | I75: 39.436874 | J75: 118.31062 | K75: 487.53157 | L75: 610.4828 | O75: Imported BOM (USA) | P75: Calculated with TP (17.2%) + International Freight (15%) + Import Duty (16%) + Domestic Freight (3%) | Qtd=3.0 | R75: Connector/Plug | S75: Medium confidence PAC match (same PN family - AMP115 backshell) | T75: 610.4828 | U75: 1034.7713 | V75: Import is cheaper (by R$ 424.29) | W75: 0.02 | Y75: 0x0x0 | Z75: Exact PN match in item catalog (41A216641AMP123) | AA75: High
A76: 41A216641P140 | B76: Part NumberEUMATIC OPERATING UNIT CONNECTOR - 5 | C76: Air | D76: Fastbrake | E76: 1 | H76: 93.10614 | I76: 116.5867 | J76: 116.5867 | K76: 480.42768 | L76: 601.58738 | M76: 480.42768 | O76: PAC (Brazil BRL) | P76: Calculated with TP (17.2%) + International Freight (15%) + Import Duty (16%) + Domestic Freight (3%) | Qtd=3.0 | R76: Connector/Plug | S76: Already nationalized (PAC) | T76: 927.42171 | U76: 601.58738 | V76: PAC/National is cheaper (by R$ 325.83) | W76: 0.091 | X76: 85369090 | Y76: 4x2x4 | Z76: Exact PN match in item catalog (41A216641P140) | AA76: High
A77: 41A216641AMP100 | B77: NIO1C CONNECTOR | C77: Controls (MCA, train control, er etc) | D77: Wiring | E77: 3 | F77: 19.173 | H77: 92.625804 | I77: 38.661743 | J77: 115.98523 | K77: 477.94915 | L77: 598.48379 | O77: Imported BOM (USA) | P77: Brazilian factory PAC price (local Brazilian cost) | R77: Connector/Plug | S77: Low confidence - family match, wrong sub-type | T77: 598.48379 | U77: 1034.7713 | V77: Import is cheaper (by R$ 436.29) | W77: 0 | Y77: 0x0x0 | Z77: Exact PN match in item catalog (41A216641AMP100) | AA77: High
A78: 41A216641P53 | B78: SNIO CONNECTOR 1 | C78: Controls (MCA, train control, er etc) | D78: Wiring | E78: 1 | H78: 91.649811 | I78: 114.7631 | J78: 114.7631 | K78: 472.91303 | L78: 592.17759 | M78: 472.91303 | O78: PAC (Brazil BRL) | P78: Calculated with TP (17.2%) + International Freight (15%) + Import Duty (16%) + Domestic Freight (3%) | Qtd=1.0 | R78: Connector/Plug | S78: Already nationalized (PAC) | T78: 613.88757 | U78: 592.17759 | V78: PAC/National is cheaper (by R$ 21.71) | W78: 0.093 | X78: 85366990 | Y78: 5.85x1.95x3.9 | Z78: Exact PN match in item catalog (41A216641P53) | AA78: High
A79: 41A216641AMP86 | B79: NIO1F CONNECTOR | C79: Controls (MCA, train control, er etc) | D79: Wiring | E79: 3 | F79: 18.9357 | H79: 91.479395 | I79: 38.183235 | J79: 114.54971 | K79: 472.03368 | L79: 591.07648 | O79: Imported BOM (USA) | P79: Calculated with TP (17.2%) + International Freight (15%) + Import Duty (16%) + Domestic Freight (3%) | Qtd=3.0 | R79: Connector/Plug | S79: Medium confidence PAC match (same PN family - AMP84 plug) | T79: 591.07648 | U79: 427.83384 | V79: PAC/National is cheaper (by R$ 163.24) | W79: 0.032 | Y79: 3.95x1.25x6.65 | Z79: Exact PN match in item catalog (41A216641AMP86) | AA79: High
A80: 41A216641P141 | B80: Part NumberEUMATIC OPERATING UNIT CONNECTOR - 7 | C80: Air | D80: Fastbrake | E80: 1 | H80: 88.371988 | I80: 110.65864 | J80: 110.65864 | K80: 455.99946 | L80: 570.99857 | M80: 455.99946 | O80: PAC (Brazil BRL) | P80: Calculated with TP (17.2%) + International Freight (15%) + Import Duty (16%) + Domestic Freight (3%) | Qtd=3.0 | R80: Connector/Plug | S80: Already nationalized (PAC) | T80: 598.30249 | U80: 570.99857 | V80: PAC/National is cheaper (by R$ 27.30) | W80: 0.068 | X80: 85369090 | Y80: 4x2x3 | Z80: Exact PN match in item catalog (41A216641P141) | AA80: High
A81: 41A212414P35 | B81: CIRCUIT BREAKER 1P | C81: SKID Assembly | D81: SKID (Skid) | E81: 6 | H81: 87.928279 | I81: 18.350505 | J81: 110.10303 | K81: 453.70992 | L81: 568.13163 | M81: 75.61832 | O81: PAC (Brazil BRL) | P81: Calculated with TP (17.2%) + International Freight (15%) + Import Duty (16%) + Domestic Freight (3%) | Qtd=3.0 | R81: Breaker | S81: Already nationalized (PAC) | T81: 603.56096 | U81: 568.13163 | V81: PAC/National is cheaper (by R$ 35.43) | W81: 0.095 | X81: 85362000 | Y81: 3.1x0.7x2.45 | Z81: Exact PN match in item catalog (41A212414P35) | AA81: High
A82: 41A212414P73 | B82: BATT CHARGER & COMP CIRCUIT BREAKER (2P, 20A / 50A) | C82: Controls (MCA, train control, er etc) | D82: Circuit Breaker | E82: 1 | H82: 85.986164 | I82: 107.67113 | J82: 107.67113 | K82: 443.6886 | L82: 555.58303 | M82: 443.6886 | O82: PAC (Brazil BRL) | P82: Calculated with TP (17.2%) + International Freight (15%) + Import Duty (16%) + Domestic Freight (3%) | Qtd=3.0 | R82: Breaker | S82: Already nationalized (PAC) | T82: 552.47525 | U82: 555.58303 | V82: Import is cheaper (by R$ 3.11) | W82: 0.39 | X82: 85362000 | Y82: 3x2x2.55 | Z82: Exact PN match in item catalog (41A212414P73) | AA82: High
A83: 41A212414P76 | B83: FUEL PUMP CIRCUIT BREAKER (4P, 25A / 45A) | C83: Controls (MCA, train control, er etc) | D83: Circuit Breaker | E83: 1 | H83: 82.77345 | I83: 103.6482 | J83: 103.6482 | K83: 427.111 | L83: 534.8247 | M83: 427.111 | O83: PAC (Brazil BRL) | P83: Calculated with TP (17.2%) + International Freight (15%) + Import Duty (16%) + Domestic Freight (3%) | Qtd=3.0 | R83: Breaker | S83: Already nationalized (PAC) | T83: 643.03503 | U83: 534.8247 | V83: PAC/National is cheaper (by R$ 108.21) | W83: 0.386 | X83: 85362000 | Y83: 2.9x2.45x3.05 | Z83: Exact PN match in item catalog (41A212414P76) | AA83: High
A84: 41A296326DDP52 | B84: EMU CONNECTOR | C84: Controls (MCA, train control, er etc) | D84: Wiring | E84: 1 | H84: 79.8362 | I84: 99.970198 | J84: 99.970198 | K84: 411.95479 | L84: 515.84622 | M84: 411.95479 | O84: PAC (Brazil BRL) | P84: Brazilian factory PAC price (local Brazilian cost) | R84: Connector/Plug | S84: Already nationalized (PAC) | T84: 582.40181 | U84: 515.84622 | V84: PAC/National is cheaper (by R$ 66.56) | W84: 0.113 | X84: 85359090 | Z84: Exact PN match in item catalog (41A296326DDP52) | AA84: High
A85: 84B523158P1 | B85: RESERVOIR DRAIN VALVE HEATER # 1 | C85: Controls (MCA, train control, er etc) | D85: TRAIN CONTROL | E85: 1 | H85: 77.094338 | I85: 96.536861 | J85: 96.536861 | K85: 397.80678 | L85: 498.13021 | M85: 397.80678 | O85: PAC (Brazil BRL) | P85: Brazilian factory PAC price (local Brazilian cost) | W85: 0.272 | X85: 85168090 | Y85: 9x1.5x9 | Z85: Exact PN match in item catalog (84B523158P1) | AA85: High
A86: 41A216641P142 | B86: Part NumberEUMATIC OPERATING UNIT CONNECTOR - 8 | C86: Air | D86: Fastbrake | E86: 1 | H86: 74.912105 | I86: 93.804289 | J86: 93.804289 | K86: 386.54646 | L86: 484.03013 | M86: 386.54646 | O86: PAC (Brazil BRL) | P86: Brazilian factory PAC price (local Brazilian cost) | R86: Connector/Plug | S86: Already nationalized (PAC) | T86: 534.28755 | U86: 484.03013 | V86: PAC/National is cheaper (by R$ 50.26) | W86: 0.054 | X86: 85369090 | Y86: 4x1x4 | Z86: Exact PN match in item catalog (41A216641P142) | AA86: High
A87: 41A216641AMP98 | B87: NIO1A CONNECTOR | C87: Controls (MCA, train control, er etc) | D87: Wiring | E87: 3 | F87: 15.455 | H87: 74.663945 | I87: 31.164515 | J87: 93.493544 | K87: 385.26595 | L87: 482.42669 | O87: Imported BOM (USA) | P87: Brazilian factory PAC price (local Brazilian cost) | R87: Connector/Plug | S87: Medium confidence PAC match (same PN family - AMP84 plug) | T87: 482.42669 | U87: 427.83384 | V87: PAC/National is cheaper (by R$ 54.59) | W87: 0.053 | Y87: 0x0x0 | Z87: Exact PN match in item catalog (41A216641AMP98) | AA87: High
A88: 41A216641ABP153 | B88: HELPER'S RADIO SPEAKER CONNECTOR | C88: Controls (MCA, train control, er etc) | D88: Wiring | E88: 1 | F88: 45.7356 | H88: 73.650389 | I88: 92.224379 | J88: 92.224379 | K88: 380.03601 | L88: 475.8778 | O88: Imported BOM (USA) | P88: Brazilian factory PAC price (local Brazilian cost) | R88: Connector/Plug | S88: Low confidence - generic family match only | T88: 475.8778 | U88: 333.06385 | V88: PAC/National is cheaper (by R$ 142.81)
A89: 17LV66BD52 | B89: CONSIST MANAGER SYSTEM RELAY | C89: Controls (MCA, train control, er etc) | D89: TRAIN CONTROL | E89: 1 | H89: 73.009239 | I89: 91.421537 | J89: 91.421537 | K89: 376.72768 | L89: 471.73513 | M89: 376.72768 | O89: PAC (Brazil BRL) | P89: Brazilian factory PAC price (local Brazilian cost) | W89: 2.313 | X89: 85364900 | Y89: 4.5x5.25x4.5 | Z89: Exact PN match in item catalog (17LV66BD52) | AA89: High
A90: 17LV66J10 | B90: RELAYS | C90: Controls (MCA, train control, er etc) | D90: TRAIN CONTROL | E90: 1 | H90: 69.554429 | I90: 87.095454 | J90: 87.095454 | K90: 358.90086 | L90: 449.41254 | M90: 358.90086 | O90: PAC (Brazil BRL) | P90: Brazilian factory PAC price (local Brazilian cost) | W90: 2.155 | X90: 85364900 | Y90: 5.8x3.5x4.5 | Z90: Exact PN match in item catalog (17LV66J10) | AA90: High
A91: 41A296326DDP78 | B91: GEW LAYER 3 ETH ERNET SWITCH POWER PLUG | C91: Controls (MCA, train control, er etc) | D91: MCA | E91: 1 | H91: 64.940826 | I91: 81.318339 | J91: 81.318339 | K91: 335.09466 | L91: 419.60263 | M91: 335.09466 | O91: PAC (Brazil BRL) | P91: Brazilian factory PAC price (local Brazilian cost) | R91: Connector/Plug | S91: Already nationalized (PAC) | T91: 621.26344 | U91: 419.60263 | V91: PAC/National is cheaper (by R$ 201.66) | W91: 0.045 | X91: 85366990 | Y91: 3x1x2 | Z91: Exact PN match in item catalog (41A296326DDP78) | AA91: High
A92: 41A265714P22 | B92: SOCKET CONTACT, .75" | C92: Controls (MCA, train control, er etc) | D92: Wiring | E92: 109 | H92: 59.410357 | I92: 0.68250582 | J92: 74.393135 | K92: 306.55744 | L92: 383.86857 | M92: 2.8124536 | O92: PAC (Brazil BRL) | P92: Calculated with TP (17.2%) + International Freight (15%) + Import Duty (16%) + Domestic Freight (3%) | Qtd=3.0 | R92: Connector/Plug | S92: Already nationalized (PAC) | T92: 362.69477 | U92: 383.86857 | V92: Import is cheaper (by R$ 21.17) | W92: 0 | X92: 85369090 | Y92: 0.75x0.1x0.1 | Z92: Exact PN match in item catalog (41A265714P22) | AA92: High
A93: 41A216641ABP139 | B93: DISTRIBUTED POWER RADIO MODULE BASE CONNECTOR | C93: Controls (MCA, train control, er etc) | D93: Wiring | E93: 1 | H93: 54.7298 | I93: 68.532181 | J93: 68.532181 | K93: 282.40577 | L93: 353.62605 | M93: 282.40577 | O93: PAC (Brazil BRL) | P93: Brazilian factory PAC price (local Brazilian cost) | R93: Connector/Plug | S93: Already nationalized (PAC) | T93: 360.48467 | U93: 353.62605 | V93: PAC/National is cheaper (by R$ 6.86) | W93: 0.066 | X93: 85366990 | Y93: 2.5x1.25x1.25 | Z93: Exact PN match in item catalog (41A216641ABP139) | AA93: High
A94: 84B104674ASP14 | B94: AMBIENT AIR TEMPERATURE SENSOR PLUG | C94: Controls (MCA, train control, er etc) | D94: MCA | E94: 1 | H94: 50.927567 | I94: 63.771058 | J94: 63.771058 | K94: 262.78624 | L94: 329.05866 | M94: 262.78624 | O94: PAC (Brazil BRL) | P94: Brazilian factory PAC price (local Brazilian cost) | R94: Connector/Plug | S94: Already nationalized (PAC) | T94: 337.85212 | U94: 329.05866 | V94: PAC/National is cheaper (by R$ 8.79) | W94: 0.027 | X94: 85366990 | Y94: 3.5x2x3.25 | Z94: Exact PN match in item catalog (84B104674ASP14) | AA94: High
A95: 41A316591P1 | B95: Card Holder 3 Slot | C95: Controls (MCA, train control, er etc) | D95: TRAIN CONTROL | E95: 1 | H95: 38.450979 | I95: 48.147982 | J95: 48.147982 | K95: 198.40705 | L95: 248.44359 | M95: 198.40705 | O95: PAC (Brazil BRL) | P95: Brazilian factory PAC price (local Brazilian cost) | W95: 1.315 | X95: 39269090 | Y95: 17x1.25x12.625 | Z95: Exact PN match in item catalog (41A316591P1) | AA95: High
A96: 41A212414P31, 41A212414P3 2-Pole Option | B96: AUTOCOUPLER CIRCUIT BREAKER, CCB(2A) | C96: Controls (MCA, train control, er etc) | D96: Circuit Breaker | E96: 1 | F96: 22.0206 | H96: 35.460905 | I96: 44.403838 | J96: 44.403838 | K96: 182.97827 | L96: 229.1238 | O96: Imported BOM (USA) | P96: Brazilian factory PAC price (local Brazilian cost) | R96: Breaker | S96: High confidence PAC match (exact PN) - not yet applied | T96: 229.1238 | U96: 94.303963 | V96: PAC/National is cheaper (by R$ 134.82) | W96: 0.093 | X96: 85362000 | Y96: 2.5x0.65x3.05 | Z96: Exact PN match in item catalog (41A212414P31) | AA96: High
A97: 41A265713P22 | B97: PIN | C97: Controls (MCA, train control, er etc) | D97: Wiring | E97: 82 | H97: 33.234893 | I97: 0.50751763 | J97: 41.616446 | K97: 171.49205 | L97: 214.74086 | M97: 2.0913665 | O97: PAC (Brazil BRL) | P97: Calculated with TP (17.2%) + International Freight (15%) + Import Duty (16%) + Domestic Freight (3%) | Qtd=1.0 | W97: 0 | X97: 85389090 | Y97: 1x0.001x0.001 | Z97: Exact PN match in item catalog (41A265713P22) | AA97: High
A98: 41A212414P3 | B98: DYNAMIC BRAKE CIRCUIT BREAKER (1P, 2A) | C98: Controls (MCA, train control, er etc) | D98: Circuit Breaker | E98: 1 | H98: 29.821879 | I98: 37.342698 | J98: 37.342698 | K98: 153.88089 | L98: 192.68832 | M98: 153.88089 | O98: PAC (Brazil BRL) | P98: Brazilian factory PAC price (local Brazilian cost) | R98: Breaker | S98: Already nationalized (PAC) | T98: 189.09308 | U98: 192.68832 | V98: Import is cheaper (by R$ 3.60) | W98: 0.193 | X98: 85362000 | Y98: 3.1x1.45x2.5 | Z98: Exact PN match in item catalog (41A212414P3) | AA98: High
A99: 41A212414P14 | B99: PTC RADIO CIRCUIT BREAKER (2P, 15A) | C99: Controls (MCA, train control, er etc) | D99: Circuit Breaker | E99: 1 | H99: 29.793742 | I99: 37.307466 | J99: 37.307466 | K99: 153.73571 | L99: 192.50652 | M99: 153.73571 | O99: PAC (Brazil BRL) | P99: Brazilian factory PAC price (local Brazilian cost) | R99: Breaker | S99: Already nationalized (PAC) | T99: 188.95797 | U99: 192.50652 | V99: Import is cheaper (by R$ 3.55) | W99: 0.195 | X99: 85362000 | Y99: 2.5x1.5x3.25 | Z99: Exact PN match in item catalog (41A212414P14) | AA99: High
A100: 41A212414P15 | B100: SMART DISPLAY #1 CIRCUIT BREAKER (2P, 6A) | C100: Controls (MCA, train control, er etc) | D100: Circuit Breaker | E100: 1 | H100: 29.532314 | I100: 36.980108 | J100: 36.980108 | K100: 152.38674 | L100: 190.81736 | M100: 152.38674 | O100: PAC (Brazil BRL) | P100: Brazilian factory PAC price (local Brazilian cost) | R100: Breaker | S100: Already nationalized (PAC) | T100: 192.06454 | U100: 190.81736 | V100: PAC/National is cheaper (by R$ 1.25) | W100: 0.2 | X100: 85362000 | Y100: 2.5x1.5x2.5 | Z100: Exact PN match in item catalog (41A212414P15) | AA100: High
...

Sheet GDT Integration and Assembly
A1: GDT Category | B1: Item / Service or Material Description | C1: Direct Cost BRL | D1: Direct Cost USD (@ 5.16) | E1: Gross Price BRL (Including PIS/COFINS and ICMS) | F1: Gross Price USD (Including PIS/COFINS and ICMS) | G1: Notes / Calculation Details
A2: Integration / Container Materials | B2: Container + enviromental Report | C2: 70000 | D2: 13565.891 | E2: 87653.393 | F2: 16987.092 | G2: Não incluso transporte do container
A3: Integration / Container Materials | B3: Pneumatics (tubulações, 14un mangueiras, 30un torneiras, conexões) | C3: 25000 | D3: 4844.9612 | E3: 31304.783 | F3: 6066.8185 | G3: Conexões pneumáticas gerais
A4: Integration / Container Materials | B4: Rack Electrical Connection | C4: 25000 | D4: 4844.9612 | E4: 31304.783 | F4: 6066.8185 | G4: Chicotes e passagem de cabos
A5: Integration / Container Materials | B5: Internal Electrical System (cabeamento, iluminação interna, 4un strobe, 6un steplights) | C5: 5000 | D5: 968.99225 | E5: 6260.9567 | F5: 1213.3637 | G5: Horn and headlight not needed
A6: Integration / Container Materials | B6: MU Connectors (4un), MU Jumpers (2un) | C6: 60000 | D6: 11627.907 | E6: 75131.48 | F6: 14560.364 | G6: Considerando eletrodutos e alongamento de cabeamento do container ao vagão
A7: Integration / Container Materials | B7: Air Conditioning, Inverter and Power | C7: 100000 | D7: 19379.845 | E7: 125219.13 | F7: 24267.274 | G7: Ar condicionado, inversor e potência para troca de calor
A8: Integration / Container Materials | B8: Container Thermal Insulation | C8: 100000 | D8: 19379.845 | E8: 125219.13 | F8: 24267.274 | G8: Isolamento térmico interno
A9: Integration / Container Materials | B9: Steel (railcar repair, ladder and access door) | C9: 12500 | D9: 2422.4806 | E9: 15652.392 | F9: 3033.4092 | G9: 25 reais por quilo
A10: Integration / Container Materials | B10: Painting and Lettering (Lettering) | C10: 5000 | D10: 968.99225 | E10: 6260.9567 | F10: 1213.3637 | G10: Não considerando pintar o vagão inteiro
A11: Integration / Container Materials | B11: Miscellaneous | C11: 10000 | D11: 1937.9845 | E11: 12521.913 | F11: 2426.7274 | G11: Insumos e materiais diversos
A12: Labor and Field Services | B12: Assembly and Integration Labor (Labor Cost) | C12: 122752 | D12: 23789.147 | E12: 153708.99 | F12: 29788.564 | G12: 1.096 horas (mecânica, elétrica, solda, pintura e campo) @ R$ 112/h
A13: Labor and Field Services | B13: Engineering / Project Design (NRE) | C13: 39424 | D13: 7640.3101 | E13: 49366.391 | F13: 9567.1301 | G13: 1 engenheiro + 1 projetista durante 1 mês
... A19: TOTAL GDT ROLLUP | B19: Total Integration, Adaptation and Services | C19: 707790.6 | D19: 137168.72 | E19: 886289.26 | F19: 171761.48 | G19: Sum of all additional materials and services from the rollup

Sheet Missing Items
A1: Part Number | B1: Description | C1: System | D1: Subsystem | E1: Status / Notes
A2: 41A296326CYP77 | B2: M12-A_ MALE_ 8-PIN_ STRAIGHT BSH | C2: SKID Assembly | D2: SKID (Skid) | E2: Quotation pending (no USD or BRL price)
A3: 41A296352PTP272 | B3: BC-PRECISION NAVIGATION MODULE | C3: SKID Assembly | D3: SKID (Skid) | E3: Quotation pending (no USD or BRL price)
A4: 41A296352PTP58 | B4: AY-DISPLAY CSX PTC DISPLAY | C4: SKID Assembly | D4: SKID (Skid) | E4: Quotation pending (no USD or BRL price)
A5: 41A296352PTP292 | B5: AX-POWER SUPPLY 13.6 V | C5: SKID Assembly | D5: SKID (Skid) | E5: Quotation pending (no USD or BRL price)
A6: MODEM ATT | B6: MODEM ATT | C6: SKID Assembly | D6: SKID (Skid) | E6: Quotation pending (no USD or BRL price)
A7: 84A237085AJP1 | B7: C-GoLIN EP_3 SMA_M2 CELL MODEM | C7: SKID Assembly | D7: Controls (MCA, train control, er etc) | E7: Quotation pending (no USD or BRL price)
A8: 17FL400B | B8: ST-DEVELOPER v19.4 | C8: SKID Assembly | D8: SKID (Skid) | E8: Quotation pending (no USD or BRL price)
A9: 41A296352CMP448 | B9: FB-DIGITAL RADIO MODULE | C9: SKID Assembly | D9: SKID (Skid) | E9: Quotation pending (no USD or BRL price)
A10: 41A296352PTP326 | B10: BH-WABTEC TRAIN MANAGEMENT COMPUTER _WTMC_ | C10: SKID Assembly | D10: SKID (Skid) | E10: Quotation pending (no USD or BRL price)
A11: 17FM711C3 | B11: H-PANEL DBM | C11: SKID Assembly | D11: SKID (Skid) | E11: Quotation pending (no USD or BRL price)
A12: 41A296352BCP9 | B12: N-HEAD OF TRAIN DEVICE | C12: SKID Assembly | D12: SKID (Skid) | E12: Quotation pending (no USD or BRL price)
... A22: PTC-FILT-NB-220-MIL-MF | B22: 220 Mhz PTC FILTER | C22: SKID Assembly | D22: later | E22: Quotation pending (no USD or BRL price)
B23: PTC Junction Box | C23: SKID Assembly | D23: SKID (Skid) | E23: Quotation pending (no USD or BRL price)
A24: 41A296352LUP15 | B24: 455 MHz Antenna (DPA, DPB, EOT ) | C24: SKID Assembly | D24: SKID (Skid) | E24: Quotation pending (no USD or BRL price)
A25: 84D749224G1 | B25: Power resistor | C25: SKID Assembly | D25: Battery Skid? | E25: Quotation pending (no USD or BRL price)

Sheet Freight Handoff
A1: US raw-cost freight handoff, sorted by US Total Cost (highest to lowest). Yellow = TP already included in source cost (rate not specified); Green = direct supplier, no TP; Blue = GET / TP to be confirmed; Uncolored = no TP status specified in the color review. PAC-sourced items are excluded.
A2: Part Number | B2: Description | C2: System | D2: SubSystem | E2: Quantity | F2: US Unit Cost (USD, no markup) | G2: US Total Cost (USD, no markup) | H2: Unit Weight (kg) | I2: Total Weight (kg) | J2: Dimensions (C x A x L, in) | K2: NCM | L2: Weight Confidence | M2: Notes | N2: Transfer Price Status
A3: 41A296352CMP437 | B3: Dual Processor Module (DPM)+ LXA (Distributed Power Radio) | C3: Controls (MCA, train control, er etc) | D3: LXA | E3: 1 | F3: 63100.819 | G3: 63100.819 | H3: 4.536 | I3: 4.536 | K3: 90328990 | L3: High | N3: Included in source cost (rate not specified)
A4: 84A222059P5 | B4: BATTERIES | C4: Power | D4: POWER | E4: 2 | F4: 15685.42 | G4: 31370.84 | H4: 1123.095 | I4: 2246.19 | L4: High | N4: Not applicable - direct supplier purchase
A5: 41A296352LUG24 | B5: CSX Antenna Enclosure Arrangement | C5: Connectivity | D5: ANTENNA KIT Master | E5: 1 | F5: 30000 | G5: 30000 | H5: 136.078 | I5: 136.078 | L5: High | N5: Not applicable - direct supplier purchase
A6: 37495P | B6: KIT ETMS VIRGIN TRAINS FEC EVO44 | C6: PTC | D6: PTC KIT MASTER | E6: 1 | F6: 28529 | G6: 28529 | H6: 45.359 | I6: 45.359 | L6: High | N6: Included in source cost (rate not specified)
A7: 84A215295P62 | B7: Pneumatic Brake Control System (Including lament and control portions) Includes EM EAB Control Functionality | C7: Air | D7: Fastbrake | E7: 1 | F7: 23409.1 | G7: 23409.1 | H7: 134.263 | I7: 134.263 | L7: High | N7: Included in source cost (rate not specified)
A8: 41A296352DNP37 | B8: RADIO PRAD PTC RADIO | C8: PTC | D8: PTC | E8: 1 | F8: 20000 | G8: 20000 | H8: 9.616 | I8: 9.616 | L8: High | N8: Not applicable - direct supplier purchase
A9: 17FM878A6 | B9: NIO 2.0 | C9: Controls (MCA, train control, er etc) | D9: MCA | E9: 3 | F9: 5176.9118 | G9: 15530.735 | H9: 8.618 | I9: 25.854 | L9: High | N9: Not applicable - direct supplier purchase
A10: L7000083-900 | B10: Wireless Communications Management Module, Gen 3 (WCM3)​ | C10: Controls (MCA, train control, er etc) | D10: TRAIN CONTROL | E10: 2 | F10: 5000 | G10: 10000 | H10: 2.268 | I10: 4.536 | L10: High | N10: Included in source cost (rate not specified)
A11: 84A237085AEP121 | B11: 8 Slot ACC Chassis for MCA w/ i7 HPEAP and SMM2 Cards | C11: Controls (MCA, train control, er etc) | D11: TRAIN CONTROL | E11: 1 | F11: 8000 | G11: 8000 | H11: 9.072 | I11: 9.072 | L11: High | N11: Included in source cost (rate not specified)
A12: 17KC108E28 | B12: MASTER CONTROLLER | C12: Controls (MCA, train control, er etc) | D12: TRAIN CONTROL | E12: 1 | F12: 5877.102 | G12: 5877.102 | H12: 25.855 | I12: 25.855 | L12: High | N12: GET / transfer price to be confirmed
A13: 84A215295P73 | B13: Air Brake Handle Assembly (AAR Console) | C13: Air | D13: Fastbrake | E13: 1 | F13: 5702.83 | G13: 5702.83 | H13: 7.938 | I13: 7.938 | L13: High | N13: Included in source cost (rate not specified)
A14: 17FM868B2 | B14: SNIO | C14: Controls (MCA, train control, er etc) | D14: MCA | E14: 1 | F14: 4150.9559 | G14: 4150.9559 | H14: 4.99 | I14: 4.99 | L14: High | N14: Not applicable - direct supplier purchase
A15: 41A296352DNP55 | B15: VOICE RADIO RITRON | C15: Connectivity | D15: VOICE RADIO | E15: 1 | F15: 3933 | G15: 3933 | H15: 7.575 | I15: 7.575 | L15: High | N15: Not applicable - direct supplier purchase
... A17: 41B546155P2 | B17: Horn | C17: Controls (MCA, train control, er etc) | D17: TRAIN CONTROL | E17: 1 | F17: 1891.99 | G17: 1891.99 | H17: 4.536 | I17: 4.536 | L17: High | N17: Not applicable - direct supplier purchase
B18: Ditchlight Control Box (SMART BOX-V3-DLC ) | C18: Controls (MCA, train control, er etc) | D18: TRAIN CONTROL | E18: 2 | F18: 800 | G18: 1600 | H18: 2.268 | I18: 4.536 | L18: High | N18: Not specified in color review
A19: 41D758679BJG16 84D704379AFG1 | B19: EC Part NumberL ASM | C19: Power | D19: Circuit Breaker | E19: 1 | F19: 1572.36 | G19: 1572.36 | H19: 4.99 | I19: 4.99 | J19: 20x3.5x25.5 | K19: 86079100 | L19: High | N19: GET / transfer price to be confirmed
B20: LED Ditch Light | C20: Controls (MCA, train control, er etc) | D20: TRAIN CONTROL | E20: 4 | F20: 375 | G20: 1500 | H20: 0.907 | I20: 3.628 | L20: High | N20: Not specified in color review
A21: 84A215295P3 | B21: POU-to-Handle cable 18' length | C21: Air | D21: Fastbrake | E21: 1 | F21: 1036.89 | G21: 1036.89 | H21: 1.247 | I21: 1.247 | L21: Medium | M21: Weight is an estimate (similar item) | N21: Included in source cost (rate not specified)
A22: RCCR-RMTCBL-RA-CUSTOM | B22: VOICE RADIO RITRON CABLE,REMOTE,RR-225/XXX, RCCR,RIGHT ANGLE,19-PIN,FLAME RETARDANT | C22: Connectivity | D22: VOICE RADIO | E22: 1 | F22: 761 | G22: 761 | M22: Weight not found - needs supplier data | N22: Not applicable - direct supplier purchase
A23: 41A296352PTP306/41A296352PTP122 | B23: Assembled Air Manifold (Contains 3 pressure sensors mounted in appropriate locations on Air Manifold.) | C23: PTC | D23: PTC | E23: 1 | F23: 595.7889 | G23: 595.7889 | H23: 5.897 | I23: 5.897 | K23: 85381000 | L23: Medium | M23: Weight is an estimate (similar item) | N23: Included in source cost (rate not specified)
A24: 32447P | B24: ASY CABLE WHEEL TACH AC EVO/SD70 ACE | C24: PTC | D24: PTC | E24: 1 | F24: 411.22 | G24: 411.22 | M24: Weight not found - needs supplier data | N24: Included in source cost (rate not specified)
A25: 41A296352PTP10/319/34 | B25: VALVE Part NumberEUMATIC NC/CO (Penalty Magnet Valve) Graham-White 812-142 | C25: PTC | D25: PTC | E25: 1 | F25: 404.6239 | G25: 404.6239 | M25: Weight not found - needs supplier data | N25: Included in source cost (rate not specified)
A26: 84A231123CSP30 | B26: Axle Tac - WRE Part Number: 29266P | C26: PTC | D26: PTC | E26: 1 | F26: 205 | G26: 205 | M26: Weight not found - needs supplier data | N26: Not specified in color review
A27: 84A207079ABP1 | B27: 41A313392DCP18 alternative 300" / | C27: Controls (MCA, train control, er etc) | D27: Wiring | E27: 25 | F27: 8.118 | G27: 202.95 | H27: 0.227 | I27: 5.675 | J27: 24x20x24 | K27: 85446000 | L27: High | N27: Not specified in color review
A28: 84A201850P4 | B28: ENGINE CONTROL SWITCH | C28: Controls (MCA, train control, er etc) | D28: TRAIN CONTROL | E28: 1 | F28: 171.544 | G28: 171.544 | M28: Weight not found - needs supplier data | N28: Not specified in color review
A29: RCCR-PWRCBL | B29: CABLE, PWR, 72V,RA,6.5FT (78").,RR-070,RCCR | C29: Connectivity | D29: VOICE RADIO | E29: 1 | F29: 159 | G29: 159 | M29: Weight not found - needs supplier data | N29: Not specified in color review
A30: 41A216641AMP126 | B30: NIO1D CONNECTOR BACKSHELL | C30: Controls (MCA, train control, er etc) | D30: Wiring | E30: 3 | F30: 29.9096 | G30: 89.7288 | H30: 0 | I30: 0 | J30: 0x0x0 | L30: High | N30: Not specified in color review
A31: 17 pin MS3106-20-29F | B31: Head of Train Device - Padom - J2 Connector | C31: Controls (MCA, train control, er etc) | D31: Wiring | E31: 1 | F31: 79.83 | G31: 79.83 | M31: Weight not found - needs supplier data | N31: Not specified in color review
A32: 41A216641AMP125 | B32: NIO1A CONNECTOR BACKSHELL | C32: Controls (MCA, train control, er etc) | D32: Wiring | E32: 3 | F32: 24.1998 | G32: 72.5994 | H32: 0.005 | I32: 0.015 | J32: 0x0x0 | L32: High | N32: Not specified in color review
A33: 5088-7000-P4611-0000000-ND‎ | B33: POE Power Connector on SMM2 (M12 FEMALE 0 L-CODED FIELD-WIREA) | C33: Controls (MCA, train control, er etc) | D33: TRAIN CONTROL | E33: 1 | F33: 72.41 | G33: 72.41 | M33: Weight not found - needs supplier data | N33: Not specified in color review
A34: 41A296352PTP67 | B34: CABLE CSX 12V P WR CBL | C34: Controls (MCA, train control, er etc) | D34: MCA | E34: 1 | F34: 71.94 | G34: 71.94 | M34: Weight not found - needs supplier data | N34: Not specified in color review
A35: 41A296352PTP69 | B35: CABLE CSX 74V P WR CBL | C35: Controls (MCA, train control, er etc) | D35: MCA | E35: 1 | F35: 71.94 | G35: 71.94 | M35: Weight not found - needs supplier data | N35: Not specified in color review
A36: 41A216641AMP93 | B36: NIO1E CONNECTOR | C36: Controls (MCA, train control, er etc) | D36: Wiring | E36: 3 | F36: 23.9499 | G36: 71.8497 | H36: 0.054 | I36: 0.162 | J36: 0x0x0 | L36: High | N36: Not specified in color review
A37: 41A216641AMP103 | B37: NIO1D CONNECTOR | C37: Controls (MCA, train control, er etc) | D37: Wiring | E37: 3 | F37: 21.2198 | G37: 63.6594 | H37: 0.045 | I37: 0.135 | J37: 1.5x1x1.5 | L37: High | N37: Not specified in color review
A38: 16246P | B38: Flexi-Axle - WRE Part Number: 16246P | C38: PTC | D38: PTC | E38: 1 | F38: 59.75 | G38: 59.75 | M38: Weight not found - needs supplier data | N38: Not specified in color review
A39: 41A216641AMP99 | B39: NIO1B CONNECTOR | C39: Controls (MCA, train control, er etc) | D39: Wiring | E39: 3 | F39: 19.67 | G39: 59.01 | H39: 0 | I39: 0 | J39: 0x0x0 | L39: High | N39: Not specified in color review
A40: 41A216641AMP123 | B40: NIO1F CONNECTOR BACKSHELL | C40: Controls (MCA, train control, er etc) | D40: Wiring | E40: 3 | F40: 19.5574 | G40: 58.6722 | H40: 0.02 | I40: 0.06 | J40: 0x0x0 | L40: High | N40: Not specified in color review
A41: 41A216641AMP100 | B41: NIO1C CONNECTOR | C41: Controls (MCA, train control, er etc) | D41: Wiring | E41: 3 | F41: 19.173 | G41: 57.519 | H41: 0 | I41: 0 | J41: 0x0x0 | L41: High | N41: Not specified in color review
A42: 41A216641AMP86 | B42: NIO1F CONNECTOR | C42: Controls (MCA, train control, er etc) | D42: Wiring | E42: 3 | F42: 18.9357 | G42: 56.8071 | H42: 0.032 | I42: 0.096 | J42: 3.95x1.25x6.65 | L42: High | N42: Not specified in color review
A43: 41A216641AMP98 | B43: NIO1A CONNECTOR | C43: Controls (MCA, train control, er etc) | D43: Wiring | E43: 3 | F43: 15.455 | G43: 46.365 | H43: 0.053 | I43: 0.159 | J43: 0x0x0 | L43: High | N43: Not specified in color review
A44: 41A216641ABP153 | B44: HELPER'S RADIO SPEAKER CONNECTOR | C44: Controls (MCA, train control, er etc) | D44: Wiring | E44: 1 | F44: 45.7356 | G44: 45.7356 | M44: Weight not found - needs supplier data | N44: Not specified in color review
A45: 41A212414P31, 41A212414P3 2-Pole Option | B45: AUTOCOUPLER CIRCUIT BREAKER, CCB(2A) | C45: Controls (MCA, train control, er etc) | D45: Circuit Breaker | E45: 1 | F45: 22.0206 | G45: 22.0206 | H45: 0.093 | I45: 0.093 | J45: 2.5x0.65x3.05 | K45: 85362000 | L45: High | N45: Not specified in color review
A46: 5373-219 | B46: CONNECTOR, ELECTRICAL | C46: Controls (MCA, train control, er etc) | D46: Wiring | E46: 1 | F46: 13.66 | G46: 13.66 | M46: Weight not found - needs supplier data | N46: Not specified in color review
A47: 41A271471P24/38 | B47: HPEAP DISCRETE CONNECTOR Backshell | C47: Controls (MCA, train control, er etc) | D47: Wiring | E47: 1 | F47: 1.9294 | G47: 1.9294 | H47: 0.023 | I47: 0.023 | J47: 5.1x1.15x2.95 | K47: 85366990 | L47: High | N47: Not specified in color review
A48: 41A296352DNP73 | B48: CABLE: GROUND S TRAP | C48: Controls (MCA, train control, er etc) | D48: MCA | E48: 1 | F48: 0.01 | G48: 0.01 | M48: Weight not found - needs supplier data | N48: Not specified in color review
A49: 41A296352DNP96 | B49: Cable: CRM Ethernet Switch to ACC | C49: Controls (MCA, train control, er etc) | D49: MCA | E49: 1 | F49: 0.01 | G49: 0.01 | M49: Weight not found - needs supplier data | N49: Not specified in color review
A50: 41B566322ACG1 | B50: TRAINLINE RESISTOR PANEL | C50: SKID Assembly | D50: Controls (MCA, train control, er etc) | E50: 1 | H50: 2.859 | I50: 2.859 | J50: 14x6x8.5 | K50: 85333990 | L50: High | M50: No US cost yet - price pending | N50: GET / transfer price to be confirmed
A51: 41C663693G1 | B51: PANEL CPF | C51: Power | D51: POWER | E51: 1 | H51: 5.761 | I51: 5.761 | J51: 20.5x10.5x11.5 | K51: 85371090 | L51: High | M51: No US cost yet - price pending | N51: GET / transfer price to be confirmed
A52: 41A296352DNP57 | B52: REMOTE HEAD - VOICE RADIO RITRON | C52: Connectivity | D52: VOICE RADIO | E52: 1 | M52: No US cost yet - price pending; Weight not found - needs supplier data | N52: Not specified in color review
A53: 41A296326CYP77 | B53: M12-A_ MALE_ 8-PIN_ STRAIGHT BSH | C53: SKID Assembly | D53: SKID (Skid) | E53: 16 | M53: No US cost yet - price pending; Weight not found - needs supplier data | N53: Not specified in color review
A54: 41A296352PTP272 | B54: BC-PRECISION NAVIGATION MODULE | C54: SKID Assembly | D54: SKID (Skid) | E54: 2 | M54: No US cost yet - price pending; Weight not found - needs supplier data | N54: Not specified in color review
A55: 41A296352PTP58 | B55: AY-DISPLAY CSX PTC DISPLAY | C55: SKID Assembly | D55: SKID (Skid) | E55: 1 | M55: No US cost yet - price pending; Weight not found - needs supplier data | N55: Not specified in color review
A56: 41A296352PTP292 | B56: AX-POWER SUPPLY 13.6 V | C56: SKID Assembly | D56: SKID (Skid) | E56: 1 | M56: No US cost yet - price pending; Weight not found - needs supplier data | N56: Not specified in color review
A57: MODEM ATT | B57: MODEM ATT | C57: SKID Assembly | D57: SKID (Skid) | E57: 3 | M57: No US cost yet - price pending; Weight not found - needs supplier data | N57: Not specified in color review
A58: 84A237085AJP1 | B58: C-GoLIN EP_3 SMA_M2 CELL MODEM | C58: SKID Assembly | D58: Controls (MCA, train control, er etc) | E58: 1 | M58: No US cost yet - price pending; Weight not found - needs supplier data | N58: Not specified in color review
A59: 17FL400B | B59: ST-DEVELOPER v19.4 | C59: SKID Assembly | D59: SKID (Skid) | E59: 1 | M59: No US cost yet - price pending; Weight not found - needs supplier data | N59: Not specified in color review
A60: 41A296352CMP448 | B60: FB-DIGITAL RADIO MODULE | C60: SKID Assembly | D60: SKID (Skid) | E60: 1 | M60: No US cost yet - price pending; Weight not found - needs supplier data | N60: Not specified in color review
A61: 41A296352PTP326 | B61: BH-WABTEC TRAIN MANAGEMENT COMPUTER _WTMC_ | C61: SKID Assembly | D61: SKID (Skid) | E61: 1 | M61: No US cost yet - price pending; Weight not found - needs supplier data | N61: Not specified in color review
A62: 17FM711C3 | B62: H-PANEL DBM | C62: SKID Assembly | D62: SKID (Skid) | E62: 1 | M62: No US cost yet - price pending; Weight not found - needs supplier data | N62: Not specified in color review
A63: 41A296352BCP9 | B63: N-HEAD OF TRAIN DEVICE | C63: SKID Assembly | D63: SKID (Skid) | E63: 1 | M63: No US cost yet - price pending; Weight not found - needs supplier data | N63: Not specified in color review
... A73: PTC-FILT-NB-220-MIL-MF | B73: 220 Mhz PTC FILTER | C73: SKID Assembly | D73: later | E73: 2 | M73: No US cost yet - price pending; Weight not found - needs supplier data | N73: Not specified in color review
B74: PTC Junction Box | C74: SKID Assembly | D74: SKID (Skid) | E74: 1 | M74: No US cost yet - price pending; Weight not found - needs supplier data | N74: Not specified in color review
A75: 41A296352LUP15 | B75: 455 MHz Antenna (DPA, DPB, EOT ) | C75: SKID Assembly | D75: SKID (Skid) | E75: 3 | M75: No US cost yet - price pending; Weight not found - needs supplier data | N75: Not specified in color review
A76: 84D749224G1 | B76: Power resistor | C76: SKID Assembly | D76: Battery Skid? | E76: 1 | M76: No US cost yet - price pending; Weight not found - needs supplier data | N76: Not specified in color review
